Workbook

Sheet Page de couverture
A1: Annexe S2
A2: Outil d’évaluation des capacités de gestion
A3: Version 1 .1
F4: Décharge de responsabilité concernant la traduction
F5: Pour toute question liée à la signification précise des informations contenues dans la traduction, veuillez vous référer à la version officielle en anglais pour en obtenir la clarification. Toute divergence ou différence dans la signification engendrée par la traduction n’est pas contraignante et n’a pas d’effet sur la certification ou les audits.
F9: Plus d'informations ?
F10: Pour en savoir plus sur Rainforest Alliance, veuillez visiter le site www.rainforest-alliance.org ou contacter info@ra.org
F13: Nom du document : | J13: Code du document : | L13: Version :
F14: Annexe S2 : Outil d’évaluation des capacités de gestion | J14: SA-G-SD-3-V1 | L14: 1.1
F15: Date de la première publication : | H15: Date de révision : | J15: Valable à partir du : | L15: Expire le :
F16: 1er juillet 2020 | H16: 31 janvier 2020 | J16: 1er juillet 2020 | L16: Jusqu’à nouvel ordre
F17: Élaboré par : | J17: Approuvé par :
F18: Département Standards and Assurance de Rainforest Alliance | J18: Directeur des Standards and Assurance
F19: Lié à :
F20: SA-S-SD-1-V1.1Norme pour l’agriculture durable 2020 de Rainforest Alliance, Exigences applicables aux exploitations agricoles (1.1.1, 1.1.2, 1.3.2). SA-G-SD-2-V1 Document d’orientation A : Comment utiliser l’outil d’évaluation des capacités de gestion de Rainforest Alliance SA-G-SD-3-V1 Document d’orientation B : Modèle de Plan de gestion
F23: Remplace :
F24: SA-S-SD-3-V1 Annexe 2 : Outil d’évaluation des capacités de gestion
F25: Applicable à :
F26: Exploitations agricoles Titulaires de certificats
F27: Pays/Région :
F28: Tous
F29: Produit agricole : | J29: Type de certification :
A30: © 2021 Rainforest Alliance. Tous droits réservés. | F30: Tous les produits agricoles du champ d’application du système de certification de Rainforest Alliance ; veuillez voir les Règles pour la certification. | J30: Certification d’exploitation agricole
A32: SA-S-SD-3-V1.1
F33: Toute utilisation de ce contenu, y compris la reproduction, la modification, la distribution ou la republication, sans le consentement écrit préalable de Rainforest Alliance, est strictement interdite.

Sheet Infos générales
A1: INFORMATIONS GENERALES DU GROUPE
A3: Nom du groupe
A5: Adresse
A7: Année de création
A10: Type d’organisation | B10: Organisation d’agriculteurs
B11: Groupe dirigé/encadré par un exportateur
B12: Autre (veuillez expliquer)
A14: Nombre de membres : | C14: Total | D14: Femme | E14: Homme
B15: à la création
B16: à présent
A19: Nombre total du personnel : | B19: Fonction | C19: Total | D19: Femme | E19: Homme
B20: Conseiller
B21: Formateur
B22: Inspecteur
B23: Autre
A25: Quand a eu lieu la dernière réunion du conseil ?
A27: Quand a eu lieu la dernière réunion générale des membres ?
A29: Culture(s) agricole(s) certifiée(s)
A31: Dernière vente collective ?
A33: Est-ce que le groupe possède sa propre installation de transformation ?
A35: Est-ce que le groupe possède une installation de stockage des produits ?

Sheet Résumé
A1: RESUME DES RESULTATS
A3: Score : se réfère aux niveaux du cycle Planifier-Réaliser-Vérifier-Agir (PRVA) :
A4: 0 | B4: Pas de PRVA : Manque de documentation (processus et politiques). Pas de structure ou d'organisation formalisée.
A5: 1 | B5: Réactive, mais documentée (PRVA) : La documentation existe avec une structure informelle mettant en œuvre les processus et les politiques. La mise en œuvre a lieu en réaction au système, puisqu’aucune planification n’a été prise en compte quand les politiques et les processus ont été élaborés.
A6: 2 | B6: Proactive (PRVA) : Une structure et de la documentation formelle pour mettre en œuvre les politiques et les processus sont en place, les parties prenantes et les membres du groupe ont été impliqués durant l’élaboration des politiques et des processus. Cependant, après la mise en œuvre, il y a eu un manque d’évaluation et d’apprentissage.
A7: 3 | B7: Amélioration continue (PRVA) : Une structure et de la documentation formelle pour mettre en œuvre les politiques et les processus sont en place. Les parties prenantes et les membres du groupe ont été impliqués durant l’élaboration des politiques et des processus. Après la mise en œuvre, les activités ont été vérifiées, évaluées et suivies pour assurer que l’apprentissage et l’amélioration aient lieu.
A8: Basé sur : NewForesight (2018)
D10: Questions | E10: Catégorie | J10: Moyenne | K10: Score | M10: =IF(K11=1,#REF!,IF(K11=2,#REF!,IF(K11=3,#REF!,#REF!))) -> #REF!
D11: =Organisation!J2 -> 5 | E11: =Organisation!A3 -> A. Structure de gestion et Organisation du groupe | J11: =Organisation!M3 -> 0 | K11: =IF(J11>=0.6, IF(J11>=1.6,IF(J11>=2.6,3,2),1),0) -> 0 | L11: 2.5 | M11: 1.5
D12: ='Gestion stratégique'!J2 -> 5 | E12: ='Gestion stratégique'!A3 -> B. Gestion stratégique | J12: ='Gestion stratégique'!M3 -> #DIV/0! | K12: =IF(J12>=0.6, IF(J12>=1.6,IF(J12>=2.6,3,2),1),0) -> #DIV/0! | L12: 2.5 | M12: 1.5
D13: =Financier!J2 -> 5 | E13: =Financier!A3 -> C. Gestion financière | J13: =Financier!M3 -> #DIV/0! | K13: =IF(J13>=0.6, IF(J13>=1.6,IF(J13>=2.6,3,2),1),0) -> #DIV/0! | L13: 2.5 | M13: 1.5
D14: =Sociétariat!J2 -> 5 | E14: =Sociétariat!A3 -> D. Implication des membres et planification des adhésions | J14: =Sociétariat!M3 -> #DIV/0! | K14: =IF(J14>=0.6, IF(J14>=1.6,IF(J14>=2.6,3,2),1),0) -> #DIV/0! | L14: 2.5 | M14: 1.5
D15: ='Formation et services'!J2 -> 5 | E15: ='Formation et services'!A3 -> E. Formation des membres et mise à disposition de services | J15: ='Formation et services'!M3 -> #DIV/0! | K15: =IF(J15>=0.6, IF(J15>=1.6,IF(J15>=2.6,3,2),1),0) -> #DIV/0! | L15: 2.5 | M15: 1.5
D16: ='Ventes et marketing'!J2 -> 5 | E16: ='Ventes et marketing'!A3 -> F. Ventes et marketing | J16: ='Ventes et marketing'!M3 -> #DIV/0! | K16: =IF(J16>=0.6, IF(J16>=1.6,IF(J16>=2.6,3,2),1),0) -> #DIV/0! | L16: 2.5 | M16: 1.5
D17: =SGI!J2 -> 6 | E17: =SGI!A3 -> G. Système de Gestion Interne | J17: =SGI!M3 -> #DIV/0! | K17: =IF(J17>=0.6, IF(J17>=1.6,IF(J17>=2.6,3,2),1),0) -> #DIV/0! | L17: 2.5 | M17: 1.5

Sheet Organisation
A1: Sujets d’évaluation et Questions | D1: Option 1 | E1: Option 2 | F1: Option 3 | G1: Option 4 | J1: Cette page possède :
J2: =COUNTA(L4:L13) -> 5 | M2: =COUNTIF(L5:L13,0) -> 4
A3: A. Structure de gestion et Organisation du groupe | J3: Documents/preuves de soutien : | K3: Commentaires/explications | L3: Sélection | M3: =SUM(M4:M13)/(5-M2) -> 0
A4: A. | B4: 1 | C4: Est-ce qu'il y a une mission ou une déclaration d'intention du groupe ? | D4: Aucune mission/déclaration d'intention n’est spécifiquement définie. | E4: Une mission/déclaration d'intention existe, mais la direction, le personnel et les membres du groupe n’en ont pas connaissance. Elle n’est pas mise en œuvre. | F4: La mission/déclaration d'intention est connue de la direction, du personnel et des membres du groupe et sert occasionnellement de référence. | G4: La mission/déclaration d'intention est connue, mise en œuvre et régulièrement révisée. | H4: A. | I4: 1
L5: 1 | M5: =IF(L5=0,0,L5-1) -> 0
A6: A. | B6: 2 | C6: Est-ce que le groupe possède des règles/réglementations internes écrites (ex : règlements, le cas échéant) ? Est-ce que les membres sont consultés pour définir ces réglementations ? | D6: Il n'y a pas de règles et de réglementations internes. | E6: Il y a des règles et des réglementations internes écrites, mais il s’agit simplement d'une copie de règlements mandatés du gouvernement, ou de règles et réglementations fournies par l’exportateur. | F6: Il y a des règles et des réglementations internes qui ont été écrites spécifiquement pour servir les besoins du groupe. Cependant, les membre du groupe n'ont pas été consultés pour l’élaboration de ces règles. | G6: Il y a des règles et des réglementations internes qui ont été écrites spécifiquement pour servir les besoins du groupe. Les membres du groupe ont été consultés pour l’élaboration de ces règles. | H6: A. | I6: 2
L7: 0 | M7: =IF(L7=0,0,L7-1) -> 0
A8: A. | B8: 3 | C8: Est-ce que le groupe possède des canaux clairement définis pour communiquer les procédures, les politiques et les autres informations aux membres ? | D8: Les procédures, les politiques et les autres informations ne sont pas communiquées aux membres. | E8: Les procédures, les politiques et les autres informations sont communiquées aux membres d'une manière informelle. | F8: Les procédures, les politiques et les autres informations sont communiquées aux membres via un ou plusieurs canaux clairement identifiés. | G8: Les procédures, les politiques et les autres informations sont communiquées aux membres via un ou plusieurs canaux clairement identifiés. La direction sollicite également activement le feedback des membres. | H8: A. | I8: 3
L9: 0 | M9: =IF(L9=0,0,L9-1) -> 0
A10: A. | B10: 4 | C10: Est-ce que le groupe possède un organigramme, attribuant des responsabilités claires à la direction et aux membres du personnel ? | D10: L’organigramme n’existe pas, aucun rôle ni aucune responsabilité n’est clairement défini pour la direction et les membres du personnel. | E10: Un organigramme informel existe, avec les rôles et responsabilités informels de la direction et des membres du personnel. | F10: Un organigramme formel existe avec les rôles et responsabilités clairs pour la gestion et le personnel. | G10: Un organigramme formel existe avec les rôles et responsabilités clairs pour la gestion et le personnel. Les rôles et les responsabilités sont régulièrement révisés et ajustés. | H10: A. | I10: 4
L11: 0 | M11: =IF(L11=0,0,L11-1) -> 0
A12: A. | B12: 5 | C12: Est-ce que le groupe possède des politiques et des procédures pour garantir un comportement éthique, l’égalité des genres et prévenir les conflits d'intérêt, la discrimination, etc. ? | D12: Il n’y a pas de telles politiques et procédures en place. | E12: Les politiques et procédures sont en place mais elles ne sont pas communiquées aux membres. Aucune procédure de traitement n’a été développée en cas de litige avéré. | F12: Les politiques et procédures sont en place et elles sont communiquées aux membres. Les litiges sont gérés de manière informelle et ont besoin d'un processus formel étape par étape actuellement manquant. | G12: Les politiques et procédures sont en place et elles sont communiquées aux membres. Une procédure de traitement des litiges a été établie. Elle indique quand et comment la déclencher ainsi que les personnes concernées. | H12: A. | I12: 5
L13: 0 | M13: =IF(L13=0,0,L13-1) -> 0

Sheet Gestion stratégique
A1: Sujets d’évaluation et Questions | D1: Option 1 | E1: Option 2 | F1: Option 3 | G1: Option 4 | J1: Cette page possède :
J2: =COUNTA(L4:L14) -> 5 | M2: =COUNTIF(L5:L13,0) -> 5
A3: B. Gestion stratégique | J3: Documents/preuves à l'appui : | K3: Commentaires/explications | L3: Sélection | M3: =SUM(M4:M13)/(5-M2) -> #DIV/0!
A4: B. | B4: 1 | C4: Est-ce que le groupe possède un plan stratégique à moyen terme (3 à 5 ans) et des plans annuels ? Est-ce que la performance réelle du plan est suivie et les résultats communiqués aux membres ? | D4: Il n’y a pas de plan stratégique. | E4: Il y a un plan stratégique, mais il n’est pas à jour et les principes fondamentaux du plan ne sont pas communiqués aux membres. | F4: Il y a un plan stratégique à jour qui est utilisé pour définir les priorités du groupe et les activités en cours. Cependant, il n'y a pas de suivi et d’évaluation de la performance du plan et il n’y a pas de communication sur le plan et ses performances aux membres. | G4: Il y a un plan stratégique à jour qui est utilisé pour définir les priorités du groupe et les activités en cours. Le suivi et l’évaluation de la performance du plan sont en place. Les principes fondamentaux du plan de même que les résultats principaux sont communiqués aux membres. | H4: B. | I4: 1
L5: 0 | M5: =IF(L5=0,0,L5-1) -> 0
A6: B. | B6: 2 | C6: Est-ce que l’organisation est adéquatement pourvue en personnel pour réaliser ses plans stratégiques (à court et moyen terme) ? | D6: Aucun personnel n’est assigné à des responsabilités spécifiques. | E6: Les responsabilités ont été allouées en réponse à un événement, plutôt qu’en résultat d'une planification pour gérer certains processus. | F6: Les responsabilités ont été attribuées dans le cadre d’une planification visant à garantir la mise en œuvre des processus spécifiques, mais ces responsabilités ne correspondent pas aux compétences spécifiques des membres du personnel. | G6: Les responsabilités ont été allouées en réponse à une planification afin d’assurer la mise en œuvre des processus spécifiques, correspondant à l’ensemble des compétences appropriées des membres du personnel. | H6: B. | I6: 2
L7: 0 | M7: =IF(L7=0,0,L7-1) -> 0
A8: B | B8: 3 | C8: Est-ce qu’il y a un processus de gestion de la qualité et d’amélioration continue en place ? (Procédures Normalisées d’Exploitation, PNE) | D8: Il n’y a pas de PNE documentées. | E8: Il y a des PNE documentées (telles que la collecte des frais, la distribution de semences, l’entreposage et le stockage), mais elles ne couvrent pas tous les domaines, elles ne sont pas suivies ou elles ne sont pas facilement accessibles par les membres/personnel. | F8: Il y a des PNE accessibles et documentées avec un échantillonnage des procédures apparaissant et qu'il faut suivre en conséquence. | G8: Des PNE documentées sont disponibles et conformes aux exigences des inspections de routine et aux mises à jour de ces procédures. | H8: B | I8: 3
L9: 0 | M9: =IF(L9=0,0,L9-1) -> 0
A10: B. | B10: 4 | C10: Est-ce que le groupe possède des politiques et structures fonctionnelles en place pour réaliser l’analyse des risques et élaborer un plan de gestion des risques ? | D10: Aucune politique ni structure en place pour mener à bien les évaluations des risques, ni pour élaborer un plan de gestion des risques. | E10: Des politiques et structures informelles sont en place pour répondre aux risques quand ils ont lieu, mais le système est simplement réactif avec des actions lorsque des incidents ont lieu. | F10: Des politiques et des structures fonctionnelles sont en place pour réaliser l’analyse des risques et élaborer un plan de gestion des risques. Cependant, l’analyse des risques n’est pas systématiquement réalisée et le plan de gestion des risques n’est pas mis à jour. | G10: Des politiques et des structures fonctionnelles sont en place pour réaliser l’analyse des risques et élaborer un plan de gestion des risques. L'analyse des risques est réalisée régulièrement et systématiquement et les résultats sont utilisés pour mettre à jour le plan de gestion des risques. | H10: B. | I10: 4
L11: 0 | M11: =IF(L11=0,0,L11-1) -> 0
A12: B. | B12: 5 | C12: Est-ce que le groupe opère/prend des décisions de manière indépendante ? | D12: Le groupe est établi et géré par un exportateur/entreprise et ne prend pas de décision de manière indépendante. | E12: Le groupe est basé sur les membres mais les décisions sont principalement prises en fonction des conseils de l’exportateur/entreprise. | F12: Le groupe est établi et géré par un négociant/une entreprise mais bénéficie d’une très large indépendance. | G12: Le groupe est basé sur les membres et prend ses décisions de manière complètement indépendante de l’exportateur/entreprise ou des autres parties prenantes. | H12: B. | I12: 5
L13: 0 | M13: =IF(L13=0,0,L13-1) -> 0

Sheet Financier
A1: Sujets d’évaluation et Questions | D1: Option 1 | E1: Option 2 | F1: Option 3 | G1: Option 4 | J1: Cette page possède :
J2: =COUNTA(L4:L14) -> 5 | M2: =COUNTIF(L5:L13,0) -> 5
A3: C. Gestion financière | J3: Documents/preuves à l'appui : | K3: Commentaires/explications | L3: Sélection | M3: =SUM(M4:M13)/(5-M2) -> #DIV/0!
A4: C. | B4: 1 | C4: Est-ce que le groupe documente et suit les politiques de gestion financière ? | D4: Il n’y a pas de manuel de comptabilité ou de documentation informelle des procédures. | E4: Il n’y a pas de manuel de comptabilité, mais plusieurs processus sont documentés. | F4: Le groupe dispose d’un manuel de comptabilité qui décrit les processus applicables à toutes les transactions liées aux finances, aux actifs et au produit. Les politiques et le manuel de comptabilité ne sont pas toujours respectés. | G4: Le groupe dispose d’un manuel de comptabilité qui décrit les processus applicables à toutes les transactions liées aux finances, aux actifs et au produit. La conformité des procédures a été soumise à un audit au cours de l’année dernière. | H4: C. | I4: 1
L5: 0 | M5: =IF(L5=0,0,L5-1) -> 0
A6: C. | B6: 2 | C6: Est-ce que le groupe réalise une planification financière à long terme et produit des déclarations financières régulières ? | D6: Il n’y a pas de planification financière, ni rapport financier régulier. | E6: Il n’y a pas de planification financière. Des rapports financiers sont en cours de préparation mais sont uniquement partiels ou ne sont pas rédigés de manière systématique (par exemple, il n’y a pas de rapprochement avec les listes des actifs, des responsabilités et des valeurs nettes). | F6: Le groupe a préparé un plan financier à long terme. Des états financiers détaillés réguliers sont en cours de préparation mais ces informations ne sont pas utilisées pour mettre à jour la planification financière. | G6: Le groupe réalise une planification financière à long terme. Des états financiers détaillés réguliers sont en cours de préparation et sont aussi utilisés pour mettre à jour la planification financière. | H6: C. | I6: 2
L7: 0 | M7: =IF(L7=0,0,L7-1) -> 0
A8: C. | B8: 3 | C8: Est-ce que la comptabilité et le système de données du groupe produisent des informations qui permettent de contrôler les opérations et de surveiller le rendement financier ? | D8: Il n’y a pas de registre précis des revenus, des dépenses et des coûts fixes/administratifs. | E8: Il y a un registre précis d'un domaine (des revenus, des dépenses et des coûts fixes/administratifs). | F8: Il y a un registre de tous les revenus, dépenses et coûts fixes/administratifs, mais ils n’ont pas été rapprochés des déclarations bancaires ou confirmés par un auditeur externe. | G8: Le revenu net des pertes et profits est représenté dans la feuille d’équilibre et est confirmé via le rapprochement des déclarations bancaires ou par un auditeur externe. | H8: C. | I8: 3
L9: 0 | M9: =IF(L9=0,0,L9-1) -> 0
A10: C. | B10: 4 | C10: Est-ce que le groupe est capable de démontrer une bonne performance financière ? | D10: Le groupe est peu rentable ou est incapable de déterminer s’il est rentable. | E10: Le groupe est capable de démontrer uniquement une année rentable au cours des trois dernières années. Cependant, le groupe n’a pas eu d’audit externe durant cette période. | F10: Le groupe est capable de démontrer uniquement une année rentable au cours des trois dernières années. Ces informations sont confirmées via un audit externe. | G10: Le groupe est capable de démontrer une tendance à la hausse de rentabilité au cours des trois dernières années. Ces informations sont confirmées via un audit externe. | H10: C. | I10: 4
L11: 0 | M11: =IF(L11=0,0,L11-1) -> 0
A12: C. | B12: 5 | C12: Le groupe a-t-il élaboré un plan qui lui permette d’effectuer les investissements et d’accéder aux ressources financières nécessaires à ses activités commerciales, d’atteindre la compatibilité avec les normes Rainforest Alliance et de mettre en œuvre son Plan de gestion de l’exploitation agricole et de services à ses membres ? | D12: Le groupe ne connait pas les exigences et ne dispose d’aucun plan d’investissement ou de financement. | E12: Le groupe manque de liquidités et ne dispose d’aucun plan lui permettant d’obtenir de nouveaux financements. | F12: Le groupe dispose d’un plan d’investissements ou de financement mais ce plan ne se base pas sur une évaluation claire des dépenses nécessaires ou des priorités. | G12: Le groupe dispose d’un plan d’investissements ou de financement basé sur une évaluation claire des dépenses nécessaires ou des priorités et est régulièrement mis à jour. | H12: C. | I12: 5
L13: 0 | M13: =IF(L13=0,0,L13-1) -> 0

Sheet Sociétariat
A1: Sujets d’évaluation et Questions | D1: Option 1 | E1: Option 2 | F1: Option 3 | G1: Option 4 | J1: Cette page possède :
J2: =COUNTA(L4:L13) -> 5 | M2: =COUNTIF(L5:L13,0) -> 5
A3: D. Implication des membres et planification des adhésions | J3: Documents/preuves de soutien : | K3: Commentaires/explications | L3: Sélection | M3: =SUM(M4:M13)/(5-M2) -> #DIV/0!
A4: D. | B4: 1 | C4: Est-ce que le groupe a convoqué une réunion générale des membres (ou assemblée) au cours des trois dernières années ? | D4: Il n’y a pas eu de réunions générales durant les trois dernières années. | E4: Il y a eu une ou plusieurs réunions générales, mais moins de 50 % des membres ont participé. | F4: Il y a eu une réunion générale tous les ans avec au moins 50% des membres participants. Cependant, les réunions se limitent à la présentation des informations aux membres. | G4: Il y a eu une réunion générale tous les ans avec au moins 50% des membres participants. Les réunions sont utilisées pour présenter et discuter des problèmes avec les membres. | H4: D. | I4: 1
L5: 0 | M5: =IF(L5=0,0,L5-1) -> 0
A6: D. | B6: 2 | C6: Est-ce que les membres fournissent des ressources financières au groupe (via des frais d’adhésion ou une autre forme de contribution financière) ? | D6: Les membres ne contribuent pas financièrement au groupe. | E6: Les membres contribuent sur une base volontaire mais ces contributions sont irrégulières et ne viennent pas de tous les membres. | F6: Les contributions des adhésions sont collectées chez tous les membres de manière régulière. | G6: Les contributions des adhésions sont collectées chez tous les membres de manière régulière et les registres indiquent la date et le montant payé par chaque membre. | H6: D. | I6: 2
L7: 0 | M7: =IF(L7=0,0,L7-1) -> 0
A8: D. | B8: 3 | C8: Quelle a été l’évolution des adhésions au cours des trois dernières années ? | D8: Il n’y a pas de registres précis des membres ou de la durée de leur adhésion. | E8: Il y a des registres précis des membres et de la durée d’adhésion. La participation aux adhésions des membres existants a chuté au cours des trois dernières années. | F8: Il y a des registres précis des membres et de la durée d’adhésion. La participation aux adhésions des membres existants n’a pas changé au cours des trois dernières années. | G8: Il y a des registres précis des membres et de la durée d’adhésion. Les adhésions de membres actifs ont progressé au cours des trois dernières années. | H8: D. | I8: 3
L9: 0 | M9: =IF(L9=0,0,L9-1) -> 0
A10: D. | B10: 4 | C10: Est-ce que le groupe possède un plan d’adhésion (incluant les communications, les engagements, le recrutement et le maintien des membres) ? | D10: Le groupe ne possède pas de plan d’adhésion. | E10: Il n’y a pas de plan formel d’adhésion mais des activités sont organisées pour recruter de nouveaux membres. | F10: Il y a un plan formel d’adhésion qui se concentre sur le recrutement et le maintien des membres. | G10: Il y a un plan formel d’adhésion qui se concentre sur le recrutement et le maintien des membres. Le plan est régulièrement révisé et discuté avec les membres. | H10: D. | I10: 4
L11: 0 | M11: =IF(L11=0,0,L11-1) -> 0
A12: D. | B12: 5 | C12: L’organisation dispose-t-elle de plans ou fait-t-elle systématiquement les efforts nécessaires à la formation et l’information des membres leur permettant de devenir des propriétaires actifs et informés ? | D12: Le groupe n’a mis en place aucune politique ni aucun service destiné aux membres nouveaux ou en difficulté. | E12: Il n’existe ni politique, ni service d’aide aux membres nouveaux ou en difficulté, mais le groupe fournit différents services d’urgence (par exemple, aide au transport, travail supplémentaire, etc.) à certains membres du groupe. | F12: Le groupe a mis en œuvre des politiques et des services couramment fournis aux membres nouveaux ou en difficulté. | G12: Le groupe a mis en œuvre des politiques et des services pour soutenir les membres nouveaux ou en difficulté et cible spécifiquement ces membres pour la fourniture de services supplémentaires (tels qu’une formation supplémentaire sur les clubs d'épargne, etc.) afin de leur permettre de consolider leur situation et de participer plus activement aux activités du groupe. | H12: D. | I12: 5
L13: 0 | M13: =IF(L13=0,0,L13-1) -> 0

Sheet Formation et services
A1: Sujets d’évaluation et Questions | D1: Option 1 | E1: Option 2 | F1: Option 3 | G1: Option 4 | J1: Cette page possède :
J2: =COUNTA(L4:L13) -> 5 | M2: =COUNTIF(L5:L13,0) -> 5
A3: E. Formation des membres et mise à disposition de services | J3: Documents/preuves à l'appui : | K3: Commentaires/explications | L3: Sélection | M3: =SUM(M4:M13)/(5-M2) -> #DIV/0!
A4: E. | B4: 1 | C4: Est-ce que le groupe possède un processus ou une structure en place pour fournir de la formation/soutien technique et autres services aux membres ? | D4: Pas de processus ou de structure en place pour fournir de la formation/soutien technique et autres services aux membres. | E4: Processus et structure informels en place pour fournir de la formation/soutien technique et autres services aux membres, ayant lieu habituellement en réaction à un incident/événement. | F4: Processus et structure formels en place pour fournir de la formation/soutien technique et autres services. Ils contiennent un plan formel (annuel) précisant le type de formation et les services à fournir, la fréquence de réalisation, etc. Cependant, les membres n’ont pas été consultés pour la conception du plan (ex : via une évaluation des besoins). | G4: Processus et structure formels existants de formation/soutien technique et autres services qui comprennent un plan formel (annuel) précisant le type de formation ou de services à fournir, la fréquence de réalisation, etc. Les membres hommes et femmes ont été activement consultés lors de la conception du plan. | H4: E. | I4: 1
L5: 0 | M5: =IF(L5=0,0,L5-1) -> 0
A6: E. | B6: 2 | C6: Est-ce que le groupe est suffisamment pourvu en personnel pour fournir la formation et les autres services aux membres ? | D6: Le groupe manque de personnel pour fournir la formation et les autres services aux membres. | E6: Le groupe possède suffisamment de personnel pour remplir tous les postes clés mais la majorité du personnel ne possède pas les qualifications adéquates pour leurs postes. | F6: Le groupe possède suffisamment de personnel pour remplir tous les postes clés et tous possèdent les qualifications adéquates pour leurs postes. Cependant, aucune formation avancée/de suivi n’est fournie pour le personnel existant. | G6: Le groupe possède suffisamment de personnel pour remplir tous les postes clés et tous possèdent les qualifications adéquates pour leurs postes. Le personnel reçoit régulièrement des formations avancées/de suivi pour les maintenir à jour des évolutions concernées pour leurs postes. | H6: E. | I6: 2
L7: 0 | M7: =IF(L7=0,0,L7-1) -> 0
A8: E. | B8: 3 | C8: Est-ce que toutes les formations ont été documentées et est-ce qu’un système de suivi est disponible ? | D8: Aucune formation fournie. | E8: Aucune documentation formelle n’existe spécifiant le type de formation fournie, le niveau de compétence du formateur, le nombre de participants et la date et durée de la formation fournie. | F8: Une documentation formelle sur la formation est disponible et contient la collecte des données ventilées des genres. Cependant, aucun processus n’existe pour suivre la qualité de la formation et pour collecter le feedback des participants afin d’apprendre et d’améliorer l’efficacité et l’efficience de la formation fournie. | G8: Une documentation formelle sur la formation est disponible et contient la collecte des données ventilées des genres. Il existe un processus pour suivre la qualité de la formation et pour collecter le feedback des participants. Les informations recueillies sont utilisées et partagées avec les personnes concernées afin d’améliorer l’efficacité et l’efficience de la formation fournie. | H8: E. | I8: 3
L9: 0 | M9: =IF(L9=0,0,L9-1) -> 0
A10: E. | B10: 4 | C10: Est-ce que la mise à disposition des services (autre que la formation) a été documentée et est-ce qu’un système de suivi est disponible ? | D10: Aucun autre service n’est fourni. | E10: Aucune documentation formelle n’existe spécifiant le type de services fournis, le nombre d’agriculteurs recevant le service et la date/durée de réalisation du service. | F10: Une documentation formelle sur la réalisation du service est disponible et contient la collecte des données ventilées des genres. Cependant, aucun processus n’existe pour suivre la qualité de la mise à disposition des services et pour collecter le feedback des bénéficiaires afin d’améliorer l’efficacité et l’efficience des services fournis. | G10: Une documentation formelle sur la réalisation du service est disponible et contient la collecte des données ventilées des genres. Il existe un processus pour suivre la qualité de la mise à disposition des services et pour collecter le feedback des participants. Les informations recueillies sont utilisées et partagées avec les personnes concernées afin d’améliorer l’efficacité et l’efficience des services fournis. | H10: E. | I10: 4
L11: 0 | M11: =IF(L11=0,0,L11-1) -> 0
A12: E. | B12: 5 | C12: Est-ce que le groupe possède un système pour garantir la qualité des intrants agricoles fournis ? | D12: Le groupe ne possède pas de système pour garantir la qualité des intrants agricoles fournis. | E12: Le groupe ne possède pas de système formel mais des vérifications sont parfois effectuées. | F12: Le groupe possède un système formel mais les vérifications ne sont pas effectuées de manière régulière. | G12: Le groupe possède un système formel et des vérifications sont effectuées de manière régulière. | H12: E. | I12: 5
L13: 0 | M13: =IF(L13=0,0,L13-1) -> 0

Sheet Ventes et marketing
A1: Sujets d’évaluation et Questions | D1: Option 1 | E1: Option 2 | F1: Option 3 | G1: Option 4 | J1: Cette page possède :
J2: =COUNTA(L3:L13)-1 -> 5 | M2: =COUNTIF(L5:L13,0) -> 5
A3: F. Ventes et marketing | J3: Documents/preuves à l'appui : | K3: Commentaires/explications | L3: Sélection | M3: =SUM(M4:M13)/(5-M2) -> #DIV/0!
A4: F. | B4: 1 | C4: Est-ce que le groupe a réalisé des ventes collectives ? | D4: Le groupe n’a pas réalisé de ventes collectives, ou des ventes collectives ont impliqué moins de 20% des membres. | E4: Le groupe a réalisé au moins une vente collective qui comporte au moins 20% des membres. | F4: Le groupe a réalisé au moins deux ventes collectives dont chacune impliquant au moins 50% des membres. | G4: Le groupe a réalisé au moins trois ventes collectives dont chacune impliquant au moins 75% des membres. | H4: F. | I4: 1
L5: 0 | M5: =IF(L5=0,0,L5-1) -> 0
A6: F. | B6: 2 | C6: Quel est le niveau de participation des membres aux ventes groupées ? | D6: Peu de membres (< 10 %) vend via le groupe et ces ventes concernent moins de la moitié de leur production. | E6: La majorité des membres (> 50 %) vend via le groupe, mais ces ventes concernent moins de la moitié de leur production. | F6: Une majorité des membres (> 50 %) vend via le groupe et ces ventes concernent plus de la moitié de leur production. | G6: Presque tous les membres (> 90 %) vendent via le groupe et ces ventes concernent plus de la moitié de leur production. | H6: F. | I6: 2
L7: 0 | M7: =IF(L7=0,0,L7-1) -> 0
A8: F. | B8: 3 | C8: Le groupe dispose-t-il d’un processus ou d’une structure permettant de mener et de gérer les activités commerciales ? | D8: Aucun processus ou structure en place pour réaliser et gérer les activités commerciales. | E8: Un processus et une structure informels en place pour réaliser et gérer les activités commerciales. | F8: Le groupe a au moins une fois élaboré un plan de marketing qui comporte les cibles de vente, les acheteurs, le volume et la valeur et il a atteint les cibles de ventes du plan de marketing. Cependant, aucun suivi ou évaluation pour apprendre et améliorer l’efficacité et l’efficience de la gestion des activités commerciales. | G8: Le groupe a au moins une fois élaboré un plan de marketing qui comporte les cibles de vente, les acheteurs, le volume et la valeur. Il a atteint les cibles de ventes du plan de marketing et il communique ce plan aux membres avant le début de la saison de plantation. Une procédure formalisée de suivi et évaluation est en place pour garantir l’apprentissage et l’amélioration de la gestion des activités commerciales. | H8: F. | I8: 3
L9: 0 | M9: =IF(L9=0,0,L9-1) -> 0
A10: F. | B10: 4 | C10: Est-ce que le groupe possède un processus ou une structure en place pour déterminer les prix avec les acheteurs ? | D10: Aucun processus ou structure en place. | E10: La documentation formelle est absente (système informel uniquement) concernant la détermination des prix. | F10: Politique formelle en place qui stipule la détermination des prix et la communication des prix aux membres, l’utilisation des primes, la distribution et l’attribution au SGI. Les parties prenantes n’ont pas été consultées durant la conception de la politique. | G10: Politique formelle en place qui stipule la détermination des prix et la communication des prix aux membres, l’utilisation des primes, la distribution et l’attribution au SGI. La consultation des parties prenantes a eu lieu durant la conception de la politique. | H10: F. | I10: 4
L11: 0 | M11: =IF(L11=0,0,L11-1) -> 0
A12: F. | B12: 5 | C12: Est-ce que le groupe possède un processus ou une structure en place pour la logistique et le contrôle de la qualité durant la transformation, le stockage et les manipulations ? | D12: Aucun processus ou structure en place pour la logistique (transformation, stockage et manipulations) ou le contrôle de la qualité. | E12: Le processus de contrôle de la qualité et de la logistique manque de documentation formelle qui stipule les procédures spécifiques pour optimiser la qualité et l’efficacité lors des activités de transformation, de stockage et de manipulation ou la gestion du flux d'informations en interne, en amont et en aval. | F12: Un processus et une politique clairs en place qui stipulent les procédures spécifiques pour optimiser la qualité et l’efficacité lors des activités de transformation, de stockage et de manipulation de même que la gestion du flux d'informations en interne, en amont et en aval. Cependant, aucun suivi ou évaluation pour apprendre et améliorer l’efficacité et l’efficience de la logistique et du contrôle de la qualité. | G12: Un processus et une politique clairs en place qui stipulent les procédures spécifiques pour optimiser la qualité et l’efficacité lors des activités de transformation, de stockage et de manipulation de même que la gestion du flux d'informations en interne, en amont et en aval. Un système est en place pour le suivi et l’évaluation afin d’apprendre et d’améliorer l’efficacité et l’efficience de la logistique et du contrôle de la qualité. | H12: F. | I12: 5
L13: 0 | M13: =IF(L13=0,0,L13-1) -> 0

Sheet SGI
A1: Sujets d’évaluation et Questions | D1: Option 1 | E1: Option 2 | F1: Option 3 | G1: Option 4 | J1: Cette page possède :
J2: =COUNTA(L4:L13) -> 6 | M2: =COUNTIF(L5:L13,0) -> 5
A3: G. Système de Gestion Interne | J3: Documents/preuves à l'appui : | K3: Commentaires/explications | L3: Sélection | M3: =SUM(M4:M13)/(5-M2) -> #DIV/0!
A4: G. | B4: 1 | C4: Est-ce que le groupe possède des politiques et structures formelles en place pour gérer la traçabilité et la conformité avec les critères de qualité et de la norme (Manuel du SGI) ? | D4: Aucune politique ou structure en place pour gérer la traçabilité et la conformité par rapport aux critères de la norme et de la qualité. | E4: Certaines politiques ou structures pour gérer la traçabilité et la conformité par rapport aux critères de la norme et de la qualité sont en place mais elles ne sont pas formellement documentées. | F4: Une documentation formelle existe (Manuel du SGI) de toutes les politiques et structures pour gérer la traçabilité et la conformité par rapport aux critères de la norme et de la qualité. Cependant, les politiques et les structures ne sont pas révisées régulièrement. | G4: Une documentation formelle existe (Manuel du SGI) de toutes les politiques et structures pour gérer la traçabilité et la conformité par rapport aux critères de la norme et de la qualité. Les politiques et les structures sont régulièrement révisées et mises à jour si nécessaire. | H4: G. | I4: 1 | J4: Manuel du SGI disponilble avec toutes les politiques et procédures | L4: 1
L5: 0 | M5: =IF(L5=0,0,L5-1) -> 0
A6: G. | B6: 2 | C6: Est-ce que le groupe est suffisamment pourvu en personnel pour chaque fonction dans le SGI ? | D6: Pas d'organigramme pour le SGI, pas de rôles ou responsabilités clairs pour la gestion du SGI et des autres personnels. | E6: Un organigramme informel existe. Il y a un responsable du SGI mais les rôles et responsabilités des autres membres du personnel ne sont pas clairs. | F6: Un organigramme formel existe avec des rôles et responsabilités clairs pour la gestion du SGI et des autres personnels. | G6: Un organigramme formel existe avec des rôles et responsabilités clairs pour la gestion du SGI et des autres personnels. Les rôles et les responsabilités sont régulièrement révisés et ajustés. | H6: G. | I6: 2
L7: 0 | M7: =IF(L7=0,0,L7-1) -> 0
A8: G. | B8: 3 | C8: Est-ce que les inspecteurs reçoivent la formation nécessaire et des mises à jour régulières ? | D8: Les inspecteurs n’ont pas reçu de formation sur les inspections. | E8: Les inspecteurs ont reçu une formation de base, mais aucune remise à niveau/suivi n’est organisé. | F8: Les inspecteurs ont reçu une formation de base et également une formation de remise à niveau/suivi. | G8: Les inspecteurs ont reçu une formation de base et également une formation de remise à niveau/suivi basée sur leurs besoins individuels. | H8: G. | I8: 3
L9: 0 | M9: =IF(L9=0,0,L9-1) -> 0
A10: G. | B10: 4 | C10: Est-ce que l’organisation possède des politiques et structures formelles en place pour réaliser des inspections internes ? (Et est-ce que les inspections ont lieu conformément à la politique ?) | D10: Aucune politique ou structure en place pour réaliser les inspections. | E10: Une politique et une structure d'inspection existent et sont habituellement mises en œuvre en réponse à un incident. Aucune clause formelle précisant qui, quand et comment réaliser l'inspection, ou comment les données doivent être collectées et comment les gérer. | F10: Une politique et une structure formelles d'inspection sont en place. La politique stipule par qui, quand et comment l’inspection de même que la collecte des données doivent être réalisées y compris la spécification de l'implication des agricultrices. Cependant, le groupe a des difficultés pour organiser les inspections conformément à la politique. | G10: Une politique et une structure formelles d'inspection sont en place et le groupe est capable d'organiser des inspections conformément à la politique. La politique stipule par qui, quand et comment l’inspection de même que la collecte des données doivent être réalisées y compris la spécification de l'implication des agricultrices. Les inspections sont planifiées et réalisées conformément à la politique. | H10: G. | I10: 4
L11: 0 | M11: =IF(L11=0,0,L11-1) -> 0
A12: G. | B12: 5 | C12: Est-ce que le groupe possède une structure en place et assez de personnel pour analyser les données des inspections internes et décider/planifier un suivi ? | D12: Il n'y a pas de structure en place pour analyser les données des inspections internes et pour décider et planifier le suivi. | E12: Il y a une structure en place mais le nombre de personnel est limité (résultant en des délais dans les analyses et aucun suivi planifié). | F12: Il y a une structure en place et le groupe possède assez de personnel pour réaliser l’analyse et planifier le suivi concernant les sanctions et pour résoudre les non-conformités en indiquant des délais et responsabilités clairs. Cependant, aucun processus n’est en place pour l’évaluation pour apprendre et améliorer l’efficacité et l’efficience du processus. | G12: Il y a une structure en place et le groupe possède assez de personnel pour réaliser l’analyse et planifier le suivi concernant les sanctions et pour résoudre les non-conformités en indiquant des délais et responsabilités clairs. Il y a un système en place pour l’évaluation pour apprendre et améliorer l’efficacité et l’efficience du processus. | H12: G. | I12: 5
L13: 0 | M13: =IF(L13=0,0,L13-1) -> 0

Sheet Sheet1
B1: 0 | C1: 0.2 | D1: 0.4 | E1: 0.6 | F1: 0.8 | G1: 1 | H1: 1.2 | I1: 1.4 | J1: 1.6 | K1: 1.8 | L1: 2 | M1: 2.2 | N1: 2.4 | O1: 2.6 | P1: 2.8 | Q1: 3
A2: 5 | B2: 0 | C2: 0 | D2: 0 | E2: 1 | F2: 1 | G2: 1 | H2: 1 | I2: 1 | J2: 2 | K2: 2 | L2: 2 | M2: 2 | N2: 2 | O2: 3 | P2: 3 | Q2: 3
A3: 4 | B3: 0 | C3: 0 | D3: 0 | E3: 1 | F3: 1 | G3: 1 | H3: 1 | I3: 2 | J3: 2 | K3: 2 | L3: 2 | M3: 3 | N3: 3
A4: 3 | B4: 0 | C4: 0 | D4: 1 | E4: 1 | F4: 1 | G4: 2 | H4: 2 | I4: 2 | J4: 3 | K4: 3
A6: =Organisation!L3 -> Sélection | C6: ='Gestion stratégique'!L3 -> Sélection | E6: =Financier!L3 -> Sélection | G6: =Sociétariat!L3 -> Sélection | I6: ='Formation et services'!L3 -> Sélection | K6: ='Ventes et marketing'!L3 -> Sélection | M6: =SGI!L3 -> Sélection
A7: =Organisation!M3 -> 0 | B7: =MATCH(A7,$B1:$Q1,0) -> 1 | C7: ='Gestion stratégique'!M3 -> #DIV/0! | D7: =MATCH(C7,$B1:$Q1,0) -> #DIV/0! | E7: =Financier!M3 -> #DIV/0! | F7: =MATCH(E7,$B1:$Q1,0) -> #DIV/0! | G7: =Sociétariat!M3 -> #DIV/0! | H7: =MATCH(G7,$B1:$Q1,0) -> #DIV/0! | I7: ='Formation et services'!M3 -> #DIV/0! | J7: =MATCH(I7,$B1:$Q1,0) -> #DIV/0! | K7: ='Ventes et marketing'!M3 -> #DIV/0! | L7: =MATCH(K7,$B1:$Q1,0) -> #DIV/0! | M7: =Organisation!M3 -> 0 | N7: =MATCH(M7,$B1:$Q1,0) -> 1
A8: =INDEX($B2:$Q4,MATCH(A6,$A2:$A4,0),B7) -> #N/A | C8: =INDEX($B2:$Q4,MATCH(C6,$A2:$A4,0),D7) -> #N/A | E8: =INDEX($B2:$Q4,MATCH(E6,$A2:$A4,0),F7) -> #N/A | G8: =INDEX($B2:$Q4,MATCH(G6,$A2:$A4,0),H7) -> #N/A | I8: =INDEX($B2:$Q4,MATCH(I6,$A2:$A4,0),J7) -> #N/A | K8: =INDEX($B2:$Q4,MATCH(K6,$A2:$A4,0),L7) -> #N/A | M8: =INDEX($B2:$Q4,MATCH(M6,$A2:$A4,0),N7) -> #N/A

Sheet Sheet2
A1: Main aspects based on AMEA guidelines:
A2: A. Organizational purpose and Governance practices
A3: B. Business management
A4: C. Member engagement and planning
A5: D. Human resource management
A6: E. Financial management
A7: F. Community and stakeholder engagement
A8: G. Member services and business activiies
A10: Red | B10: From the AMEA guidelines
A11: Yellow | B11: From the M4 tool
A12: Wit: | B12: From the NewForesight tool
A13: Beige: | B13: From the Adore tool
