Workbook

Sheet summary
P1: Score | Q1: Level
K2: ='Group risk assessment L0'!A2 -> 0 | P2: ='Group risk assessment L0'!#REF! -> #REF! | Q2: =IF(P2>0.25, IF(P2>0.5,IF(P2>0.75,3,2),1),0) -> #REF! | R2: =IF(Q2=1,L$17,IF(Q2=2,L$18,IF(Q2=3,L$19,L$16))) -> #REF!
K3: =#REF! -> #REF! | P3: =#REF! -> #REF! | Q3: =IF(P3>0.25, IF(P3>0.5,IF(P3>0.75,3,2),1),0) -> #REF! | R3: =IF(Q3=1,L$17,IF(Q3=2,L$18,IF(Q3=3,L$19,L$16))) -> #REF!
K4: =#REF! -> #REF! | P4: =#REF! -> #REF! | Q4: =IF(P4>0.25, IF(P4>0.5,IF(P4>0.75,3,2),1),0) -> #REF! | R4: =IF(Q4=1,L$17,IF(Q4=2,L$18,IF(Q4=3,L$19,L$16))) -> #REF!
K5: =#REF! -> #REF! | P5: =#REF! -> #REF! | Q5: =IF(P5>0.25, IF(P5>0.5,IF(P5>0.75,3,2),1),0) -> #REF! | R5: =IF(Q5=1,L$17,IF(Q5=2,L$18,IF(Q5=3,L$19,L$16))) -> #REF!
K6: =#REF! -> #REF! | P6: =#REF! -> #REF! | Q6: =IF(P6>0.25, IF(P6>0.5,IF(P6>0.75,3,2),1),0) -> #REF! | R6: =IF(Q6=1,L$17,IF(Q6=2,L$18,IF(Q6=3,L$19,L$16))) -> #REF!
K7: =#REF! -> #REF! | P7: =#REF! -> #REF! | Q7: =IF(P7>0.25, IF(P7>0.5,IF(P7>0.75,3,2),1),0) -> #REF! | R7: =IF(Q7=1,L$17,IF(Q7=2,L$18,IF(Q7=3,L$19,L$16))) -> #REF!
K8: =#REF! -> #REF! | P8: =#REF! -> #REF! | Q8: =IF(P8>0.25, IF(P8>0.5,IF(P8>0.75,3,2),1),0) -> #REF! | R8: =IF(Q8=1,L$17,IF(Q8=2,L$18,IF(Q8=3,L$19,L$16))) -> #REF!
K9: =#REF! -> #REF! | P9: =#REF! -> #REF! | Q9: =IF(P9>0.25, IF(P9>0.5,IF(P9>0.75,3,2),1),0) -> #REF! | R9: =IF(Q9=1,L$17,IF(Q9=2,L$18,IF(Q9=3,L$19,L$16))) -> #REF!
K10: =#REF! -> #REF! | P10: =#REF! -> #REF! | Q10: =IF(P10>0.25, IF(P10>0.5,IF(P10>0.75,3,2),1),0) -> #REF! | R10: =IF(Q10=1,L$17,IF(Q10=2,L$18,IF(Q10=3,L$19,L$16))) -> #REF!
K11: =#REF! -> #REF! | P11: =#REF! -> #REF! | Q11: =IF(P11>0.25, IF(P11>0.5,IF(P11>0.75,3,2),1),0) -> #REF! | R11: =IF(Q11=1,L$17,IF(Q11=2,L$18,IF(Q11=3,L$19,L$16))) -> #REF!
P12: =AVERAGE(P2:P11) -> #REF! | Q12: =IF(P12>0.25, IF(P12>0.5,IF(P12>0.75,3,2),1),0) -> #REF! | R12: =IF(Q12=1,L$17,IF(Q12=2,L$18,IF(Q12=3,L$19,L$16))) -> #REF!
K15: Level
K16: 0 | L16: 0
K17: 1 | L17: ¬
K18: 2 | L18: ¬¬
K19: 3 | L19: ¬¬¬

Sheet NEW integrated RA (S + L)
A2: Question | B2: Requirements in standard | C2: Which CH type does this apply to? | D2: Other variables | E2: Issue | F2: Mitigation self-assessment – risk questions | G2: Answer parameter | H2: Country/sector risk context applicability | I2: Mitigation actions to be included in the Management Plan | J2: Comments
B3: Management
A4: 1 | C4: Group Certification | E4: Deforestation/ Native vegetation | F4: Do you expect production sites of group members to be shifting or expanding? | G4: no | H4: All | I4: No additional action needed
C5: Group Certification | E5: Deforestation/ Native vegetation | G5: Yes | H5: All | I5: Ensure that producers and workers know that natural vegetation and natural ecosystems have to be maintained, through awareness raising and regular monitoring. Clearly mark the boundaries of on-farm natural ecosystems and their buffer zones and ensure that production and processing activities, including agrochemical use, do not encroach into these areas. | J5: AP: not sure if this question is needed - mitigation measures are basically implementing th standard on the new farm units. They will anyway have to implement the whole standard, not only the criteria related to native vegetation RR: I think it is good to keep, to assess the risks of expanding to new areas
C6: Large | E6: Deforestation/ Native vegetation | F6: Are production sites shifting or expanding? | G6: no | H6: All | I6: No additional action needed
C7: Large | E7: Deforestation/ Native vegetation | G7: Yes | H7: All | I7: Ensure that workers know that natural vegetation and natural ecosystems have to be maintained, through awareness raising and regular monitoring. Clearly mark the boundaries of on-farm natural ecosystems and their buffer zones and ensure that production and processing activities, including agrochemical use, do not encroach into these areas. | J7: AP: not sure if this question is needed - mitigation measures are basically implementing th standard on the new farm units. They will anyway have to implement the whole standard, not only the criteria related to native vegetation
A8: 2 | B8: 1.8 Traceability | C8: Group Certification | E8: Intermediaries | F8: Do you/will you make use of intermediaries and/or subcontractors* in your supply chain? | G8: yes | H8: All | I8: Set up a clear traceability flow, that includes the documented and physical traceability rules for all actors in your supply chain (farmers, subcontractors, intermediary, processing units, transport, collection centers, management etc.). Train all actors on your traceability procedure. This includes the intermediaries and/or subcontractors. Monitor traceability and record keeping at all actors. Monitoring intermediaries especially during the harvest period. For monitoring, verify calibration of scales and record keeping at intermediaries and cross-check with information of sales from a sample of producers.
C9: Group Certification | E9: Intermediaries | G9: no | H9: All | I9: Set up a clear traceability flow, that includes the documented and physical traceability rules for all actors in your supply chain (farmers, processing units, transport, collection centers, management etc.). Train all actors on your traceability procedure. Monitor traceability and record keeping at all actors.
C10: Large | E10: Subcontractors | F10: Do you/will you make use of subcontractors* in your supply chain? | G10: yes | H10: All | I10: Set up a clear traceability flow, that includes the documented and physical traceability rules for all actors in your supply chain (processing units, transport, subcontractors, warehouse etc.). Train all actors on your traceability procedure. Monitor traceability and record keeping at all actors. For subcontractors, verifying if all subcontractors comply with the traceability procedure and all requirements in the standard that apply to them is part of the self-assessment.
C11: Large | E11: Subcontractors | G11: No | H11: All | I11: Set up a clear traceability flow, that includes the documented and physical traceability rules for all actors in your supply chain (processing units, transport, subcontractors, warehouse etc.). Train all actors on your traceability procedure. Monitor traceability and record keeping at all actors.
A12: 3 | C12: Group Certification | E12: Record keeping | F12: Do you expect farmers to have difficulties keeping (traceability) records? | G12: yes | H12: All | I12: Include administrion/keeping of receipts in training plan. The group supports the farmer to keep the receipts at the same place (ex: plastic folder) Put up signs to encourage farmers to keep receipts Monitor keeping of receipts | J12: AP: Do we mean records or receipts that they receive from the buying station/group? In the standard, farmers are not requested to keep records so not sure if 'record books' is needed. If receipt, then - the group needs to find a system for the farmer to keep them at the same place (ex: plastic folder) - remove the term 'record' to align with the standard and avoid confusion Changed
C13: Group Certification | E13: Record keeping | G13: no | H13: All | I13: No additional action needed
A14: 4 | C14: Group Certification | E14: Product separation | F14: Do you/will you only handle RA certified product and only buy from RA certified producers? | G14: yes | H14: All | I14: No further actions needed (apart from actions on compliance with the standard)
C15: Group Certification | E15: Product separation | F15: Do you/will you only handle RA certified product and only buy from RA certified producers? | G15: no | H15: All | I15: Implement a system for identifying the products originating from certified producers by means of physical or visual identification and in the tracebaility documents (receipts, registry, etc.). Example of visual identification can be tags on the bags during the product transportation and storage
A16: 5 | C16: Group Certification | E16: Record keeping | F16: Do group members have access to different market outlets / different buyers for their certifiers product? | G16: yes | H16: All | I16: Information on harvested volumes based on deliveries might not be reliable, therefore, put a system in place to get information on harvested volumes (this can be done by asking producers directly through out the year or during internal inspections). Collect the information on harvested volume throughout the year (monthly basis) instead of once a year during internal inspections | J16: AP: I would focus the mitigation action on getting the information on harvested volume through out the year (monthly basis) instead of once a year during internal inspections Changed
C17: Group Certification | E17: Record keeping | G17: no | H17: All | I17: No additional action needed | J17: Anneke: how can you reduce this risk?
A18: 6 | C18: Group Certification | E18: Product separation | F18: Do group members often rely on farm operators to manage their farm? | G18: yes | H18: all | I18: Guarantee that the farm manager is the same year after year through the internal inspections and that they are aware of the traceability requirements. Check if farm operator also manages non-certified farms and if so, encourage to include them in the certified group as well. Always invite the farm operator to trainings (on traceability and other topics) | J18: AP: mitigation action could be to always invite the farm operator to trainings (on traceability and other topics), unless already in the standard Changed
C19: Group Certification | E19: Product separation | G19: no | H19: All | I19: No additional action needed | J19: Anneke: not the right place to put it in the risk assessment?
A20: 7 | B20: Productivity & profitability | C20: Group Certification | E20: Optimum yield | F20: Is the average yield of the certified crop of the group members at or above the average yield for the crop in your country? | G20: Yes | H20: All | I20: No additional action needed | J20: AP: is a definition of 'optimum yield' needed? RR: Changed the formulation of the question
C21: Group Certification | E21: Optmimum yield | G21: No/Don't know | H21: All | I21: Train staff to recognise & prioritise production constraints in field Identify the main productivity constraints in the field Establish trials and business model farms to showcase impact of rejuvenation, fertilisation and good pest and disease control | J21: AP: production or productivity constraints? RR: productivity, so also costs of production
A22: 8 | C22: Group Certification | E22: Access to inputs and knowledge | F22: Do all group members have access to agricultural inputs and adequate knowledge to optimize productivity? | G22: Yes | H22: All | I22: No additional action needed
C23: Group Certification | E23: Access to inputs and knowledge | G23: No/Don't know | H23: All | I23: Identify the main needs among group members regarding inputs and knowledge. Support group members with training on finance, business management and understanding production costs and net income (self-selected requirement 1.4.5) If needed, facilitate accesss to financial services (e.g. loans for farm investments) (self-selected requirement 1.4.5)
A24: 9 | C24: Group Certification | E24: Living income | F24: Do you estimate that all group members earn a decent income with the production of the certified crop? | G24: Yes | H24: All | I24: No additional action needed
C25: Group Certification | E25: Living income | G25: No/Don't know | H25: All | I25: Assess the total net income for a representative sample of group member households, using the Living Income benchmark (self-selected requirement 1.9.6) Support group members with training on finance, business management and understanding production costs and net income (self-selected requirement 1.4.5) If needed, facilitate accesss to financial services (e.g. loans for farm investments) (self-selected requirement 1.4.5) Support group members to make informed decisions on income diversification strategies, e.g. other income generating activities, product upgrading (self-selected requirement 1.4.6)
B26: Farming practices
A27: 10 | B27: 2.6 Agrochemical management | C27: Group Certification | D27: Pesticides use | E27: Use of prohibited agrochemicals | F27: Review the Agrochemicals Rainforest Alliance Prohibited List : Is it common practice in the region to use one or more of the agrochemicals from the Rainforest Alliance Prohibited List, including on the non-certified crops on the farm? | G27: Yes | H27: All | I27: In case use of banned pesticide use is found during the external audit, the CB may issue a non-certification. To avoid this, include in your management plan: Group member training on the prohibition of the use of banned agrochemicals, and which ones those are. Group members training on the risk of using highly hazardous agrochemicals. Verify use of banned agrochemicals in internal inspections. Monitoring of use of agrochemicals during application period. Set up system to collect stocks of banned agrochemicals from the group members. Note: farmers that have used banned agrochemicals for the harvest to be certified cannot be included in the certification and have to wait for the next harvest cycle to apply again. | J27: AP: I would separate the 2 questions, answering a Yes/No is confusing here. Changed
C28: Group Certification | D28: Pesticides use | E28: Use of prohibited agrochemicals | G28: no | H28: All | I28: No additional action needed
B29: 2.6 Agrochemical management | C29: Large | D29: Pesticides use | E29: Use of prohibited agrochemicals | F29: Review the Agrochemicals Rainforest Alliance Prohibited List : do you use one or more of the agrochemicals from the Rainforest Alliance Prohibited List, including on the non-certified crops on the farm? | G29: Yes | H29: All | I29: In case use of prohibited pesticide use is found during the external audit, the CB may issue a non-certification. Farms that have used pesticides agrochemicals for the harvest to be certified cannot be included in the certification and have to wait for the next harvest cycle to apply again. If you haven't, then ensure ban of use of prohibited agrochemicals by implementing: Get rid of all prohibited agrochemicals prohibited agrochemicals, and which ones those are. Staff training on the risk of using highly hazardous agrochemicals. Verify use of prohibited agrochemicals in internal inspections. Monitoring of use of agrochemicals during application period.
C30: Large | D30: Pesticides use | E30: Use of prohibited agrochemicals | G30: no | H30: All | I30: No additional action needed
A31: 11 | B31: 2.6 Agrochemical management | C31: Group Certification | D31: Pesticides use | E31: Use of prohibited agrochemicals | F31: If you are certified by other standards, are there any RA banned agrochemicals that are not banned under these other standards? | G31: Yes | H31: All | I31: In case use of prohibited pesticide is found during the external audit, the CB may issue a non-certification. To avoid this, include in your management plan: Group member training on the ban of the use of prohibited agrochemicals, and which ones those are. Group members training on the risk of using highly hazardous agrochemicals. Verify use of prohibited agrochemicals in internal inspections. Monitoring of use of agrochemicals during application period. Set up system to collect stocks of prohibited agrochemicals from the group members. Note: farmers that have used prohibited agrochemicals for the harvest to be certified cannot be included in the certification and have to wait for the next harvest cycle to apply again. | J31: AP: I would separate the 2 questions, answering a Yes/No is confusing here. Changed
C32: Group Certification | D32: Pesticides use | E32: Use of prohibited agrochemicals | G32: no | H32: All | I32: No additional action needed
B33: 2.6 Agrochemical management | C33: Large | D33: Pesticides use | E33: Use of prohibited agrochemicals | F33: If you are certified by other standards, are there any Rainforest Alliance prohibited agrochemicals that are not banned under these other standards? | G33: Yes | H33: All | I33: In case use of prohibited pesticide use is found during the external audit, the CB may issue a non-certification. Farms that have used prohibited agrochemicals for the harvest to be certified cannot be included in the certification and have to wait for the next harvest cycle to apply again. If you haven't, then ensure ban of use of prohibited agrochemicals by implementing: Get rid of all prohibited agrochemicals. Staff training on the ban of the use of prohibited agrochemicals, and which ones those are. Staff training on the risk of using highly hazardous agrochemicals. Verify use of prohibited agrochemicals in internal inspections. Monitoring of use of agrochemicals during application period.
C34: Large | D34: Pesticides use | E34: Use of prohibited agrochemicals | G34: no | H34: All | I34: No additional action needed
A35: 12 | B35: 2.6 Agrochemical management | C35: Group Certification | D35: Pesticides use | E35: Amount of pesticide applications | F35: Is it common practice that producers firstly try biological, physical, and other non-chemical control methods for pest control before using agrochemicals? | G35: Yes | H35: All | I35: No additional action needed
C36: Group Certification | D36: Pesticides use | E36: Amount of pesticide applications | G36: No | H36: All | I36: Pay special attention to compliance with chapter 2.5 of the Agricultural Standard. In case needed, contact a local university or extension service for development of the Integrated Pest Management procedure. Identify sources for the purchase of lower toxicity agrochemicals as well as non-chemical pest control products. Make sure all members have the necessary knowledge and skills to apply Integrated Pest Management. Train members on record keeping. Monitor use of agrochemicals and application of IPM procedure by group members (including record keeping), during application time.
A37: 13 | C37: Group Certification | D37: Pesticides use | E37: Use of PPE | F37: Is it common practice that group members or their workers use Personal Protective Equipment (PPE) for application of agrochemicals? | G37: yes | H37: All | I37: No additional action needed | J37: AP: don't use the abbreviation PPE but the entire words I would rephrase 'Is it common practice that workers of group members use PPE for application of agrochemicals? ' to 'Is it common practice that group members or their workers use PPE for application of agrochemicals? Changed
C38: Group Certification | D38: Pesticides use | E38: Use of PPE | G38: no | H38: All | I38: Ensure availability of sufficient PPE for all those applying agrochemicals. Develop and implement management policies on the correct use of PPE. Make sure all those applying agrochemicals are trained on correct application of the agrochemicals and PPE. Group members trained on the risk of using highly hazardous agrochemicals. Explore the option of developing spray teams to replace agrochemical application by individual group members. Monitor the use of PPEs during application time. | J38: AP: Remove the part 'for group', this question will only populate for group certification Why 'training on banned agrochemicals' as a mitigation measure for this point? Changed
C39: Large | D39: Pesticides use | E39: Use of PPE | F39: Are all workers spraying agrochemicals using the correct Personal Protective Equipment (PPE) at all times when they apply agrochemicals? | G39: Yes | H39: All | I39: No additional action needed
C40: Large | D40: Pesticides use | E40: Use of PPE | G40: No | H40: All | I40: Make an assessment among the workers on the reasons for not using PPE. Use the outcomes of this assessment to define the measures. Develop and implement management policies on the correct use of PPE. Make sure all those applying agrochemicals are trained on correct application of the agrochemicals and PPE. Ensure availability of sufficient PPE for all those applying agrochemicals. Monitor the use of PPEs during application time.
A41: 14 | B41: 2.4 Soil conservation | C41: All | E41: Erosion | F41: Are there any areas that have a slope steeper than 1m rise over 3m run over an area >0.1ha? | G41: Yes | H41: All | I41: Implement measures to protect against erosion, including planting of native groundcover, contour planting, living barriers and drainage/dewatering systems.
C42: All | E42: Erosion | G42: No | H42: All | I42: Make sure no gully forming is happening and that organic top layer is not washed
A43: 15 | C43: All | E43: Waterlogging | F43: Are there any areas within the farm / group member farms with long periods of standing water after rain? | G43: Yes | H43: All | I43: Implement measures to improve drainage through physical measures, digging drainage trenches, or improving soil structure to increase the soil’s potential to take up water and store it
C44: All | E44: Waterlogging | G44: No | H44: All | I44: No additional action needed
A45: 16 | C45: All | E45: Waterlogging | F45: Is high ground water level a problem in certain areas? | G45: Yes | H45: All | I45: Assess whether the area is suitable for crop cultivation and consider what crops are suitable for these areas. In some cases: improve drainage and/or conserve protective vegetation
C46: All | E46: Waterlogging | G46: No | H46: All | I46: No additional action needed
A47: 17 | C47: All | E47: Drought | F47: Is drought (becoming) a limiting factor for crop production? | G47: Yes | H47: All | I47: Keep soil covered to reduce evapotransperation. Assure deep-rooting crops are used. Consider mixed cropping, preferable with shrub / tree crops Provide shade When irrigating: assure water losses are minimised and check if lime/salt crusts are found in upper layer. If so, consult a soil institute.
C48: ALl | E48: Drought | G48: No | H48: All | I48: Make sure soil structure is conserved to avoid compaction
B49: Working Conditions
A50: 18 | B50: 1.5 Grievance mechanism | C50: All | E50: Grievance Mechanism | F50: Is information about the grievance mechanism and the assess and address committee visible and accessible to all workers? | G50: Yes | H50: All | I50: Check & update public display regularly to make sure information is still correct, visible and accessible to all; including languages of local and temporary staff
C51: All | E51: Grievance Mechanism | G51: No | H51: All | I51: Ensure that producers and workers have access to practical information in their language about how and where they can access the grievance mechanism and the assess and address committee when they have a grievance that they want to be resolved.
A52: 19 | B52: 3.1 A&A | C52: All | E52: Equal opportunities & prevention of discrimination | F52: Are any of the following populations present on or near the farm or group: - Migrant workers (foreign or from within the country) - Specific ethnic minorities (any ethnicities which are not the largest ethnicity within the workforce) -Indigenous people (where applicable) -People that do not speak the dominant language in the country & region | G52: yes | H52: All | I52: Assess whether members of these populations are working on the farm or contracted by group members. Make sure that group and farm management is aware of the kind of populations that are present and registers their specifics: kind of population, number (estimation), language and other where relevant
C53: All | E53: Equal opportunities & prevention of discrimination | G53: no | H53: All | I53: No additional action needed
A54: 20 | C54: Large | E54: Equal opportunities & prevention of discrimination | F54: Do hiring procedures follow rules and regulations to prevent discriminatory practices? | G54: Yes | H54: All | I54: No additional action needed
G55: No | H55: All | I55: Make sure all job vacancies are announced widely, in appropriate languages
A56: 21 | C56: Large | E56: Workplace Violence and Harassment prevention | F56: Has the management taken any targeted action to prevent violence and harassment (including sexual harassment)? | G56: Yes | H56: All | I56: No additional action needed
C57: Large | E57: Workplace Violence and Harassment | G57: No | H57: All | I57: Implement at least one of the following measures: - Training of trainers, technical staff and other persons in direct contact with members and workers on respectful behavior and concepts of workplace violence and harassment - training of workers on the topic on respectful behavior and concepts of workplace violence and harassment Please note: in most cases workplace violence and harassment will relate to experiences faced by women. However risks are also faced by men. Ensure your answers cover risks in relation to all workers regardless of gender.
A58: 22 | C58: Group Certification | E58: Age verification | F58: Is there a risk that farm group members are not validating hired workers' ages at the time they are appointed? | G58: No | H58: All | I58: Check with internal inspections the small farms' workers registration on year of birth
C59: Group Certification | E59: Age verification | G59: Yes | H59: All | I59: 1) Communicate to all farmers that have hired workers, how to verify the age of all new hires at the workplace, including those supplied by labour providers. 2) Verification of age should be based on identity documents, school and medical records or other verifiable forms of identification proof. 3) Check with internal inspection the data in the workers list
C60: Large | E60: Age verification | F60: Does the site require proof of age and retain documentation when hiring workers? | G60: Yes | H60: Medium & High According to RA risk maps on Child Labor | I60: Conduct a review once per year to verify that there are identity documents on file for all workers under the age of 18; | J60: AP:'Country/sector risk context applicability' => specify that we are using the child labor risk maps (not visible for the producer but needed for technology)
C61: Large | E61: Age verification | G61: Yes | H61: Low | I61: No additional action needed
C62: Large | E62: Age verification | G62: No | H62: All | I62: 1) Verify the ages of all young workers on site while respecting children’s protection and privacy rights 2) Develop and implement a system to verify the identity and age of all new hires at the workplace, including those supplied by labour providers. 3) Ensure the system bases its decisions on verifiable forms of identification proof, including identity documents, school and medical records. Include in the age verification system school enrolment & status. 4) Ensure information about age from which children can work and circumstances under which are clearly communicated to staff and workers.
A63: 23 | C63: Group Certification | E63: Hazardous work | F63: Has the group management listed any tasks, processes or other working conditions that could be hazardous to young workers? | G63: Yes | H63: Low | I63: Communicate this list to all group members that hire young workers | J63: AP:'Country/sector risk context applicability' => specify that we are using the child labor risk maps (not visible for the producer but needed for technology)
C64: Group Certification | E64: Hazardous work | G64: No | H64: Low | I64: List the tasks and processes that involve hazardous working conditions ; communicate this to all group members
C65: Group Certification | E65: Hazardous work | G65: Yes | H65: Medium & High According to RA risk maps on Child Labor | I65: 1) List the hazardous tasks / processes. 2) Communicate this list to all group members and; 3) through training and child labor monitoring, ensure members are aware that workers younger than 18 cannot perform these hazardous tasks. 4) check with internal inspections
C66: Group Certification | E66: Hazardous work | G66: No | H66: Medium & High According to RA risk maps on Child Labor | I66: 1) Develop a list of tasks and work processes – aligned with any relevant national policy - from which under 18s would be banned from performing. Ensure the list covers jobs that involve hazardous substances, dangerous equipment or heavy lifting. The list of tasks should also make clear that underage workers are prohibited from performing work at night or during school hours. 2) Review the list every season to ensure list is up to date with national policy. 3) Communicate to all group members what tasks are and are not hazardous 4) Clarify to group members that work by under 18s must be performed in accordance with the list 5) clarify internal steps and potential internal sanctions where it is discovered that a member is permitting under-18s to perform hazardous work.
C67: Large | D67: Farm has formally registered workers aged under the age of 18 | E67: Hazardous work | F67: Has the farm management listed any tasks, processes or other working conditions taking place on the farm that could be hazardous to young workers? | G67: Yes | H67: All | I67: List the hazardous tasks / processes and ensure all supervisors are aware that workers younger than 18 cannot perform these. | J67: AP: 'Farm has formally registered workers aged under the age of 18' is part of the profile completion 1 (or do we expect the producer to answer that in the risk assessment tool)? RR: Is that indeed included in profile completion 1? I would not agree to put it in profile completion, since this can change at any time...
C68: Large | D68: Farm has formally registered workers aged under the age of 18 | E68: Hazardous work | G68: No | H68: Low | I68: 1) Develop a list of tasks and work processes – aligned with any relevant national policy or law - that under 18s cannot perform. Ensure the list covers jobs that involve hazardous substances, dangerous equipment or heavy lifting. The list of tasks should also make clear that underage workers are prohibited from performing work at night or during school hours. 2) Review the list every season to ensure list is up to date with national policy. 3) Ensure supervisors are aware of this list and pro-actively prevent young workers from being involved in hazardous tasks
C69: Large | D69: Farm has formally registered workers aged under the age of 18 | E69: Hazardous work | G69: No | H69: Medium & High According to RA risk maps on Child Labor | I69: 1) Develop a list of tasks and work processes – aligned with relevant national policy or law - that under 18s are banned from performing. Ensure the list covers jobs that involve hazardous substances, dangerous equipment, working at height, and/ or heavy lifting. The list of tasks should also make clear that young workers are prohibited from performing work at night. 2) Review the list every season to ensure list is up to date with national law and policy 3) Conduct a health and safety review/risk assessment of all major farm activities to identify the major hazards, plus proposed steps to remove or reduce exposure for young workers [e.g. remove dangers of machinery, sharp tools, harmful substances, work at height, carrying heavy loads, working at height and working at night). 4) Ensure all supervisors are aware of the hazardous tasks list and which tasks young workers are allowed to perform. 5) conduct awareness with your workers, especially those working in teams with young workers, about what tasks young workers are allowed to perform and from which age
A70: 24 | C70: Group Certification | E70: Education | F70: Is there a risk that school-going aged children of group staff, or group members, or children of workers, do not attend school within a safe walking / traveling distance? (Use the map of the group area to assess this) | G70: Yes | H70: All | I70: 1) create awareness about importance of education with group members & discuss ways with members how group can support children's education 2) Identify in internal inspections if there are group members whose children have a higher risk of not attending school due to larger distance or other accessibility issues | J70: AP: why not group members' children? Changed
C71: Group Certification | E71: Education | G71: No | H71: Low | I71: No additional action needed
C72: Group Certification | E72: Education | G72: No | H72: Medium & High According to RA risk maps on Child Labor | I72: 1) create awareness about importance of education with group members & discuss ways with members how group can support children's education 2) Identify in internal inspections if there are group members whose children have a higher risk of not attending school due to larger distance or other accessibility issues
C73: Large | D73: Families living on-site | E73: Education | F73: Are children living on-site and of school-going age going to school within safe walking distance or at reasonable traveling distance using safe transport? | G73: No | H73: Low | I73: Collaborate with the local department of education and local NGOs to support access to education for children living on site; consider arranging safe transport or advocating for sattelite classrooms on site for younger children, where possible administered by the local education department; provide support to workers whose children are not in school so that they can access education; | J73: AP: is 'Families living on-site?' part of profile completion 1 (or do we expect the producer to answer that in the risk assessment tool)? RR: Yes, so only if they indicated this with YES in the profile completion 1, this question appears in the risk assessment
C74: Large | D74: Families living on-site | E74: Education | G74: No | H74: Medium & High According to RA risk maps on Child Labor | I74: Collaborate with the local department of education and local NGOs to support access to education for children living on site; consider arranging safe transport or advocating for sattelite classrooms on site for younger children, where possible administered by the local education department
C75: Large | D75: Families living on-site | E75: Education | G75: Yes | H75: Medium & High According to RA risk maps on Child Labor | I75: Coordinate with the local school and request to be informed should any of the children living on site drop out or attend very irregularly [ensure this process is aligned with national law on data protection]
C76: Large | D76: Families living on-site | E76: Education | G76: Yes | H76: Low | I76: No additional action needed
A77: 25 | C77: Large | E77: Family workers | F77: Is there a risk that under-18s perform work on the farm? | G77: Yes | H77: Medium & High According to RA risk maps on Child Labor | I77: Set up child labour monitoring process 1)Appoint member of staff to supervise the work of all under 18s registered as working on the farm and to monitor the under 18s health and school attendance 2) the responsible staff member checks locations where under-18 olds work, to ensure young workers are not undertaking hazardous tasks and not engaged during school hours or at night/ without sufficient periods for rest in between school days. Frequency should depend on level of risk (e.g. the higher the risk, the more frequent the monitoring) Record findings of these visits. 3) Follow the RA Remediation tool when removing children from child labor, ensuring care is taken to minimise damage to families when they miss out on income. Supervisors and workers are informed about policy of hiring young workers, including the age from which children can be hired individually, in accordance with the Rainforest Alliance Standard as well as the national law.
C78: Large | E78: Family workers | G78: Yes | H78: Low | I78: Supervisors and workers are informed about policy of hiring young workers, including the age from which children can be hired individually, in accordance with the Rainforest Alliance Standard as well as the national law.
C79: Large | E79: Family workers | G79: No | H79: Medium & High According to RA risk maps on Child Labor | I79: Appoint child labor monitors [sufficient to provide an effective degree of coverage and visibility across farm] to maintain oversight over children’s working, health and school attendance patterns and to maintain awareness of the group child labor policy across inspectors, farmers, young worker supervisors and hired workers themselves.
C80: Large | E80: Family workers | G80: No | H80: Low | I80: Inform supervisors and workers about policy of hiring young workers, including the age from which children can be hired individually, in accordance with the Rainforest Alliance Standard as well as the national law.
C81: Group Certification | E81: Family workers | F81: Is there a risk that under-18s perform work on any of the farms within the group? | G81: Yes | H81: Medium & High According to RA risk maps on Child Labor | I81: 1) Inform members about the policy regarding family child work, including the age from which children can support their parents, and from which age children can be hired individually to conduct light work, in accordance with the Rainforest Alliance Standard as well as the national law. 2) Explain the assess and address model to members to promote transparency about child labor risks and support solutions to mitigate the risk
C82: Group Certification | E82: Family workers | G82: Yes | H82: Low | I82: 1) Inform members about the policy regarding family child work, including the age from which children can support their parents, and from which age children can be hired individually to conduct light work, in accordance with the Rainforest Alliance Standard as well as the national law. 2) Explain the assess and address model to members to promote transparency about child labor risks and support solutions to mitigate the risk
C83: Group Certification | E83: Family workers | G83: No | H83: Medium & High According to RA risk maps on Child Labor | I83: Appoint child labor monitors [sufficient to provide an effective degree of coverage and visibility across farms in the producer group] to maintain oversight over children’s working, health and school attendance patterns and to maintain awareness of the group child labor policy across inspectors, farmers, young worker supervisors and hired workers themselves.
C84: Group Certification | E84: Family workers | G84: No | H84: Low | I84: No additional action needed
A85: 26 | C85: Group Certification | E85: Labour providers | F85: Is it likely that group members use labour providers to recruit workers? | G85: No | H85: All | I85: No additional action needed
C86: Group Certification | E86: Labour providers | G86: Yes | H86: Low | I86: 1. Check the labor providers that are active in the region, and their compliance with legal requirements. 2. Raise awareness among group members on how to work with labor providers, which labor providers should be avoided, and that there needs to be a contract in place (if more than 5 year round workers) or that the name contract and registration number need to be recorded (group members with less than 5 workers) 3. Check with internal inspections with which labor providers groups members are working (if any) and under what conditions.
C87: Group Certification | E87: Labour providers | G87: Yes | H87: Medium & High According to RA risk maps on Forced Labor | I87: 1. Check the labor providers that are active in the region, and their compliance with legal requirements. 2. Raise awareness among group members on how to work with labor providers, which labor providers should be avoided, and that there needs to be a contract in place (if more than 5 year round workers) or that the name contract and registration number need to be recorded (group members with less than 5 workers) 3. Check with internal inspections with which labor providers group members are working (if any) and under what conditions. 4. Verify whether the workers recruited through labor providers are treated equally with other workers and provided the same information about their protections under the RA standard.
A88: 27 | C88: All | E88: Labour providers | F88: Does the farm/group management use labour providers to recruit any workers? | G88: No | H88: All | I88: No additional action needed
C89: All | E89: Labour providers | G89: yes | H89: Low | I89: 1. Make sure that the labor providers used are licensed or certified by the appropriate government authority, if one exists.
C90: All | E90: Labour providers | G90: yes | H90: Medium & High According to RA risk maps on Forced Labor | I90: 1. Ensure that farms have written contracts with each labor provider, requiring that labor providers abide by RA worker protection standards. 2. When possible, farms should directly contract workers who are recruited by labor providers. 3. For workers whose direct employer is a labor provider, check the Assess & Address monitoring system periodically with some of these workers to ensure that their pay, working conditions, etc. are as promised by the labor provider. 4. Make sure that the workers recruited through labor providers are treated equally with other workers and provided the same information about their protections under the RA standard. 5. The Assess & Address monitoring system should periodically check with workers who are recruited through labor providers, to see if they owe any debts related to recruitment fees. If so, the farm should negotiate with the labor provider full repayment of these fees to the worker. 6. Management should assign responsibility to one or more members of staff to oversee labor providers' compliance and the above measures. Farms should stop working with labor recruiters that do not meet these expectations.
A91: 28 | C91: Group Certification | E91: Wage payment practices | F91: Is it likely that group members pay their workers by volume/piece rate? | G91: No | H91: All | I91: No additional action needed
C92: Group Certification | E92: Wage payment practices | G92: Yes | H92: All | I92: Training/awareness raising of group members on how to assure that workers receive a fair payment
C93: All | E93: Wage payment practices | F93: Are workers paid by volume/piece rate? | G93: Yes | H93: All | I93: 1. Farm-group management must ensure that workers have written or verbal contracts in place according to requirement 3.3. 2. When calculated by volume, workers' pay must equal at least the minimum wage based on a 48-hour working week or national legal working hours limit. 3. Deductions from wages for costs such as employer-provided housing or food must only be taken with workers' consent. 4. Ensure that personnel responsible for wage payment are correctly trained in calculations and requirements.
C94: All | E94: Wage payment practices | G94: No | H94: All | I94: No additional action needed
A95: 29 | C95: Large | E95: Freedom of movement | F95: Are there security guards on the farm? | G95: No | H95: All | I95: No additional action needed
C96: Large | E96: Freedom of movement | G96: Yes | H96: All | I96: 1. Communicate to workers of their rights under the law to freely leave the job. This can be done through their contracts, information posted in the workplace, a workers' organization, one of the farm's committees, or other means. 2. For workers living on the farm, farms should communicate their rights to freedom of movement on and off the farm outside working hours. 3. Train security guards on rights of workers, eg that workers living on the farm have the right of movement on and off the farm outside working hours. | J96: AP: (I am not a specialist but) reading the mitigation measures, it seems that if the answer is Yes, they are in an illegal situation (restricting freedom of movement)?? Changed question and included other measure
A97: 30 | C97: All | E97: Prison/military labor | F97: Are any workers recruited/provided to the farm/group by military or prison officials? | G97: No | H97: All | I97: No additional action needed
C98: All | E98: Prison/military labor | G98: Yes | H98: All | I98: 1. Military officials mobilizing military personnel to perform agricultural labor is a form of forced labor. Make sure that farms do not utilize this type of labor. 2. Enusre that any prisoners working on the farm have freely provided their consent to work. 3. Ensure that prison labors are treated the same as all other workers with respect to contracts, pay, working conditions, and all other worker protections in the RA standard.
A99: 31 | C99: Large | E99: Deposit or document retention | F99: Do workers give any money (such as deposits) or documents (such as passports) to farm management or labor providers? | G99: No | H99: All | I99: No additional action needed
C100: Large | E100: Deposit or document retention | G100: Yes | H100: All | I100: 1. Enusre that workers are not required to pay any type of deposit or provide any personal document to management, other than to confirm identity at the time of hiring. 2. In instances where workers prefer to provide documents or other belongings to management for safe keeping, ensure that workers have permanent, unrestricted access to these locations.
A101: 32 | B101: 1.6 Gender | C101: All | E101: Gender Commitment from Leadership | F101: Has the group/farm management already been taking actions to address gender and/or women empowerment for at least more than a year? | G101: yes | H101: All | I101: Continue the actions
...

Sheet Page de couverture
A1: Annexe S03 :
A2: Outil de Base d’Evaluation des Risques
A3: Document SA-S-SD-4a
A4: Version 1.3
A5: FR
A6: Traduction publiée le 11 may 2023
A7: Contraignant à partir du 1er juillet 2023
F9: Nom du document : | J9: Date de la première publication : | L9: Expire le :
F10: Annexe S03: Outil de Base d’Evaluation des Risques | J10: 6 février 2023 | L10: Jusqu’à nouvel ordre
F11: Lié à :
F12: SA-S-SD-1 Norme pour l’agriculture durable, exigences applicables aux exploitations agricoles SA-S-SD-2 Norme pour l’agriculture durable 2020 de Rainforest Alliance, exigences applicables à la chaîne d'approvisionnement SA-S-SD-23 Annexe Chapitre 5 : Social
O13: À propos de l’Annexe S03 : L’outil d’évaluation des risques contient les fichiers suivants :
O14: - SA-S-SD-4a Annexe S03: Outil de Base d’Evaluation des Risques - SA-S-SD-4b Annexe S03: Partie 1.3.5. Évaluation approfondie des risques de changement climatique - SA-S-SD-4c Annexe S03: Partie 1.6.3. Évaluation approfondie des risques liés au genre - SA-S-SD-4d Annexe S03: Partie 5.1.5 Évaluation approfondie et traitement des risques
F15: Remplace :
F16: SA-S-SD-4-V1.1FR Annexe S3 : Outil d’évaluation des risques
F17: Applicable aux :
F18: Titulaires de certificat
F19: Pays/Région :
F20: Tous
F21: Produit agricole : | J21: Type de certification :
F22: Tous les produits agricoles du champ d’application du système de certification de Rainforest Alliance ; veuillez voir les Règles pour la certification. | J22: Titulaires de certificat
F25: Décharge de responsabilité concernant la traduction
F26: Pour toute question liée à la signification précise des informations contenues dans la traduction, veuillez vous référer à la version officielle en anglais pour en obtenir la clarification. Toute divergence ou différence dans la signification engendrée par la traduction n’est pas contraignante et n’a pas d’effet sur la certification ou les audits.
A30: © 2023 Rainforest Alliance. Tous droits réservés. | F30: Plus d’informations ?
F31: Pour plus d’information sur Rainforest Alliance, visitez le site www.rainforest-alliance.org ou contactez info@ra.org
F33: Toute utilisation de ce contenu, y compris la reproduction, la modification, la distribution ou la republication, sans le consentement écrit préalable de Rainforest Alliance est strictement interdite.

Sheet Outil d’orientation pour l’éval

Sheet Overview and guidance
A2: Initial Risk Assessment
A3: Initial GAP assessment | B3: GAP assessment: the GAP assessment is an assessment of the GAPs between the current state of a Certificate Holder (estate or group) and the requirements of the Rainforest Allianca. This assessment is based on the Rainforest Alliance standard. This assessment is not mandatory, however will help you identify the areas that need to be worked on and the amount of work needed still to be ready for the certification audit.
A4: Self Assessment
A5: Mitigation Actions

Sheet Indiv. cert. Risk Assessment
B2: Chapter | C2: Theme | D2: Which farmers does this apply to? | E2: Issue | F2: Question applicable to (Group Management, medium/large estate management, group member during internal inspections) | G2: Mitigation self-assessment – risk questions | H2: Answer parameter | I2: Country/sector risk context applicability | J2: Mitigation actions to be included in the Management Plan | K2: Comments
B3: A. Management.
C4: Traceability | D4: All farm businesses | E4: Traceability procedure | F4: Management | G4: Do you/will you make use of intermediaries/subcontractors* in your supply chain? | H4: Yes | J4: Set up a clear traceability flow, that includes the documented and physical traceability rules for all actors (subcontractors/intermediary, processing units, CH management etc.). Train all actors on your traceability procedure. Monitor traceability and record keeping at intermediaries/subcontractors (during the harvest period). (Part of the Internal inspection (TBD))
C5: Traceability | D5: All farm businesses | E5: Traceability procedure | F5: Management | G5: Do you/will you make use of intermediaries/subcontractors* in your supply chain? | H5: No | J5: Set up a clear traceability flow, that includes the documented and physical traceability rules for all actors (farmer, collection centers, CH management).
B6: B. Farming Practices
C7: Inputs | D7: All farm businesses | F7: Management | G7: Review the Rainforest Alliance list of banned agrochemicals. Do you use one or more of the agrochemicals from the pesticide watchlist? | J7: Set up an IPM.
C8: Inputs | D8: All farm businesses | F8: Management | G8: (RR:) Are you applying pesticides more than XX times per year? (Define per crop what is an expected number of times to apply pesticides per year) | J8: Define strategy to reduce use of pesticides. Stress use of PPE. High risk for MRL.
A9: 1 | B9: 4. Environment | C9: Erosion | D9: All | E9: Steep Slopes | F9: All | G9: Are there any areas that have a slope greater than 1m rise over 3m run over an area >0.1ha? | H9: Yes | I9: All | J9: Implement measures to protect against erosion, including planting of native groundcover.
A10: 1 | B10: 4. Environment | C10: Erosion | D10: All | E10: Steep Slopes | F10: All | G10: Are there any areas that have a slope greater than 1m rise over 3m run over an area >0.1ha? | H10: No | I10: All | J10: No further action
B11: C. Working Conditions (social chapter or "workers and communities" which was our proposal)
C12: General | D12: There are 20 or more employees engaged at any point during the growing season | E12: Structure | G12: Does the farm have a trained committee/person in charge of the work around Assess and Address within the RA Standard? Is there a trained Grievance Committee (criterion 1.5)? Is there a trained Gender Committee (1.6)? | H12: Yes | I12: All | J12: No further action
C13: General | D13: There are 20 or more employees engaged at any point during the growing season | E13: Structure | G13: Does the farm have a trained committee/person in charge of the work around Assess and Address within the RA Standard? Is there a trained Grievance Committee (criterion 1.5)? Is there a trained Gender Committee (1.6)? | H13: No [to any] | I13: all | J13: Committee/person are (s)elected and committee set up; they participate in the A&A online training module / gender online training module and / or grievance mechanism training module as applicable ensuring all committees are set up and trained.
C14: General | D14: There are 20 or more employees engaged at any point during the growing season | E14: Skills/ capabilities | G14: Have supervisors and management experience / knowledge on dealing with cases of child labour, forced labour, discrimination and workplace violence/harassment? | H14: Yes | J14: No further actions
C15: General | D15: There are 20 or more employees engaged at any point during the growing season | E15: Skills/ capabilities | G15: Have supervisors and management experience / knowledge in dealing with cases of child labour, forced labour, discrimination and workplace violence/harassment? | H15: No | I15: All | J15: Management representatives / supervisors undergo training on assess and address topics
C16: General | D16: There are 20 or more employees engaged at any point during the growing season | E16: Public communication about Grievance Mechanism and Assess and Address Committee and its responsibilities | G16: Is information about the grievance mechanism and the assess and address committee visible and accessible to all workers? | H16: Yes | I16: All | J16: Check & update public display regularly to make sure information is still correct, visible and accessible to all; including languages of local and temporary staff
C17: General | D17: There are 20 or more employees engaged at any point during the growing season | E17: Public communication about Grievance Mechanism and Assess and Address Committee and its responsibilities | G17: Is information about the grievance mechanism and the assess and address committee visible and accessible to all workers? | H17: No | I17: All | J17: Ensure that producers and workers have access to practical information in their language about how and where they can access the grievance mechanism and the assess and address committee when they have a grievance that they want to be resolved.
C18: Discrimination | D18: All farm businesses | E18: Prevention of discrimination | G18: Do hiring procedures follow rules and regulations to prevent discriminatory practices? | H18: yes | I18: All | J18: No further actions
C19: Discrimination | D19: All farm businesses | E19: Prevention of discrimination | G19: Do hiring procedures follow rules and regulations to prevent discriminatory practices? | H19: No | I19: Low | J19: - Make sure all job vacancies are announced widely, in appropriate languages
C20: Discrimination | D20: All farm businesses | E20: Prevention of discrimination | G20: Do hiring procedures follow rules and regulations to prevent discriminatory practices? | H20: No | I20: Medium, High | J20: - Conduct in-person training of managers and supervisors on unconscious bias and on avoiding any kind of discriminatory decision in relation to hiring, working conditions, pay, benefits, training, promotion, termination, redundancy - develop procedures to prevent discrimination during hiring, between others: organize job interviews with more than one interviewer, preferibly of different genders; widespread announcement of job vacancies in appropriate languages; job description should not exclude certain groups of people
C21: Discrimination | D21: All farm businesses | E21: Equal opportunities & prevention of discrimination | G21: If any of the following groups are present at the farm, have you taken actions to fairly represent them amongst management and supervisory staff? These groups could include: -Women -> will go to gender requirement -Migrants (foreign or from within the country) - Specific ethnic minority groups (any ethnicities which are not the largest ethnicity within the workforce) -Indigenous groups (where applicable) -Groups whose members do not speak the dominant language in the country & region | H21: Yes | I21: All | J21: No further action
C22: Discrimination | D22: All farm businesses | E22: Equal opportunities & prevention of discrimination | G22: If any of the following groups are present at the farm, have you taken actions to fairly represent them amongst management and supervisory staff? These groups could include: -Women -> will go to gender requirement -Migrants (foreign or from within the country) - Specific ethnic minority groups (any ethnicities which are not the largest ethnicity within the workforce) -Indigenous groups (where applicable) -Groups whose members do not speak the dominant language in the country & region | H22: No | I22: Low | J22: publish vacancies for management and supervisory functions in a language(s) and in places accessible for all
C23: Discrimination | D23: All farm businesses | E23: Equal opportunities & prevention of discrimination | G23: If any of the following groups are present at the farm, have you taken actions to fairly represent them amongst management and supervisory staff? These groups could include: -Women -> will go to gender requirement -Migrants (foreign or from within the country) - Specific ethnic minority groups (any ethnicities which are not the largest ethnicity within the workforce) -Indigenous groups (where applicable) -Groups whose members do not speak the dominant language in the country & region | H23: No | I23: Medium, High | J23: - include unconscious bias and other anti discriminatory practices in the training and awareness raising of staff and management as required in 3.1.1 AND - publish vacancies for management and supervisory functions in a language(s) and in places accessible for all
C24: Workplace Violence and Harassment | D24: All farm businesses | E24: Workplace Violence and Harassment | G24: Has management taken any targeted action to prevent workplace violence and harassment (including sexual harassment)? | H24: Yes | I24: All | J24: No further action
C25: Workplace Violence and Harassment | D25: All farm businesses | E25: Workplace Violence and Harassment | G25: Has management taken any targeted action to prevent workplace violence and harassment (including sexual harassment)? | H25: No | I25: Low | J25: - do a risk scan of the workplace that will identify high risk areas (e.g. dark corridors, sections where people work on their own, etc.)
C26: Workplace Violence and Harassment | D26: All farm businesses | E26: Workplace Violence and Harassment | G26: Has management taken any targeted action to prevent workplace violence and harassment (including sexual harassment)? | H26: No | I26: Medium, High | J26: Implement at least one of the following measures: - Training for supervisors, safety guards and other staff in direct contact with workers on respectful behavior and concepts of workplace violence and harassment - training of workers on the topic on respectful behavior and concepts of workplace violence and harassment - do a risk scan of the workplace that will identify high risk areas and define actions to make them safer (e.g. dark corridors, sections where people work on their own, etc.) Please note: in most cases workplace violence and harassment will relate to experiences faced by women. However risks are also faced by men. Ensure your answers cover risks in relation to all workers regardless of gender.
... C46: Child labour | D46: All farm businesses | E46: Family workers | G46: Do workers bring their own children to the farm (to live or work)? | H46: No | I46: Lower | J46: No further action
C47: Forced labour | D47: All workplaces | E47: Labour providers | F47: Farm management | G47: Does the farm use labour providers to recruit any workers? | H47: No | I47: All | J47: No further action
C48: Forced labour | D48: All workplaces | E48: Labour providers | F48: Farm management | G48: Does the farm use labour providers to recruit any workers? | H48: Yes | I48: All | J48: 1. Farm must ensure that any labor providers used are licensed or certified by the appropriate government authority, if one exists.
C49: Forced labour | D49: All workplaces | E49: Labour providers | F49: Farm management | G49: Does the farm use labour providers to recruit any workers? | H49: Yes | I49: Med, High | J49: 1. Farms must have written contracts with each labor provider, requiring that labor providers abide by RA worker protection standards. 2. When possible, farms should directly contract workers who are recruited by labor providers. 3. For workers whose direct employer is a labor provider, the Assess & Address monitoring system should check periodically with some of these workers to ensure that their pay, working conditions, etc. are as promised by the labor provider. 4. Workers recruited through labor providers should be treated equally with other workers and provided the same information about their protections under the RA standard. 5. The Assess & Address monitoring system should periodically check with workers who are recruited through labor providers, to see if they owe any debts related to recruitment fees. If so, the farm should negotiate with the labor provider full repayment of these fees to the worker. 6. Management should assign responsibility to one or more members of staff to oversee labor providers' compliance and the above measures. Farms should stop working with labor recruiters that do not meet these expectations.
D50: All workplaces | E50: Wage payment practices | F50: Farm management | G50: Are workers paid by volume/piece rate? | H50: No | I50: All | J50: No further action.
C51: Forced labour | D51: All workplaces | E51: Wage payment practices | F51: Farm management | G51: Are workers paid by volume/piece rate? | H51: Yes | I51: All | J51: 1. Farms must ensure that workers have written or verbal contracts in place according to requirement 3.3.1. 2. When calculated by volume, workers' pay must equal at least the minimum wage based on a 48-hour working week or national legal working hours limit. 3. Deductions from wages for costs such as employer-provided housing or food must only be taken with workers' consent. 4. Workers must be paid at least monthly. 5. Workers must be provided pay slips showing hours worked (regular and overtime) and/or volume produced, calculation of wages and deductions, and wages paid.
D52: All workplaces | E52: Wage payment practices | F52: Farm management | G52: Are workers paid by volume/piece rate? | H52: Yes | I52: Med, High | J52: 1. Management should confirm that personnel responsible for wage payment are correctly trained in calculations and requirements. 2. Management should make available personnel who speak the appropriate languages to explain/answer workers' questions about wage calculations and pay slips. 3. Management should assign responsibility to a member of staff to conduct a periodic review of pay records to identify instances of underpayment, delayed payment, and other inconsistencies.
C53: Forced labour | D53: All workplaces | E53: Freedom of movement | F53: Farm management | G53: Are security guards present on the farm/group premises? | H53: No | I53: All | J53: No further action
C54: Forced labour | D54: All workplaces | E54: Freedom of movement | F54: Farm management | G54: Are security guards present on the farm/group premises? | H54: Yes | I54: All | J54: 1. Farms must communicate to workers of their rights under the law to freely leave the job. This can be done through their contracts, information posted in the workplace, a workers' organization, one of the farm's committees, or other means. 2. For workers living on the farm, farms should communicate their rights to freedom of movement on and off the farm outside working hours.
C55: Forced labour | D55: All workplaces | E55: Freedom of movement | F55: Farm management | G55: Are security guards present on the farm/group premises? | H55: Yes | I55: Med, High | J55: 1. The Assess & Address monitoring system, working with other committees such as the Gender Committee, should periodically check with workers to see if they feel threatened by security guards.
C56: Forced labour | D56: Non-local workers are included among the workforce How will we know this; is it a question in the registry? | E56: Prison/military labor | F56: Farm management | G56: Are any workers recruited/provided to the farm by military or prison officials? | H56: No | I56: All | J56: No further actions.
C57: Forced labour | D57: Non-local workers are included among the workforce How will we know this; is it a question in the registry? | E57: Prison/military labor | F57: Farm management | G57: Are any workers recruited/provided to the farm by military or prison officials? | H57: Yes | I57: All | J57: 1. Military officials mobilizing military personnel to perform agricultural labor is a form of forced labor. Farms must not utilize this type of labor. 2. Farms must ensure that any prisoners working on the farm have freely provided their consent to work. 3. Prison labor must be treated the same as all other workers with respect to contracts, pay, working conditions, and all other worker protections in the RA standard.
C58: Forced labour | D58: Non-local workers are included among the workforce How will we know this; is it a question in the registry? | E58: Prison/military labor | F58: Farm management | G58: Are any workers recruited/provided to the farm by military or prison officials? | H58: Yes | I58: Med, High | J58: 1. The Assess & Address monitoring system should periodically check with prison laborers to ensure they are receiving the same treatment as other workers.
C59: Forced labour | D59: Non-local workers are included among the workforce How will we know this; is it a question in the registry? | E59: Deposit or document retention | F59: Farm management | G59: Do workers give any money (such as deposits) or documents (such as passports) to farm management or labor providers? | H59: No | I59: All | J59: No further action.
C60: Forced labour | D60: Non-local workers are included among the workforce How will we know this; is it a question in the registry? | E60: Deposit or document retention | F60: Farm management | G60: Do workers give any money (such as deposits) or documents (such as passports) to farm management or labor providers? | H60: Yes | I60: All | J60: 1. Farms should not require workers to pay any type of deposit or provide any personal document to management, other than to confirm identity at the time of hiring.
C61: Forced labour | D61: Non-local workers are included among the workforce How will we know this; is it a question in the registry? | E61: Deposit or document retention | F61: Farm management | G61: Do workers give any money (such as deposits) or documents (such as passports) to farm management or labor providers? | H61: Yes | I61: Med, High | J61: 1. The Assess & Address monitoring system, working with other committees such as the Grievance Committee, should periodically check with workers to see if they have had to pay deposits or hand over documents. 2. In instances where workers prefer to provide documents or other belongings to management for safe keeping, management must ensure that workers have permanent, unrestricted access to these locations.
C62: Living Wage | F62: Group management; medium/large estate management | G62: Does the business have a constant production level or are there peaks of production over a year (high and low production seasons)? | I62: All | J62: If No, the business needs to set in place a system to start collecting the necessary data about types of workers.
C63: Living Wage | F63: Group management; medium/large estate management | G63: If there were variations in production levels during the year, what is the number of months per year with average production, high peaks, and low peaks? | I63: All | J63: N/A | K63: See above.
C64: Living Wage | F64: Group management; medium/large estate management | G64: Does your business hav a piece-rate payments or periods of time, or a combination of both type of structure? | I64: All | J64: N/A
C65: Living Wage | F65: Group management; medium/large estate management | G65: If there were variations in production levels during the year, what is the number of months per year with average production, high peaks, and low peaks? | H65: Yes/No | I65: All | J65: If No, the business needs to set in place a system for collecting the necessary data about types of workers. | K65: What is the difference between this question and the question in row 82?
C66: Living Wage | F66: Group management; medium/large estate management | G66: Do you know what is the total number of men and women who occupy each type of position (averaged throughout the year)? -> to gender | H66: Yes/No | I66: All | J66: If no, business sets a system in place to collect gender disaggregated data on type of positions. | K66: Align with the gender questions.
C67: Living Wage | F67: Group management; medium/large estate management | G67: Do you keep record of the type of unit against which payments are made? For example, the units for positions with piece-rate; payment schemes could be hectares, linear meters, production volume (e.g., boxes, kilograms), and others. For other positions, the unit of payment may be hour, day, week, or month. | H67: Yes/No | I67: All | J67: If No, business sets a system in place to collect data for the type of unit against which payments are made for all major types of workers.
C68: Living Wage | F68: Group management; medium/large estate management | G68: Does the farm collect data on the amount paid in local currency per unit worked for each type of position in the form of values based on gross wages paid per unit? | H68: Yes/No | I68: All | J68: If No, the business needs to set in place a system for collecting the necessary data about types of workers.
C69: Living Wage | F69: Group management; medium/large estate management | G69: Can the farm calculate the Average number of units that are worked in a day for each type of position (for high, low, and average periods, if applicable)? | H69: Yes/No | I69: All | J69: If No, the business needs to set in place a system for collecting the necessary data about types of workers. | K69: What do you want to achieve with this one? Is it that management should have records on payments?
C70: Living Wage | F70: Group management; medium/large estate management | G70: Does the farm collect data on Average hours per day worked for each type of position (for high, low, and average periods, if applicable)? | H70: Yes/No | I70: All | J70: If No, the business needs to set in place a system for collecting the necessary data about types of workers.
C71: Living Wage | F71: Group management; medium/large estate management | G71: Does the farm collect data on Average hours per week worked for each type of position (for high, low, and average periods, if applicable) | H71: Yes/No | I71: All | J71: If No, the business needs to set in place a system for collecting the necessary data about types of workers.
C72: Living Wage | F72: Group management; medium/large estate management | G72: Does the farm collect data on Average amount of monthly bonuses granted for each type of position if bonuses for performance or quality that depend directly on the worker exist? | H72: Yes/No | I72: All | J72: If No, the business needs to set in place a system for collecting the necessary data about types of workers.
C73: Living Wage | F73: Group management; medium/large estate management | G73: Does your company provide subsidizedor donated food services to workers? | H73: Yes/No | I73: All | J73: If No, the business needs to set in place a system for collecting the necessary data about types of workers.
C74: Living Wage | F74: Group management; medium/large estate management | G74: Does your company provide subsidized or donated food services to workers? | H74: Yes/No | I74: All | J74: As the living wage benchmark reports do not stipulate a specific amount for transportation from home to the workplace and vice versa, there is no explicit reference value for this benefit, so the average monthly amount paid by_x000D_ the company to provide this service to each worker is included in the analysis
C75: Living Wage | F75: Group management; medium/large estate management | G75: Does your company provide donated health care services to workers? Does the medical service provided by the company cover all medical consultation expenses not covered by public health entities? | H75: Yes/No | I75: All | J75: If the answer to all these questions is yes, then the reference amount associated with expenses for private medical services is factored into the calculations according to the living wage benchmark report for the area.
C76: Living Wage | F76: Group management; medium/large estate management | G76: Does your company donate packages of school supplies for the workers’ children? | H76: Yes/No | I76: All | J76: If the amount paid by the company for the purchase of school supplies is less than the reference value according to the living wage benchmark report for the area, the actual amount paid by the company (divided by 12 months) is included in the analysis. If the amount paid by the company is greater than the reference value according to the living wage benchmark report, it should be noted that the purchased items are in accordance with the official lists recommended by the relevant authorities (e.g., ministries of education).
C77: Living Wage | F77: Group management; medium/large estate management | G77: Does your company provide family housing for its workers?_x000D_ | H77: Yes/No | I77: All | J77: If Yes, only family homes provided by the company that comply with decent housing standards are included. The reference value for renting a decent home in the area is included in the Matrix. If the company covers the costs associated with maintenance and public services, then the reference values for for renting a decent home in the_x000D_ area is included in the Salary Matrix tool. | K77: Overlap
C78: Gender | D78: All | E78: Gender Training for Leadership | F78: All | G78: Have management, supervisors and/or internal inspectors been trained in the past year on gender equality? | H78: yes | I78: All | J78: No further action
C79: Gender | D79: All | E79: Gender Training for Leadership | F79: All | G79: Have management, supervisors and/or internal inspectors been trained in the past year on gender equality? | H79: No | I79: All | J79: Train management, supervisors, internal inspectors annually on issues related to gender equality and women’s empowerment (maternity leave, sexual harassment…), AND/OR train management, supervisors, internal inspectors on gender bias in hiring, promotion, and employee engagement, AND/OR make gender-related trainings (e.g. sexual harassment, discrimination, gender equality or gender bias) a requirement for all management, supervisors, and internal inspectors
C80: Gender | D80: All | E80: Gender Commitment from Leadership | F80: All | G80: Has management undertaken significant action in the past to address gender equality and/or women empowerment? | H80: yes | I80: All | J80: No further action
C81: Gender | D81: All | E81: Gender Commitment from Leadership | F81: All | G81: Has management undertaken significant action in the past to address gender equality and/or women empowerment? | H81: No | I81: All | J81: Formulation of a policy on gender equality and women’s empowerment which will be shared with the rest of the workers AND/OR Stakeholder mapping of gender related (human rights) organizations that could support addressing gender within workers, AND/OR Ensure that management and/or other high-level functions are accountable for meeting the gender plan targets
C82: Gender | E82: Representation in higher level functions | F82: All | G82: Are women currently represented significally in relation to their number amongst supervisors, management and other high level functions within the farm? | H82: yes | I82: All | J82: No further action
C83: Gender | E83: Representation in higher level functions | F83: All | G83: Are women currently represented significally in relation to their number amongst supervisors, management and other high level functions within the farm? | H83: no | I83: All | J83: -establish a minimum quota for female trainers, supervisors, management and other high level functions AND/OR - organize professional training targeted at female workers to improve their opportunities for higher level jobs AND/OR -make sure that job advertisement reach male AND female workers and that job requirements are achievable for female workers - give in person training to management staff invovled in recruitment on unconscious bias and methodologies to prevent gender based discriminatory practices
C84: Gender | F84: All | G84: Do you know what is the total number of men and women who occupy each type of position (averaged throughout the year)? | H84: yes/no | I84: All | J84: If no, business sets a system in place to collect gender disaggregated data on type of positions.
B85: C. Environment
A86: 1 | C86: Forests and Protected Areas 4.1 | D86: All | E86: Deforestation/ Native vegetation | F86: All | G86: Are production sites shifting or expanding? | H86: no | I86: All | J86: No further action
C87: Forests and Protected Areas 4.1 | D87: All | E87: Deforestation/ Native vegetation | F87: All | G87: Are production sites shifting or expanding? | H87: Yes | I87: All | J87: Ensure that producers and workers know that native vegetation and natural ecosystems have to be maintained, through awareness raising and regular monitoring. Clearly mark the boundaries of on-farm natural ecosystems and their buffer zones and ensure that production and processing activities, including agrochemical use, do not encroach into these areas.
B88: 4. Environment | C88: HCV | D88: Farmers that are within X km of a protected area | E88: High Conservation Value Areas (HCV) | F88: Farm management | H88: yes | I88: bla | J88: 0.3
B89: 4. Environment | C89: HCV | E89: High Conservation Value Areas (HCV) | G89: . Is the farm (or any farm in a group) located closer than 5 km to an Intact Forest Landscape? | H89: Yes/No --> if yes --> | J89: List all activities by farmers (and any resident staff) that involve tree felling, clearing or burning of vegetation, cattle-grazing, and hunting/collection in the wider landscape outside the farm, and stop or redirect any activity that may degrade the structure or species composition of an IFL. | K89: TIFFANY: this is not MVP for geosaptial analysis, focus is on deforestation and PA
B90: 4. Environment | C90: HCV | E90: High Conservation Value Areas (HCV) | G90: Is the farm (or any farm in a group) located in or closer than 2 km to a designated Protected Area (PA), a Key Biodiversity Area (KBA), a Ramsar site or a UNESCO World Heritage site | H90: Yes/No --> if yes --> | J90: • respect the borders and integrity of the area; • comply with all applicable legal requirements and provisions – general national legislation related to PAs and their buffer zones as well as any specific regulations for the area; • do not threaten the main conservation attributes of the area, i.e. the values for which the area has been protected or classified as a PA, KBA or Ramsar site | K90: TIFFANY: this is not MVP for geosaptial analysis, focus is on deforestation and PA
B91: 4. Environment | C91: HCV | E91: High Conservation Value Areas (HCV) | G91: Do local communities have any legal or customary rights on the farm? | H91: Yes/No --> if yes --> | J91: a) Map local community land uses on the farm in a participatory and inclusive way with the affected community; b) Identify and mitigate any direct and indirect impacts from farming activities on these resources, or on habitat that support these resources; c) Formalise agreements with communities on the use and management of such areas using Free, Prior and Informed Consent principles, and document the process.
B92: 4. Environment | C92: HCV | E92: High Conservation Value Areas (HCV) | G92: Do you use communal lands for purposes related to farming, e.g. cattle grazing, timber collection, or hunting? | H92: Yes/No --> if yes --> | J92: a) Identify and describe all current or planned practices related with farming, including for the certified crops, livestock, construction, etc that use resources from communal lands; b) Evaluate if farming-associated activities impact on the vegetation structure or on the community’s land-uses; c) Seek ways to reduce negative impacts and avoid relying on the resources of communal lands when expanding or diversifying farming activities
B93: 4. Environment | C93: HCV | E93: High Conservation Value Areas (HCV) | G93: Is the farm, or farm group, larger than 10,000 hectares, and is the answer ‘Yes’ to questions 1, 2, or 3? | H93: Yes/No --> if yes --> | J93: a) Commission a HCVRN Licenced Assessor to do an HCV assessment; b) Develop and implement an HCV Management and Monitoring plan based on the recommendations in the report; c) Consider how threats outside the farm could affect HCVs within the farm boundaries. Seek opportunities to engage with neighbouring farmers and communities to address and mitigate such threats across the wider landscape; d) If you answered ‘Yes’ on Question 5, develop your management and monitoring plan in collaboration with the affected communities.
A94: 1 | B94: 4. Environment | C94: Native Vegetation | D94: All | E94: Native Vegetation | F94: All | G94: Do all on-farm natural ecosystems, including hedges, tree lines, riparian buffers, and forest contain native vegetation? | H94: Yes | I94: All | J94: Maintain existing native vegetation; Ensure that the total farm area with native vegetation meets the criteria in 4.2.2-4.2.6
A95: 1 | B95: 4. Environment | C95: Native Vegetation | D95: All | E95: Native Vegetation | F95: All | G95: Do all on-farm natural ecosystems, including hedges, tree lines, riparian buffers, and forest contain native vegetation? | H95: No | I95: All | J95: Identify appropriate native species that can be planted to increase the proportion of native vegetation in on-farm natural ecosystems including forests, riparian buffers, hedges, and tree lines.
A96: 1 | B96: 4. Environment | C96: Natural Ecosystems | D96: All CHs with on-farm forest | E96: Forests | F96: All | G96: Does the forest resemble natural forest in terms of canopy cover, forest strata, and the presence of vines or lianas? See document titiled Guidance on Implementing 4.1-4.3 for more information on measuring forest quality. | H96: Yes | I96: All | J96: No further action
A97: 1 | B97: 4. Environment | C97: Natural Ecosystems | D97: All CHs with on-farm forest | E97: Forests | F97: All | G97: Does the forest resemble natural forest in terms of canopy cover, forest strata, and the presence of vines or lianas? See document titiled Guidance on Implementing 4.1-4.3 for more information on measuring forest quality. | H97: No | I97: All | J97: Plan to manage canopy cover, forest strata, and presence of vines or lianas (e.g., by creating openings, planting additional species, and restricting harvesting or grazing as neccessary) to facilitate natural forest regeneration and growth. See document titled Guidance on Implementing 4.1-4.3 for more details on managing on-farm forests.
A98: 2 | B98: 4. Environment | C98: Natural Ecosystems | D98: All CHs with on-farm wetlands | E98: Waterways, Water Sources, and Wetlands | F98: All | G98: Do wetlands store or convey flood waters at any time of the year? | H98: Yes | I98: All | J98: Plan to delineate and manage wetland and active floodplain, and ensure that production or processing activities do not encroach into the floodplain
A99: 2 | B99: 4. Environment | C99: Natural Ecosystems | D99: All CHs with on-farm wetlands | E99: Waterways, Water Sources, and Wetlands | F99: All | G99: Do wetlands store or convey flood waters at any time of the year? | H99: No | I99: All | J99: No further action
A100: 3 | B100: 4. Environment | C100: Natural Ecosystems | D100: All CHs with on-farm grassland/rangeland or non-natural desert | E100: Grassland, Rangeland, and Non-natural Desert | F100: All | G100: Do grassland/rangeland or non-natural desert areas contain large bare areas that are at risk of eroding into nearby waterways? | H100: Yes | I100: All | J100: Plant additional native groundcover (grasses, shrubs, trees) and implement measures to protect against erosion.
A101: 3 | B101: 4. Environment | C101: Natural Ecosystems | D101: All CHs with on-farm grassland/rangeland or non-natural desert | E101: Grassland, Rangeland, and Non-natural Desert | F101: All | G101: Do grassland/rangeland or non-natural desert areas contain large bare areas that are at risk of eroding into nearby waterways? | H101: No | I101: All | J101: Monitor the area for erosion and implement erosion control measures as neccessary. Conserve and enhance any existing native vegetation.
A102: 4 | B102: 4. Environment | C102: Natural Ecosystems | D102: All CHs with permanently fallow land | E102: Fallow Land | F102: All | G102: Are trees regenerating naturally on permanently fallow land? | H102: Yes | I102: All | J102: No further action
A103: 4 | B103: 4. Environment | C103: Natural Ecosystems | D103: All CHs with permanently fallow land | E103: Fallow Land | F103: All | G103: Are trees regenerating naturally on permanently fallow land? | H103: No | I103: All | J103: Re-vegetate fallow land by planting native grass, shrub, and tree species in accordance with an appropriate successional regime
A104: 5 | B104: 4. Environment | C104: Natural Ecosystems | D104: All CHs with multiple areas of natural ecosystem | E104: Ecosystem Connectivity | F104: All | G104: Are the areas of natural ecosystem connected by landscape corridors? | H104: Yes | I104: All | J104: No further action
A105: 5 | B105: 4. Environment | C105: Natural Ecosystems | D105: All CHs with multiple areas of natural ecosystem | E105: Ecosystem Connectivity | F105: All | G105: Are the areas of natural ecosystem connected by landscape corridors? | H105: No | I105: All | J105: Plan to connect existing ecosystem fragments with habitat or landscape corridors. Maintain and enhance buffer zones around existing ecosystem fragments to prevent encroachment of farm activities and enforce agrochemical "non-application zones".
... A107: 1 | B107: 4. Environment | C107: Deforestation/conversion | D107: All CHs with on-farm forest | E107: Harvesting in Forests | F107: All | G107: Is there any harvesting of forestry products, including wood and non-timber forestry products, from natural ecosystems on the group of farms? | H107: Yes | I107: All | J107: Describe the harvesting activities and include a plan for sustainable continuation of these practices. Identify any potential threats to the quality or spatial extent of the natural ecosystems resulting from harvesting practices.
C108: Climate Change | D108: All | G108: Are producers aware of the risks and impacts that climate change poses to livelihoods and production systems? | H108: Yes/No --> if no --> | I108: All | J108: Awareness raising on climate change risks and their impacts on agriculutral production systems and livelihoods more broadly.
D109: All | G109: Have producers identified the most significant climate change threats/risks/impacts (current and projected) on livelihood resources and farming systems? | H109: Yes/No --> if no --> | I109: All | J109: a) Carry out a climate change risk assesment to identify and describe the most significant cimate risks based on RA CC risk assessment tool.
D110: All | G110: Does a risk managament plan exist and have the identified risks and impacts (current and projected) been taken into account? | H110: Yes/No --> if no --> | I110: All | J110: a) Develop a farm map identifying most at risk areas based on identified climate impacts; b) Develop mitigation strategies to address identified risk as they relate to other standard criteria e.g. soil management; c) Develop mitigation strategies to address identified risk as they relate to other livelihood strategies i.e. opportunties for diversification so that people are managing risk by planning for and investing in the future.
D111: All | G111: Do producers have access to relevant climate change information, skills and services to develop and employ adaptation strategies? | H111: Yes/No --> if no --> | I111: All | J111: Awareness raising about available information to improve adaptive capacity and resilience, early warning systems, support tools and importance of equal rights to access resources.
D112: All | G112: Are emergency measures to deal with extreme weather events and their potential impacts (i.e. evacuation plan) developed and in place? | H112: Yes/No --> if no --> | I112: All | J112: Based on risk map and where appicable develop an emergency response plan for household and/wider community locations e.g. households located on steep slopes at risk of landslides.

Sheet Risk assessment l1
A2: Initial Risk Assessment: the initial risk assessment is a set of questions a group or estate management shall answer before implementation of the certification program in order to have an indication on topics that require special attendion during planning and implementation of the program. E.g. topics that need to be covered in the trainings, topics that require special attention during internal inspections etc. -What topics do we want to include in the initial risk assessment? -Who can provide the questions per topic?
B5: Requirement | D5: Feeds into: internal inspections | E5: High/Medium/Low | F5: Feeds into: management plan | I5: Level 0 | J5: Level 1 | K5: Level 2 | L5: Level 3
B6: (1.3.5) Management conducts a risk assessment in relation to the criteria in this standard for their group/farm at least every three years, including at least the risks associated with: -Traceability - Social risks including child labor, forced labor and workplace harassment and violence - Agrochemicals management - Deforestation and biodiversity loss - Economic fluctuations or shocks - Climate change, extreme weather, environmental hazards | D6: (1.3.1) An internal inspection system is in place to assess compliance of group members with the Rainforest Alliance standard. ... - consecutive years: - scope of inspection is based on risk assessment and on previous inspections | F6: (1.4.1) Management makes a management plan, describing improvement areas, actions to be taken, services to be delivered and usage of Premium. The management plan is based on at least, but not limited to, the internal inspection (1.3.1) and risk assessment (1.3.5). Actions are implemented, monitored, and documented. The management plan is updated at least every three years. | I6: No PDCA: Lack of documentation (processes and policies). No structure or formalized organization. | J6: Reactive, but documented (PDCA): Documentation exists with an informal structure implementing the processes and policies. Implementation occurs in reaction to the system, as no planning was taken into account when policies and process were developed. | K6: Proactive (PDCA): Formal documentation and structure to implement policies and processes, stakeholder involvement and planning has been involved during the development of the policies and processes. Post-implementation, there was a lack of evaluation and learning. | L6: Continuous improvement (PDCA): Formal documentation and structure to implement policies and processes, stakeholder involvement and planning has been involved during the development of the policies and processes. Post-implementation, activities were checked, evaluated and monitored to ensure that learning and improvement takes place. | M6: This page has:
M7: =COUNTA(N9:N64) -> 13
A8: A. Management (see capacity assessment tool?) | C8: Topic | D8: Question applicable to (Group Managemet, medium/large estate management, group member during internal inspections) | F8: Question | G8: Yes/No | H8: If yes, should show in Mitigation Actions | M8: Supporting documents / evidence: | N8: Selection | O8: Weighted | P8: =AVERAGE(P9:P64) -> 0.38430769 | Q8: Maximum
A9: A. | B9: 1 | C9: Group management capacity
N10: 4 | O10: =IF(N10=1,0)+IF(N10=2,0.333)+IF(N10=3,0.666)+IF(N10=4,100%) -> 1 | P10: =O10*Q10/100 -> 1 | Q10: 100
A11: A. | B11: 2 | C11: Economic fluctuations or shocks
A12: A. | B12: 3 | C12: Traceability | D12: CH management | F12: Do you/will you make use of intermediaries in your supply chain? | H12: Set up a clear traceability flow, that includes the documented and physical traceability rules for all actors (farmer, intermediary, CH management). Train the intermediaries on traceability. Monitor traicability and record keeping at intermediaries (during the harvest period).
A13: B. Farming Practices | M13: Supporting documents / evidence: | N13: Selection | O13: Weighted | P13: =AVERAGE(P14:P71) -> 0.333 | Q13: Maximum
A14: B. | B14: 4 | C14: Agrochemical management | D14: Farm level | F14: Review the Rainforest Alliance list of banned agrochemicals. Is it common practice in the region to use one or more of the agrochemicals from the banned pesticide list? | H14: Group member training on the prohibition of the use of banned agrochemicals, and which ones those are. Include verification on use of banned agrochemicals in internal inspections. Monitoring of use of banned agrochemicals during application period. Note: farmers that have used banned agrochemicals for the harvest to be certified cannot be included in the certification and have to wait for the next harvest cycle to apply again.
A15: B. | B15: 5
N16: 2 | O16: =IF(N16=1,0)+IF(N16=2,0.333)+IF(N16=3,0.666)+IF(N16=4,100%) -> 0.333 | P16: =O16*Q16/100 -> 0.333 | Q16: 100
A17: B. | B17: 6
N18: 2 | O18: =IF(N18=1,0)+IF(N18=2,0.333)+IF(N18=3,0.666)+IF(N18=4,100%) -> 0.333 | P18: =O18*Q18/100 -> 0.333 | Q18: 100
A19: C. Working Conditions | M19: Supporting documents / evidence: | N19: Selection | O19: Weighted | P19: =AVERAGE(P20:P78) -> 0.333 | Q19: Maximum
A20: C. | B20: 7 | C20: Discrimination | D20: Group members | F20: If you hire labor (beyond family labor), are any of the workers from historically discriminated groups (indigenous communities, minorities, lower castes etc.)? | H20: Ensure that all workers receive equal pay for jobs of equal value. Ensure that all workers understand the working conditions if needed by explaining in their own language.
D21: Group members | F21: Is it possible that any of the group members hires labor (beyond family labor), are any of the workers from historically discriminated groups (indigenous communities, minorities, lower castes etc.)?
D22: CH management | F22: Do you have any female workers beyond family labor? | H22: Ensure that a registry is kept, also if they are casual workers, indicating their sex. Ensure that they understand the working conditions, including remuneration level and other benefits, if needed by explaining in their own language.
D23: Group members | F23: Is it possible that any of the group members hires any female workers beyond family labor?
A24: C. | B24: 8 | C24: Forced Labor | D24: Group members | F24: Is it possible that there migrant workers (including seasonal and temporary) working on any of the farms? | H24: Ensure that migrant workers have safe place to keep their identity and other important documents, which is accessible to them at all times.
D25: Group members | F25: Is it possible that there are workers on any of the farms who were recruited by a third-party labor provider? | H25: Maintain records of which workers were recruited by which labor provider. Ensure that written contracts are in place between the farm/group and each labor provider, specifying that providers must abide by all Rainforest Alliance standards and that the workers they recruit must not pay any recruitment fees. Ensure that workers are always paid their wages directly, not indirectly through a third party.
D26: Group members | F26: Is it possible that workers on any of the farms have paid a recruitment fee to labor providers or other actors in the recruitment chain? | H26: In the hiring process, integrate a process to ask workers whether they hold any recruitment-related debt.
D27: Group members | F27: Is it possible that any workers are lacking a written contract, or documented verbal agreement? | H27: Group members work towards signing direct contracts/verbal agreements with permanent workers and workers who are employed for more than 3 consecutive months.
D28: Group members | F28: Is it possible that any workers are directly employed by labor providers (contract signed between worker and labor provider)? | H28: Group members work towards signing direct contracts/verbal agreements with permanent workers and workers who are employed for more than 3 consecutive months.
D29: Group members | F29: Do hired workers receive food, housing, and/or transportation provided by the farmer/group management? | H29: Ensure that workers' contracts/records of verbal agreements specify the in-kind benefits they will receive and specific cost deductions that will be taken for them. In-kind benefits must be in accordance with national law, and never exceed 30% of the total remuneration.
D30: Group members | F30: @Lennie: It would. But isn't that OK? If this tool helps a farmer identify an actual gap, it also helps the farmer remediate that gap. | H30: Eliminate any restrictions on workers' freedom of movement outside their working hours. Allow workers to maintain possession of their mobile phones and other communication devices.
D31: Group members | F31: Do workers ever wait longer than 1 month to be paid? | H31: Ensure that workers are paid regularly at scheduled intervals, at least monthly. Payments must be documented with a pay slip or other suitable wage record to allow verification.
D32: Group members | F32: Do workers ever receive advances or loans from the farm/group? | H32: Ensure that advances/loans amount to no more than 1-2 months' salary and that repayment terms are reasonable (no higher than prevailing market interest rates), documented, and agreed by both parties. | N32: 2 | O32: =IF(N32=1,0)+IF(N32=2,0.333)+IF(N32=3,0.666)+IF(N32=4,100%) -> 0.333 | P32: =O32*Q32/100 -> 0.333 | Q32: 100
A33: C. | B33: 9 | C33: Child Labor | F33: Is pre-school education and/or day care freely available for children in this community? | H33: Check if pre-school age children are taken on to farms and if so, if there is a safe place for them to be.
H34: Talk to parents and guardings about risk of children being on farms and work with farm owners and local organisations to find suitable and safe places for children to be when parent’s work.
F35: Does this community lack sufficient primary and secondary schools to educate all children? | H35: As a longer-term measure, engage with external actors to obtain support to improve school access.
F36: If there are schools in the community, do they charge any formal or informal fees to enroll children, or are there costs associated with education including books, uniform, transport, etc.? | H36: As a longer-term measure, engage with external actors to obtain support for children whose families cannot afford these costs.
F37: If schools are available in the community, do parents keep children home from school in order to work or do household tasks; and/or do older children drop out of school to work? | H37: Raise awareness among workers/members/families of the importance of sending children to school and the Rainforest Alliance requirement against child labor.
F38: Is it considered normal in this community for children to work in farming? | H38: Raise awareness among workers/members/families of the importance of sending children to school and the Rainforest Alliance requirement against child labor. | N38: 2 | O38: =IF(N38=1,0)+IF(N38=2,0.333)+IF(N38=3,0.666)+IF(N38=4,100%) -> 0.333 | P38: =O38*Q38/100 -> 0.333 | Q38: 100
A39: C. | B39: 10 | C39: Harassement and Violence | F39: If you hire labor (beyond family labor), are there female workers between them who work without the presence of their partner or another relative who work with male workers? | H39: Ensure that female workers work together, if possible, with a female supervisor.
F40: If you hire labor (beyond family labor), are there young workers (below 21) who work without the presence of a family member? | H40: Ensure that young workers work in a safe environment, in a group, if possible with a female supervisor.
F41: Do you have female and/or young workers amongst your hired labor (beyond family labor) who work in an isolated environment? | H41: Ensure that they work in groups with at least several women, if possible with a female supervisor.
F42: Have all supervisors been trained on appropriate behavior and the procedures that are in place to address inappropriate behavior towards other workers? | H42: Company supervisors are trained to use appropriate disciplinary techniques and procedures. A policy is in place to suspend or terminate supervisors who do not adhere to these techniques and procedures.
F43: Does the farm/group hire security guards to protect the premises? | H43: Ensure that workers are able to come and go from the farm without intimidation from security guards. Train security guards on proper conduct including a prohibition on threats and bribery. | N43: 2 | O43: =IF(N43=1,0)+IF(N43=2,0.333)+IF(N43=3,0.666)+IF(N43=4,100%) -> 0.333 | P43: =O43*Q43/100 -> 0.333 | Q43: 100
A44: C. | B44: 11 | C44: All | F44: Do workers lack awareness of how they can raise concerns about any labor abuses? | H44: Distribute information within the group/farm and/or conduct trainings for workers on the use and functioning of the grievance mechanism and the presence and functions of the pp/committee for human rights issues.
F45: Do workers/member farmers lack awareness of the concepts of discrimination, forced labor, child labor, and workplace harassment and violence and the difference between acceptable and unacceptable behavior. | H45: Inform workers in their own language on concepts, acceptable behavior, rights and procedures in place regarding the four topics. | N45: 2 | O45: =IF(N45=1,0)+IF(N45=2,0.333)+IF(N45=3,0.666)+IF(N45=4,100%) -> 0.333 | P45: =O45*Q45/100 -> 0.333 | Q45: 100
A46: C. | B46: 12 | C46: Gender | D46: CH management | F46: Will the gender plan elaborated with the outcomes of this assessment be incorporated in the general management plan? | G46: No | H46: Share the outcomes of this gender analysis with group/farm management. Elaborate the gender plan in coordination with group/farm management and have it incorporated in the general management plan
G47: Yes | H47: Ensure that progress of the gender plan will be frequently discussed in the management meetings
D48: CH management | F48: Does farm/group management understand the concepts of sex, gender,and gender equality? | H48: Organize awareness sessions with management on concepts and importance of gender equality and related issues
F49: Is monitoring with sex-disaggregated data carried out for (elected) leadership positions, participation in training, access to loans for farm investments, diversification, workers wages (SH) or for workers, workers wages, access to supervisory, f/m in workers union, f/m in supervisory or management positions... (M/LF) | H49: Introduce monitoring with sex-disaggregated data and make sure that the collected data are shared with the person/committee responsible for gender.
D50: CH management | F50: Do men and women have an equal role in decision making? | H50: Raise awareness about importance to include more women (or men) in decision making positionsOrganize leadership trainings for womenFacilitate participation of women in meetings by adjusting location, timing, etc.
D51: CH management | F51: Are supervisory and management jobs and other better paid jobs accessible for men and women? | H51: Ensure that job requirements can be fulfilled by both men and women where possibleOffer additional training on management, administration and other topics for women to facilitate their access to better paid jobs
D52: CH management/group members | F52: Are trainings (for farmers and CH staff?) considering the needs and interests of both men and women? | H52: Do assessment for training and organize training on topics on basis of its outcomesFacilitate participation of women by adjusting location, timing, use of female facilitators, local language...Train women to become internal inspector or trainer
D53: CH management | F53: Do women and men receive the same remuneration and benefits related to a job of equal value? | H53: Ensure that all workers have access to information about the wages and benefits that relateto different job types in their own languageEnsure that jobs of equal value receive equal pay and benefits
D54: Group members | F54: Do women and men have the same access to farmers' cooperative? (SH) | H54: Promote members registration as a coupleUse agricultural activities as a criterion to become a member, instead of landownershipFacilitate female farmers registration by offering a reduction of memberships fee Approach female farmers personally to invite them to becomemember
D55: CH management | F55: Do female and male workers have the same access to workers union? (M/LF) | H55: Promote female workers participation by training, awareness raising of male leaders and workers, personal invites, target setting
D56: Group members | F56: Do female and male farmers have the same access to inputs and services like loans for agricultural investment, seedlings, information, etc.? (SH) | H56: Ensure that male and female farmers are aware of inputs and services being offered and know where and how to access themEnsure that measures are in place to facilitate access of female farmers to inputs and services taking into account their time poverty and lack of means of transport (time and place of reception, required documents, etc.)Monitor the reception of inputs and services with sex-disaggregated data, identify gaps
D57: CH management | F57: Do female and male workers have the same access to inputs and services like training, health services, benefits | H57: Ensure that male and female farmers are aware of inputs and services being offered and know where and how to access themEnsure that measures are in place to facilitate access of female farmers to inputs and services taking into account their time poverty and lack of means of transport (time and place of reception, required documents, etc.). Monitor the reception of inputs and services with sex-disaggregated data, identify gaps. | N57: 2 | O57: =IF(N57=1,0)+IF(N57=2,0.333)+IF(N57=3,0.666)+IF(N57=4,100%) -> 0.333 | P57: =O57*Q57/100 -> 0.333 | Q57: 100
A58: C. Environment | M58: Supporting documents / evidence: | N58: Selection | O58: Weighted | P58: =AVERAGE(P59:P89) -> 0.333 | Q58: Maximum
A59: D. | B59: 12 | C59: Deforestation and Biodiversity (Align with work of Tiffany) | D59: Group management | F59: Is there a map in place that outlines natural forests and other natural ecosystems (such as savanna, wetlands, peatlands), production areas, protected areas and set-aside land, and rivers?
D60: Concerning group members | F60: Is it probable that there producers that have borders to forests, protected areas and rivers? | H60: Awareness raising of the requirements related to these – no degradation of forests, protected areas and natural ecosystems, no-application zones of pesticides and riparian buffer zones?
D61: Concerning group members | F61: Is it likely producers are not aware that the should maintain natural vegetation on the farm? | H61: Awareness raising of producers on maintenance of natural vegetation on the farm. | N61: 2 | O61: =IF(N61=1,0)+IF(N61=2,0.333)+IF(N61=3,0.666)+IF(N61=4,100%) -> 0.333 | P61: =O61*Q61/100 -> 0.333 | Q61: 100
D62: Concerning group members | F62: Is it likely that producers hunt on the farm? | H62: Awareness raising of producers on hunting requirements.
D63: Concerning group members | F63: Are there any endangered species in the area? And if so, do you think that farmers are aware of the endangered species there are and how to protect them? | H63: Awareness raising on endangered species and how to protect them.
N64: 2 | O64: =IF(N64=1,0)+IF(N64=2,0.333)+IF(N64=3,0.666)+IF(N64=4,100%) -> 0.333 | P64: =O64*Q64/100 -> 0.333 | Q64: 100

Sheet Sheet2
A1: Main aspects based on AMEA guidelines:
A2: A. Organizational purpose and Governance practices
A3: B. Business management
A4: C. Member engagement and planning
A5: D. Human resource management
A6: E. Financial management
A7: F. Community and stakeholder engagement
A8: G. Member services and business activiies
A10: Red | B10: From the AMEA guidelines
A11: Yellow | B11: From the M4 tool
A12: Wit: | B12: From the NewForesight tool
A13: Beige: | B13: From the Adore tool

Sheet Group risk assessment L0
A1: Question | B1: Theme | C1: Certification option (group or large estate) | D1: Which CHs does this apply to? | E1: Issue | F1: Mitigation self-assessment – risk questions | G1: Answer parameter | H1: Country/sector risk context applicability | I1: Mitigation actions to be included in the Management Plan | J1: Comments
B2: Management
A3: 1 | B3: Group management capacity | C3: Group Certification | D3: All Farmer Groups | E3: Management capacity | F3: Based on the outcomes of the capacity assessment tool, have you identified areas to improve? If yes, please indicate which actions you want to take for the applicable areas of the 7 areas included in the Capacity Assessment Tool. | H3: All | I3: 1
C4: Group Certification | D4: All Farmer Groups | H4: All | I4: 2
C5: Group Certification | D5: All Farmer Groups | H5: All | I5: 3
C6: Group Certification | D6: All Farmer Groups | H6: All | I6: 4
C7: Group Certification | D7: All Farmer Groups | H7: All | I7: 5
C8: Group Certification | D8: All Farmer Groups | H8: All | I8: 6
C9: Group Certification | D9: All Farmer Groups | H9: All | I9: 7
A10: 1 | B10: Traceability | C10: Group Certification | D10: All Farmer Groups | E10: Intermediaries | F10: Do you/will you make use of intermediaries* in your supply chain? | G10: yes | H10: All | I10: Include all intermediaries in your traceability procedure. Train the intermediaries on traceability. Monitor traceability, calibration of scales and record keeping at intermediaries (during the harvest period) and cross-check with information of sales from a sample of producers. If intermediaires are paid according to weight bought in, mitigation should include regular verification of scales.
C11: Group Certification | D11: All Farmer Groups | E11: Intermediaries | F11: Do you/will you make use of intermediaries* in your supply chain? | G11: no | H11: All | I11: No further actions needed (apart from actions on compliance with the standard)
A12: 1 | C12: Group Certification | D12: All Farmer Groups | E12: Record keeping | F12: Do you expect farmers to have difficulties keeping (traceability) records? | G12: yes | H12: All | I12: Include record keeping in training plan. Monitor record keeping.
C13: Group Certification | D13: All Farmer Groups | E13: Record keeping | F13: Do you expect farmers to have difficulties keeping records? | G13: no | H13: All | I13: No further actions needed (apart from actions on compliance with the standard)
A14: 1 | C14: All farmer organizations | D14: All | E14: Product separation | F14: Do you/will you only handle RA certified product and only buy from RA certified producers? | G14: yes | H14: All | I14: No further actions needed (apart from actions on compliance with the standard)
C15: All farmer organizations | D15: All | E15: Product separation | F15: Do you/will you only handle RA certified product and only buy from RA certified producers? | G15: no | H15: All | I15: Implement a system for identifying the products originating from certified producers by means of physical or visual identification and in the tracebaility documents (receipts, registry, etc.).
A16: 1 | C16: Group Certification | D16: All Farmer Groups | E16: Yield estimation | F16: Is there an important pressure on the land? Do farmers often divide or sell their land? | G16: yes | H16: All | I16: Include assessment of the certified area for each producer in the yearly internal inspections to ensure that the areas in the group member administration match the reality of the farms.
C17: Group Certification | D17: All Farmer Groups | E17: Yield estimation | F17: Is there an important pressure on the land? Do farmers often divide or sell their land? | G17: no | H17: All | I17: No further actions needed (apart from actions on compliance with the standard)
A18: 1 | C18: Group Certification | D18: All Farmer Groups | E18: Record keeping | F18: Do group members have access to different market outlets / different buyers for their certifiers product? | G18: yes | H18: All | I18: Information on harvested volumes based on deliveries might not be reliable, therefore, put a system in place to get information on harvested volumes (this can be done by asking producers directly through out the year or during internal inspections).
C19: Group Certification | D19: All Farmer Groups | E19: Record keeping | F19: Do group members have access to different market outlets / different buyers for their certifiers product? | G19: no | H19: All | I19: No further actions needed (apart from actions on compliance with the standard)
A20: 1 | C20: Group Certification | D20: All Farmer Groups | E20: Product separation | F20: Do group members often rely on farm operators to manage their farm? | G20: yes | H20: all | I20: Guarantee that the farm managers is the same year after year through the internal inspections and that they are aware of the traceability requirements. Check if farm operator also manages non-certified farms and if so, encourage to include them in the certified group as well.
C21: Group Certification | D21: All Farmer Groups | E21: Product separation | F21: Do group members often rely on farm operators to manage their farm? | G21: no | H21: All | I21: No further actions needed (apart from actions on compliance with the standard)
A22: 1 | C22: All farmer organizations | D22: All | E22: Product separation | F22: Does the certified product need to be aggregated for processing? | G22: yes | H22: All | I22: Mixing with non-certified products might occur to guarantee minimum volume for processing. Group management to put a control system to regularly check that product separation is respected (also at subcontractor level).
C23: All farmer organizations | D23: All | E23: Product separation | F23: Does the certified product need to be aggregated for processing? | G23: no | H23: All | I23: No further actions needed (apart from actions on compliance with the standard)
B24: Farming practices
A25: 1 | B25: Agrochemical management | D25: All Farmer Groups | E25: Use of banned inputs | F25: Review the Rainforest Alliance list of banned agrochemicals: Is it common practice in the region to use one or more of the agrochemicals from the banned pesticide list, including on the non-certified crops on the farm? | G25: Yes | H25: All | I25: Group member training on the prohibition of the use of banned agrochemicals, and which ones those are. Group members trained on the risk of using highly hazardous agrochemicals. Include verification on use of banned agrochemicals in internal inspections. Monitoring of use of banned agrochemicals during application period. Set up system to collect stocks of banned agrochemicals from the group members. Note: farmers that have used banned agrochemicals for the harvest to be certified cannot be included in the certification and have to wait for the next harvest cycle to apply again.
D26: All Farmer Groups | E26: Use of banned inputs | F26: Review the Rainforest Alliance list of banned agrochemicals: Is it common practice in the region to use one or more of the agrochemicals from the banned pesticide list? | G26: No | H26: All | I26: No specific mitigation action
A27: 2 | D27: All Farmer Groups | E27: Use of banned inputs | F27: Review the Rainforest Alliance list of banned agrochemicals: If you are certified by other standards, are there any RA banned agrochemicals that are not banned under these other standards? | G27: Yes | H27: All | I27: Group member training on the prohibition of the use of banned agrochemicals, and which ones those are. up member training on the prohibition of the use of banned agrochemicals, and which ones those are. Group members trained on the risk of using highly hazardous agrochemicals. Include verification on use of banned agrochemicals in internal inspections. Monitoring of use of banned agrochemicals during application period. Set up system to collect stocks of banned agrochemicals from the group members. Note: farmers that have used banned agrochemicals for the harvest to be certified cannot be included in the certification and have to wait for the next harvest cycle to apply again.
D28: All Farmer Groups | E28: Use of banned inputs | F28: Review the Rainforest Alliance list of banned agrochemicals: If you are certified by other standards, are there any RA banned agrochemicals that are not banned under these other standards? | G28: No | H28: All | I28: No specific mitigation action
A29: 3 | D29: All Farmer Groups | E29: Amount of pesticide applications | F29: Does your group already have an effective IPM system for the certified crop in place, including the identification and monitoring of pests? | G29: Yes | H29: All | I29: Make sure all members have the necessary knowledge and skills to apply IPM.
D30: All Farmer Groups | E30: Amount of pesticide applications | F30: Does your group already have an effective IPM system for the certified crop in place, including the identification and monitoring of pests? | G30: No | H30: All | I30: Develop the IPM strategy for your crop, including the development of a pest monitoring system and the establishment of action thresholds. (May need to contact local university or extension service.) Make sure all members have the necessary knowledge and skills to apply IPM. Train members on record keeping. Identify sources for the purchase of lower toxicity agrochemicals as well as non-chemical pest control products.
A31: 4 | D31: All Farmer Groups | E31: Pesticide residues | F31: Do you or your buyer regularly check samples of the crop for residues of agrochemicals (MRL)? | G31: Yes | H31: All | I31: Make sure there is a good traceability system back to the producer
D32: All Farmer Groups | E32: Pesticide residues | F32: Do you or your buyer regularly check samples of the crop for residues of agrochemicals (MRL)? | G32: No | H32: All | I32: Make sure there is a good traceability system back to the farm units Identify a laboratory for residue analysis and set up a sampling system and procedure
A33: 5 | D33: All Farmer Groups | E33: Use of PPE | F33: Are all workers/farmers spraying agrochemicals using the correct PPE at all times when they apply agrochemicals? | G33: Yes | H33: All | I33: No specific mitigation action
D34: All Farmer Groups | E34: Use of PPE | F34: Are all workers/farmers spraying agrochemicals using the correct PPE at all times when they apply agrochemicals? | G34: No | H34: All | I34: Ensure availability of sufficient PPE for all those applying agrochemicals. Develop and implement management policies on the correct use of PPE. Make sure all those applying agrochemicals are trained on correct application of the agrochemicals and PPE. up member training on the prohibition of the use of banned agrochemicals, and which ones those are. Group members trained on the risk of using highly hazardous agrochemicals. For group, explore the option of developing spray teams to replace agrochemical application by individual group members.
A35: 1 | B35: Soil conservation | D35: All | E35: Erosion | F35: Are there any areas that have a slope steeper than 1m rise over 3m run over an area >0.1ha? | G35: Yes | H35: All | I35: Implement measures to protect against erosion, including planting of native groundcover, contour planting, living barriers and drainage/dewatering systems.
B36: Soil conservation | D36: All | E36: Erosion | F36: Are there any areas that have a slope steeper than 1m rise over 3m run over an area >0.1ha? | G36: No | H36: All | I36: Make sure no gully forming is happening and that organic top layer is not washed
A37: 1 | B37: Water management | D37: All | E37: Waterlogging | F37: Are there any areas within the farm / group member farms with long periods of standing water after rain? | G37: Yes | H37: All | I37: Implement measures to improve drainage through physical measures, digging drainage trenches, or improving soil structure to increase the soil’s potential to take up water and store it
B38: Water management | D38: All | E38: Waterlogging | F38: Are there any areas within the farm / group member farms with long periods of standing water after rain? | G38: No | H38: All | I38: No further action
A39: 2 | B39: Water management | D39: All | E39: Waterlogging | F39: Is high ground water level a problem in certain areas? | G39: Yes | H39: All | I39: Assess whether the area is suitable for crop cultivation and consider what crops are suitable for these areas. In some cases: improve drainage and/or conserve protective vegetation
B40: Water management | D40: All | E40: Waterlogging | F40: Is high ground water level a problem in certain areas? | G40: No | H40: All | I40: No further action
A41: 3 | B41: Water management | D41: All | E41: Drought | F41: Is drought (becoming) a limiting factor for crop production? | G41: Yes | H41: All | I41: Keep soil covered to reduce evapotransperation. Assure deep-rooting crops are used. Consider mixed cropping, preferable with shrub / tree crops Provide shade When irrigating: assure water losses are minimised and check if lime/salt crusts are found in upper layer. If so, consult a soil institute.
B42: Water management | D42: All | E42: Drought | F42: Is drought (becoming) a limiting factor for crop production? | G42: No | H42: All | I42: Make sure soil structure is conserved to avoid compaction
A43: 1 | B43: Soil fertility | D43: All | E43: Nutrient deficiencies | F43: Is soil testing being done to determine fertilizer application? | G43: Yes | H43: All | I43: Determine appropriate fertilizer (both organic and inorganic) application schemes.
B44: Soil fertility | D44: All | E44: Nutrient deficiencies | F44: Is soil testing being done to determine fertilizer application? | G44: No | H44: All | I44: See if soil testing can be introduced or if nutrient deficiency can be otherwise determined by observation in crop or vegetation
B45: Working Conditions
B46: General | E46: Grievance Mechanism | F46: Is information about the grievance mechanism and the assess and address committee visible and accessible to all workers? | G46: Yes | H46: All | I46: Check & update public display regularly to make sure information is still correct, visible and accessible to all; including languages of local and temporary staff | J46: KM: I have copied this from Indiv CH for trader led groups - important that on sites with more than x no of workers, this rule also applies. What is the no of workers this should apply from?
B47: General | E47: Grievance Mechanism | F47: Is information about the grievance mechanism and the assess and address committee visible and accessible to all workers? | G47: No | H47: All | I47: Ensure that producers and workers have access to practical information in their language about how and where they can access the grievance mechanism and the assess and address committee when they have a grievance that they want to be resolved.
A48: 1 | B48: Discrimination | D48: All farm businesses | E48: Equal opportunities & prevention of discrimination | F48: Are any of the following groups present on or near the farm or group: - Migrant workers (foreign or from within the country) - Specific ethnic minority groups (any ethnicities which are not the largest ethnicity within the workforce) -Indigenous groups (where applicable) -Groups whose members do not speak the dominant language in the country & region | G48: yes | H48: All | I48: Assess whether members of these groups are group members, or workers on the farm, or working with group members, or contracted as group staff If this is the case, include unconscious bias and other anti discriminatory practices in the training and awareness raising of staff and management as required in 3.1.1 AND - publish vacancies for management and supervisory functions in a language(s) and in places accessible for all | J48: Wording to be adjusted (needs to be easy to understand). What do we mean with underrepresented?
B49: Discrimination | D49: All farm businesses | E49: Equal opportunities & prevention of discrimination | F49: Are any of the following groups present on or near the farm or group: - Migrant workers (foreign or from within the country) - Specific ethnic minority groups (any ethnicities which are not the largest ethnicity within the workforce) -Indigenous groups (where applicable) -Groups whose members do not speak the dominant language in the country & region | G49: no | H49: All | I49: No further action
B50: Discrimination | D50: All farm businesses | E50: Equal opportunities & prevention of discrimination | F50: If any of the following groups are present on the farm, have you undertaken action to fairly represent them amongst management, as internal inspector, or other decision making functions? : -Women -> will go to gender questions -Migrant workers (foreign or from within the country) - Specific ethnic minority groups (any ethnicities which are not the largest ethnicity within the workforce) -Indigenous groups (where applicable) -Groups whose members do not speak the dominant language in the country & region | G50: No | H50: medium, High
A51: 1 | B51: Workplace Violence and Harassment | D51: All farm businesses | E51: Workplace Violence and Harassment prevention | F51: Has the group's leadership taken any targeted action to prevent violence and harassment (including sexual harassment)? | G51: Yes | H51: All | I51: No further action | J51: This is the only appropriate formulation for this question - even still risk of false answers is high
B52: Workplace Violence and Harassment | D52: All farm businesses | E52: Workplace Violence and Harassment prevention | F52: Has the group's leadership taken any targeted action to prevent violence and harassment (including sexual harassment)? | G52: no | H52: Low | I52: No further action
B53: Workplace Violence and Harassment | D53: All farm businesses | E53: Workplace Violence and Harassment | F53: Has the group's leadership taken any targeted action to prevent violence and harassment (including sexual harassment)? | G53: No | H53: Med & High | I53: Implement at least one of the following measures: - Training of trainers, internal inspectors and other persons in direct contact with members and their workers on respectful behavior and concepts of workplace violence and harassment - training of workers on the topic on respectful behavior and concepts of workplace violence and harassment Please note: in most cases workplace violence and harassment will relate to experiences faced by women. However risks are also faced by men. Ensure your answers cover risks in relation to all workers regardless of gender.
A54: 1 | B54: Child labour | D54: All farm businesses | E54: Age verification | F54: Are farmer members required to validate hired workers' ages at the time they are appointed? | G54: Yes | H54: all | I54: In line with core requirement 1.2.2, for hired young workers (15 - 17 years), the registry contains: • housing address • Name and address of parent(s) or legal guardian(s) • School registration • Type of work or tasks • The number of daily and weekly working hours. | J54: This question is critical - while not focused on external risks - clarity and verifiability of the question on age verification is of highest importance
B55: Child labour | D55: All farm businesses | E55: Age verification | F55: Are farmer members required to validate hired workers' ages at the time they are appointed? | G55: Yes | H55: Lower, Med | I55: No further action
B56: Child labour | D56: All farm businesses | E56: Age verification | F56: Are farmer members required to validate hired workers' ages at the time they are appointed? | G56: No | H56: High | I56: Communicate to all farmers, who report they hire labour, how to verify the age of all new hires at the workplace, including those supplied by labour providers, in line with Core Requirement 1.2.2. Verification of age should be based on identity documents, school and medical records or other verifiable forms of identification proof. In line with core requirement 1.2.2, for hired young workers (15 - 17 years), the registry should contains: • housing address • Name and address of parent(s) or legal guardian(s) • School registration • Type of work or tasks • The number of daily and weekly working hours.
B57: Child labour | D57: All farm businesses | E57: Age verification | F57: Are farmer members required to validate hired workers' ages at the time they are appointed? | G57: No | H57: All | I57: a.For each under-18 year old worker, identify and record the name and contact information for their consenting family member. b. For each under-18 year old worker, identify the responsible adult member who will be supervising and guiding the child in work (‘young worker supervisor’) b.Where a high proportion of children and a low number of adults are part of the labor force, ensure the ratio of adult supervisors to workers younger than 18 meets national labor law requirements.
A58: 1 | B58: Child labour | D58: All farm businesses | E58: Hazardous work | F58: Have you listed any tasks, processes or other working conditions taking place on your farm that could be hazardous to young workers? | G58: Yes, please list | H58: Lower | I58: List the tasks and processes that involve hazardous working conditions
B59: Child labour | D59: All farm businesses | E59: Hazardous work | F59: Have you listed any tasks, processes or other working conditions taking place on your farm that could be hazardous to young workers? | G59: Yes, please list | H59: High | I59: 1) List the hazardous tasks / processes. 2) Communicate this list to all group members and; 3) through internal inspections and child labor monitoring, ensure members are aware that workers younger than 18 cannot perform these hazardous tasks.
B60: Child labour | D60: All farm businesses | E60: Hazardous work | F60: Have you listed any tasks, processes or other working conditions taking place on your farm that could be hazardous to young workers? | G60: No | H60: All | I60: 1) Develop a list of tasks and work processes – aligned with any relevant national policy - from which under 18s would be banned from performing. Ensure the list covers jobs that involve hazardous substances, dangerous equipment or heavy lifting. The list of tasks should also make clear that underage workers are prohibited from performing work at night or during school hours. 2) Review the list every season to ensure list is up to date with national policy. 3) Communicate to all group members what tasks are and are not hazardous 4) Clarify to group members that work by under 18s must be performed in accordance with the list 5) clarify internal steps and potential internal sanctions where it is discovered that a member is permitting under-18s to perform hazardous work.
B61: Child labour | D61: All farm businesses | E61: Hazardous work | F61: Have you listed any tasks, processes or other working conditions taking place on your farm that could be hazardous to young workers? | G61: No | H61: Med, High | I61: In addition to steps outlined in row 54: 1) Develop checklist to systematically monitor working conditions of under 18s, covering: protection against performing prohibited hazardous tasks, protection from harassment, abuse in the workplace. 2) Use this checklist at internal inspections;
B62: Child labour | D62: All farm businesses | E62: Hazardous work | F62: Is the group taking any steps to protect under 18 year old workers / children of group members from conducting hazardous tasks? | G62: yes | H62: Med, High | I62: Please list the steps; In addition to steps outlined in row 53, develop and implement Child Labor Monitoring System in accordance with A&A Monitoring Guidance and steps outlined in row 70
B63: Child labour | D63: All farm businesses | E63: Hazardous work | F63: Is the group taking any steps to protect under 18 year old workers / children of group members from conducting hazardous tasks? | G63: yes | H63: low | I63: Please list the steps
B64: Child labour | D64: All farm businesses | E64: Hazardous work | F64: Is the group taking any steps to protect under 18 year old workers / children of group members from conducting hazardous tasks? | G64: no | H64: Med, High | I64: In addition to steps outlined in row 54 and 55, set up child labor monitoring system in accordance with steps outlined in row 70 and Assess and Address monitoring guidance
B65: Child labour | D65: All farm businesses | E65: Hazardous work | F65: Is the group taking any steps to protect under 18 year old workers / children of group members from conducting hazardous tasks? | G65: no | H65: low | I65: no further steps (beyond those outlined in row 54)
A66: 1 | B66: Child labour | D66: All farm businesses | E66: Education | F66: Do children of group staff, group members and group members' workers, of school-going age, attend school within a safe walking distance or at reasonable traveling distance using safe transport? | G66: No | H66: Med, High | I66: 1) Identify reasons why children do not go to school: a) distance to school b) quality of education/violence in school / absence of teacher c) costs associated with schooling; 3) based on the analysis, together with local department of education and local NGOs, develop ways to support access to education for children of group staff, members or members' workers; this could include satelite classrooms in villages currently without schools, setting up sustainable and safe transport for the youngest children; removing barriers to education (e.g. birth certificates, family income, learning materials through support from government/supply chain partners) 3) create awareness about importance of education with group members & discuss ways with members how group can support children's education | J66: Ergon view: All countries we are looking at this stage offer some free or heavily subsidized education option - risk is more in relation to accessibility as opposed to availability or affordability
B67: Child labour | D67: All farm businesses | E67: Education | F67: Do children of group staff, group members and group members' workers, of school-going age, attend school within a safe walking distance or at reasonable traveling distance using safe transport? | G67: No | H67: Lower | I67: 1) Identify reasons why children do not go to school: a) distance to school b) quality of education/violence in school / absence of teacher c) costs associated with schooling; 3) based on the analysis, together with local department of education and local NGOs, develop ways to support access to education for children of group staff, members or members' workers; this could include satelite classrooms in villages currently without schools, setting up sustainable and safe transport for the youngest children; removing barriers to education (e.g. birth certificates, family income, learning materials through support from government/supply chain partners) 3) create awareness about importance of education with group members & discuss ways with members how group can support children's education | J67: Meike: there should be an option of don't know. The person filling in this information probably does not know exactly how far the schools are from all the farms...In the future maybe we can do something with automatization.
B68: Child labour | D68: All farm businesses | E68: Education | F68: Do children of group staff, group members and group members' workers, of school-going age, attend school within a safe walking distance or at reasonable traveling distance using safe transport? | G68: Yes | H68: Lower | I68: No further action
B69: Child labour | D69: All farm businesses | E69: Education | F69: Do children of group staff, group members and group members' workers, of school-going age, attend school within a safe walking distance or at reasonable traveling distance using safe transport? | G69: Yes | H69: High | I69: 1) Monitor school going behavior of members' children of school going age, through internal inspections and the assess and address monitoring; 2) The assess and address committee to establish contact with department of education to collaborate on drop-out cases / temporary absence / child labor cases when they happen
A70: 1 | B70: Child labour | D70: All farm businesses | E70: Family workers | F70: Do under-18s perform work on any of the farms within the group? | G70: Yes | H70: medium, High | I70: A&A committee to set up a child labour monitoring system including child labor monitors/child labor liaison officers. The plan should specify 1) how management will promote awareness (through child labor monitors as well as directly) on tasks that children are allowed to do and underage and hazardous child labor 2) how frequent child labor monitors will monitor that children are only performing non-hazardous, age appropriate tasks that do not interfere with schooling and 3) what follow up steps will be taken when risk of child labor increases 4) what the remediation process involves when cases have been confirmed through the grievance mechanism.
B71: Child labour | D71: All farm businesses | E71: Family workers | F71: Do under-18s perform work on any of the farms within the group? | G71: Yes | H71: All | I71: 1) Members are informed about policy of family child work and hiring young workers, including the age from which children can support their parents and conduct light work, the age from which children can be hired individually, in accordance with the Rainforest Alliance Standard as well as the national law. 2) Assess and address model is cleary explained to promote transparency about child labor risks and support solutions to mitigate the risk
D72: All farm businesses | E72: Family workers | F72: Do under-18s perform work on any of the farms within the group? | G72: Yes | H72: All | I72: When national law requirs medical screening tests for young workers before they start their employment contract, remind farmers of this requirement and verify this as part of internal inspections.
B73: Child labour | D73: All farm businesses | E73: Family workers | F73: Do under-18s perform work on any of the farms within the group? | G73: No | H73: Med, High | I73: Appoint child labor monitors [sufficient to provide an effective degree of coverage and visibility across farms in the producer group] to maintain oversight over children’s working, health and school attendance patterns and to maintain awareness of the group child labor policy across inspectors, farmers, young worker supervisors and hired workers themselves.
B74: Child labour | D74: All farm businesses | E74: Family workers | F74: Do under-18s perform work on any of the farms within the group? | G74: No | H74: Lower | I74: No further action
A75: 1 | B75: Forced labour | D75: All workplaces | E75: Labour providers | F75: Does the farm/group use labour providers to recruit any workers? | G75: No | H75: All | I75: No further action
B76: Forced labour | D76: All workplaces | E76: Labour providers | F76: Does the farm/group use labour providers to recruit any workers? | G76: Yes | H76: All | I76: 1. In the case of a small farm, the name, contact, and, if labor provider is officially registered and the official registration number of the labor provider is recorded. 2. Farms that employ an average of 5 or more workers, and group management, must ensure that the labor provider is licensed or certified by the competent national authority, if applicable.
B77: Forced labour | D77: All workplaces | E77: Labour providers | F77: Does the farm/group use labour providers to recruit any workers? | G77: Yes | H77: Med, High | I77: 1. Farms employing an average of 5 or more workers and group management should have written contracts with each labor provider, requiring that labor providers abide by RA worker protection standards. 2. When possible, farms/groups should directly contract workers who are recruited by labor providers. 3. For workers whose direct employer is a labor provider, the Assess & Address monitoring system should check periodically with some of these workers to ensure that their pay, working conditions, etc. are as promised by the labor provider. 4. Workers recruited through labor providers should be treated equally with other workers and provided the same information about their protections under the RA standard. 5. The Assess & Address monitoring system should periodically check with workers who are recruited through labor providers, to see if they owe any debts related to recruitment fees. If so, the farm should negotiate with the labor provider full repayment of these fees to the worker. 6. Farms/groups should stop working with labor recruiters that do not meet these expectations.
D78: All workplaces | E78: Wage payment practices | F78: Are workers paid by volume/piece rate? | G78: No | H78: All | I78: No further action.
A79: 1 | B79: Forced labour | D79: All workplaces | E79: Wage payment practices | F79: Are workers paid by volume/piece rate? | G79: Yes | H79: All | I79: 1. Farms/groups must ensure that workers have written or verbal contracts in place according to requirement 3.3. 2. When calculated by volume, workers' pay must equal at least the minimum wage based on a 48-hour working week or national legal working hours limit. 3. Deductions from wages for costs such as employer-provided housing or food must only be taken with workers' consent. 4. Farms that employ an average of 5 or more workers, and group management, must pay workers at least monthly and provide workers pay slips showing hours worked (regular and overtime) and/or volume produced, calculation of wages and deductions, and wages paid.
D80: All workplaces | E80: Wage payment practices | F80: Are workers paid by volume/piece rate? | G80: Yes | H80: Med, High | I80: 1. Group management should confirm that personnel responsible for wage payment are correctly trained in calculations and requirements.
B81: Forced labour | D81: All workplaces | E81: Freedom of movement | F81: Are security guards present on the farm/group premises? | G81: No | H81: All | I81: No further action
B82: Forced labour | D82: All workplaces | E82: Freedom of movement | F82: Are security guards present on the farm/group premises? | G82: Yes | H82: All | I82: 1. Farms/groups should communicate to workers of their rights under the law to freely leave the job. This can be done through their contracts, information posted in the workplace, a workers' organization, one of the farm's committees, or other means. 2. For workers living on the farm, farms should communicate their rights to freedom of movement on and off the farm outside working hours.
B83: Forced labour | D83: All workplaces | E83: Freedom of movement | F83: Are security guards present on the farm/group premises? | G83: Yes | H83: Med, High | I83: 1. The Assess & Address monitoring system, working with other committees such as the Gender Committee, should periodically check with workers to see if they feel threatened by security guards.
B84: Forced labour | D84: Non-local workers are included among the workforce How will we know this; is it a question in the registry? | E84: Prison/military labor | F84: Are any workers recruited/provided to the farm/group by military or prison officials? | G84: No | H84: All | I84: No further actions.
A85: 1 | B85: Forced labour | D85: Non-local workers are included among the workforce How will we know this; is it a question in the registry? | E85: Prison/military labor | F85: Are any workers recruited/provided to the farm/group by military or prison officials? | G85: Yes | H85: All | I85: 1. Military officials mobilizing military personnel to perform agricultural labor is a form of forced labor. Farms must not utilize this type of labor. 2. Farms must ensure that any prisoners working on the farm have freely provided their consent to work. 3. Prison labor must be treated the same as all other workers with respect to contracts, pay, working conditions, and all other worker protections in the RA standard.
B86: Forced labour | D86: Non-local workers are included among the workforce How will we know this; is it a question in the registry? | E86: Prison/military labor | F86: Are any workers recruited/provided to the farm/group by military or prison officials? | G86: Yes | H86: Med, High | I86: 1. The Assess & Address monitoring system should periodically check with prison laborers to ensure they are receiving the same treatment as other workers.
A87: 1 | B87: Forced labour | D87: Non-local workers are included among the workforce How will we know this; is it a question in the registry? | E87: Deposit or document retention | F87: Do workers give any money (such as deposits) or documents (such as passports) to farm management or labor providers? | G87: No | H87: All | I87: No further action.
B88: Forced labour | D88: Non-local workers are included among the workforce How will we know this; is it a question in the registry? | E88: Deposit or document retention | F88: Do workers give any money (such as deposits) or documents (such as passports) to farm management or labor providers? | G88: Yes | H88: All | I88: 1. Farms/groups should not require workers to pay any type of deposit or provide any personal document to management, other than to confirm identity at the time of hiring.
B89: Forced labour | D89: Non-local workers are included among the workforce How will we know this; is it a question in the registry? | E89: Deposit or document retention | F89: Do workers give any money (such as deposits) or documents (such as passports) to farm management or labor providers? | G89: Yes | H89: Med, High | I89: 1. The Assess & Address monitoring system, working with other committees such as the Grievance Committee, should periodically check with workers to see if they have had to pay deposits or hand over documents. 2. In instances where workers prefer to provide documents or other belongings to management for safe keeping, farm/group management must ensure that workers have permanent, unrestricted access to these locations.
A90: 1 | B90: Gender | D90: All | E90: Gender Commitment from Leadership | F90: Has management undertaken significant action in the past to address gender equality and/or women empowerment? | G90: yes | H90: All | I90: No further action | J90: Shouldn't management keep these actions in place?
B91: Gender | D91: All | E91: Gender Commitment from Leadership | F91: Has management undertaken significant action in the past to address gender equality and/or women empowerment? | G91: No | H91: All | I91: Formulation of a policy on gender equality and women’s empowerment which will be shared with the rest of the group, AND/OR Stakeholder mapping of gender related organizations that could help to incorporate gender within group, AND/OR Ensure that management and/or other high-level functions are accountable for meeting the gender plan targets
B92: Gender | D92: All | E92: Female representation in group | F92: Is a significant number of female farmers (co) member of the group? | G92: yes | H92: All | I92: no further action needed
B93: Gender | D93: All | E93: Female representation in group | F93: Is a significant number of female farmers (co) member of the group? | G93: No | H93: All | I93: - Develop measures to facilitate access of female farmers to the group (e.g. by lowering membership fees, by promoting co- registration with partner, by actively inviting female farmers to become a part, by installing a minimum quota, etc.) AND/OR - Undertake measures to ensure that trainings and other services that are offered by the group are accessible for all female farmers
A94: 1 | B94: Gender | D94: All | E94: Representation in higher level functions | F94: Are female farmers currently represented significally in relation to their number amongst trainers, internal inspectors and/or other high level functions within the group | G94: yes | H94: All | I94: No further action
B95: Gender | D95: All | E95: Representation in higher level functions | F95: Are female farmers currently represented significally in relation to their number amongst trainers, internal inspectors and/or other high level functions within the group | G95: No | H95: All | I95: establish a minimum quota for female trainers and inspectors and other high level functions AND/OR - organize training targeted at female farmers that is needed to be eligible as a trainer, inspector or other high level function AND/OR - make sure job announcements reach male AND female farmers and that job requirements are achievable for female farmers AND/OR - give training to management staff involved in recruitment on unconscious bias and methodologies to prevent gender based discriminatory practices
B96: Gender | D96: All | E96: Gender Training for Leadership | F96: Have management, supervisors, and/or internal inspectors been trained in the past year on gender equality? | G96: yes | H96: all | I96: No further actions
B97: Gender | E97: Gender Training for Leadership | F97: Have management, supervisors, and/or internal inspectors been trained in the past year on gender equality? | G97: No | H97: all | I97: -Train management, supervisors, and/or internal inspectors annually on issues related to gender equality and women’s empowerment (maternity leave, sexual harassment…) AND/OR make gender-related trainings (e.g. sexual harassment, discrimination, gender equality or gender bias) a requirement for all management, supervisors, and internal inspectors, AND/OR partner with local NGOs to provide gender bias or gender equality training to management, supervisors, internal inspectors
B98: Environment
B99: Analysis Geodata | D99: All | E99: Deforestation | F99: Member provided envelope and the overlap with Deforestation country risk map showed risks | G99: Automatic | H99: ? | I99: Identify farms located in the high and medium risk areas (red and orange) and include them in the Internal Inspection plan according to: Farms in red area should be identified and if deforestation happened within the farm boundaries, the farm should be excluded from the certification For farms in orange area, verify if there are parts of them that fall within the red area and if so, identify whether deforestation happend within the boudaries, if yes, the farm should be excluded from the certification For those producers that are orange or red, and it seems like they have not deforested, but are close to areas where there is still forest and/or where recent deforestation has happened: inform them that deforestation is not allowed, set up MoUs with them that they will not expand into the forest; organize awareness raising sessions | J99: Henriette: I thought we were going to discuss the follow up on the risk categories, and that it was not decided yet.
D100: All | F100: Member provided geodata (point/polygon) and they overlap with deforestation country risk map | G100: Automatic | H100: ? | I100: Include in montintoring and internal inspection activities data from the analysis: farms/farm units whose buffers/polygons overlap completely with deforested area should not be certified Member to verify whether deforestation occurred inside farms/farm units whose buffers/polygons partly overlap with deforested area.
...

Sheet Tableau de bord
B2: =G129 -> Outil de Base d’Evaluation des Risques
B4: =G112 -> Type de titulaire de certificat (sélectionner)
B5: Certification de groupe | C5: =G133 -> <- Selectionnez "Grande" pour les grandes exploitations agricoles (individuelles et en groupe) et les petites exploitations agricoles certifiées individuellemen.
B7: =H112 -> Gestion
B9: =$G$113 -> Exigence du standard | C9: =$G$114 -> Problème | D9: =$G$115 -> No. de question | E9: =$G$116 -> Question | F9: =$G$117 -> Réponse (sélectionner) | G9: =$G$118 -> Mesure d’atténuation | H9: =$G$119 -> Mesure d'atténuation propre du titulaire de certificat
B10: =VLOOKUP(D10,'Basic Risk Assessment DATASHEET'!A:B,2,FALSE) -> 1.2.10 Zone de l’exploitation agricole | C10: =VLOOKUP(D10,'Basic Risk Assessment DATASHEET'!A:E,5,FALSE) -> Déforestation/défrichement illicite et couverture végétale indigène | D10: 1 | E10: =IFERROR(VLOOKUP($B$10&D10&$B$5,'Basic Risk Assessment DATASHEET'!$F$3:$G$129,2,FALSE),B128) -> Vous attendez-vous à ce que les sites de production des membres du groupe s’étendent ou changent ? | F10: Oui | G10: =VLOOKUP(RIGHT(E10&F10,250),'Basic Risk Assessment DATASHEET'!$J$3:$K$129,2,FALSE) -> S’assurer, grâce à la sensibilisation et au suivi régulier, que les producteurs et les travailleurs sachent que la végétation naturelle et les écosystèmes naturels doivent être conservés. Marquer clairement les limites des écosystèmes naturels dans l’exploitation agricole et leurs zones tampons et s’assurer que les activités de transformation et de production, dont l'utilisation des produits agrochimiques, n’empiètent pas sur ces zones.
B12: =$G$113 -> Exigence du standard | C12: =$G$114 -> Problème | D12: =$G$115 -> No. de question | E12: =$G$116 -> Question | F12: =$G$117 -> Réponse (sélectionner) | G12: =$G$118 -> Mesure d’atténuation | H12: =$G$119 -> Mesure d'atténuation propre du titulaire de certificat
B13: =VLOOKUP(D13,'Basic Risk Assessment DATASHEET'!A:B,2,FALSE) -> 2.1 Traçabilité | C13: =VLOOKUP(D13,'Basic Risk Assessment DATASHEET'!A:E,5,FALSE) -> Intermédiaires | D13: 2 | E13: =IFERROR(VLOOKUP($B$13&D13&$B$5,'Basic Risk Assessment DATASHEET'!$F$3:$G$129,2,FALSE),$B$128) -> Utilisez-vous/Utiliserez-vous des intermédiaires et/ou des sous-traitants* dans votre chaîne d'approvisionnement ? | F13: Non | G13: =VLOOKUP(RIGHT(E13&F13,250),'Basic Risk Assessment DATASHEET'!$J$3:$K$129,2,FALSE) -> 1) Mettre en place un flux clair de traçabilité, qui inclut les règles de traçabilité physiques et documentées pour tous les acteurs de votre chaîne d'approvisionnement (agriculteurs, unités de transformation, transport, centres de collecte, direction, etc.). 2) Former tous les acteurs sur votre procédure de traçabilité. 3) Suivre la traçabilité et tenir des registres de tous les acteurs.
C14: =VLOOKUP(D14,'Basic Risk Assessment DATASHEET'!A:E,5,FALSE) -> Tenue de registres | D14: 3 | E14: =IFERROR(VLOOKUP($B$13&D14&$B$5,'Basic Risk Assessment DATASHEET'!$F$3:$G$129,2,FALSE),$B$128) -> Vous attendez-vous à ce que les agriculteurs aient des difficultés à tenir des registres (traçabilité) ? | F14: Oui | G14: =VLOOKUP(RIGHT(E14&F14,250),'Basic Risk Assessment DATASHEET'!$J$3:$K$129,2,FALSE) -> 1) Inclure l'administration/conservation des reçus dans le plan de formation. 2) Le groupe aide l’agriculteur à conserver les reçus au même endroit (ex : pochette plastique). 3) Mettre des affiches pour encourager les agriculteurs à conserver les reçus. 4) Faire le suivi de la conservation des reçus.
C15: =VLOOKUP(D15,'Basic Risk Assessment DATASHEET'!A:E,5,FALSE) -> Séparation des produits | D15: 4 | E15: =IFERROR(VLOOKUP($B$13&D15&$B$5,'Basic Risk Assessment DATASHEET'!$F$3:$G$129,2,FALSE),$B$128) -> Gérez-vous/allez-vous (direction) utiliser uniquement des produits certifiés RA et/ou achetez-vous/achèterez-vous uniquement à des producteurs certifiés RA ? | F15: Non | G15: =VLOOKUP(RIGHT(E15&F15,250),'Basic Risk Assessment DATASHEET'!$J$3:$K$129,2,FALSE) -> 1) Mettre en œuvre un système pour identifier les produits provenant de producteurs certifiés par des moyens d'identification physique ou visuelle et au niveau des documents de traçabilité (reçus, registre, etc.). 2) Par exemple, des étiquettes sur les sacs durant le transport et le stockage des produits peuvent représenter une identification visuelle.
C16: =VLOOKUP(D16,'Basic Risk Assessment DATASHEET'!A:E,5,FALSE) -> Volumes récoltés | D16: 5 | E16: =IFERROR(VLOOKUP($B$13&D16&$B$5,'Basic Risk Assessment DATASHEET'!$F$3:$G$129,2,FALSE),$B$128) -> Les membres du groupe ont-ils accès à des débouchés commerciaux/acheteurs différents pour leurs produits certifiés ? | F16: Non | G16: =VLOOKUP(RIGHT(E16&F16,250),'Basic Risk Assessment DATASHEET'!$J$3:$K$129,2,FALSE) -> Pas d’action supplémentaire requise
C17: =VLOOKUP(D17,'Basic Risk Assessment DATASHEET'!A:E,5,FALSE) -> Opérateurs de l’exploitation agricole | D17: 6 | E17: =IFERROR(VLOOKUP($B$13&D17&$B$5,'Basic Risk Assessment DATASHEET'!$F$3:$G$129,2,FALSE),$B$128) -> Les membres du groupe dépendent-ils souvent des opérateurs des exploitations agricoles pour gérer leur exploitation agricole ? | F17: Non | G17: =VLOOKUP(RIGHT(E17&F17,250),'Basic Risk Assessment DATASHEET'!$J$3:$K$129,2,FALSE) -> Pas d’action supplémentaire requise
B20: =$G$113 -> Exigence du standard | C20: =$G$114 -> Problème | D20: =$G$115 -> No. de question | E20: =$G$116 -> Question | F20: =$G$117 -> Réponse (sélectionner) | G20: =$G$118 -> Mesure d’atténuation | H20: =$G$119 -> Mesure d'atténuation propre du titulaire de certificat
B21: =VLOOKUP(D21,'Basic Risk Assessment DATASHEET'!A:B,2,FALSE) -> Le terme ‘productivité et rentabilité’ fait référence aux points suivants : 2.1.2 rendement des récoltes ; 1.3.6 entrées financières et compétences ; 1.3.7 diversification ; 3.1. coûts de production et Revenu vital | C21: =VLOOKUP(D21,'Basic Risk Assessment DATASHEET'!A:E,5,FALSE) -> Récolte optimum | D21: 7 | E21: =IFERROR(VLOOKUP($B$21&D21&$B$5,'Basic Risk Assessment DATASHEET'!$F$3:$G$129,2,FALSE),$B$128) -> Le rendement moyen de la culture certifiée des membres du groupe est-il égal ou supérieur au rendement moyen dans votre région ? | F21: Non/Ne sais pas | G21: =VLOOKUP(RIGHT(E21&F21,250),'Basic Risk Assessment DATASHEET'!$J$3:$K$129,2,FALSE) -> 1) Former le personnel à reconnaitre et à prioriser les contraintes de production sur le terrain. 2) Identifier les principales contraintes de productivité sur le terrain. 3) Mettre en place des expérimentations et des modèles d’exploitations agricoles en vue de présenter l’impact de la régénération et de la fertilisation des sols ainsi que de la lutte efficace contre les maladies et les ravageurs
C22: =VLOOKUP(D22,'Basic Risk Assessment DATASHEET'!A:E,5,FALSE) -> Accès à la finance, aux intrants et aux connaissances | D22: 8 | E22: =IFERROR(VLOOKUP($B$21&D22&$B$5,'Basic Risk Assessment DATASHEET'!$F$3:$G$129,2,FALSE),$B$128) -> Tous les membres du groupe ont-ils accès aux financements, aux intrants agricoles et aux connaissances adéquates pour optimiser la productivité ? | F22: Non/Ne sais pas | G22: =VLOOKUP(RIGHT(E22&F22,250),'Basic Risk Assessment DATASHEET'!$J$3:$K$129,2,FALSE) -> 1) Identifier les principaux besoins des membres du groupe concernant les intrants et les connaissances. 2) Aider les membres du groupe avec des formations en finance, en gestion d’entreprise et en compréhension des coûts de production, des revenus nets et de l'élaboration d'un plan d'affaires simple (exigence librement choisie 1.3.6). 3) Au besoin, faciliter l’accès aux services financiers (ex : prêts pour les investissements des exploitations agricoles) (exigence librement choisie 1.3.6).
C23: =VLOOKUP(D23,'Basic Risk Assessment DATASHEET'!A:E,5,FALSE) -> Revenu vital | D23: 9 | E23: =IFERROR(VLOOKUP($B$21&D23&$B$5,'Basic Risk Assessment DATASHEET'!$F$3:$G$129,2,FALSE),$B$128) -> Tous les membres du groupe tirent-ils un revenu décent avec la production de la culture certifiée ? | F23: Non/Ne sais pas | G23: =VLOOKUP(RIGHT(E23&F23,250),'Basic Risk Assessment DATASHEET'!$J$3:$K$129,2,FALSE) -> 1) Évaluer le revenu net total pour un échantillon représentatif des ménages des membres du groupe en utilisant la référence de Revenu vital (exigence librement choisie 3.1.2). 2) Aider les membres du groupe avec des formations en finance, en gestion d’entreprise et en compréhension des coûts de production, des revenus nets et de l'élaboration d'un plan d'affaires simple (exigence librement choisie 1.3.6). 3) Au besoin, faciliter l’accès aux services financiers (ex : prêts pour les investissements des exploitations agricoles) (exigence librement choisie 1.3.6). 4) Aider les membres du groupe à prendre des décisions en connaissance de cause concernant les stratégies de diversification des revenus (ex : d’autres activités de génération de revenus, modernisation du produit) (exigence librement choisie 1.3.7).
B26: =H113 -> Pratiques agricoles
B28: =$G$113 -> Exigence du standard | C28: =$G$114 -> Problème | D28: =$G$115 -> No. de question | E28: =$G$116 -> Question | F28: =$G$117 -> Réponse (sélectionner) | G28: =$G$118 -> Mesure d’atténuation | H28: =$G$119 -> Mesure d'atténuation propre du titulaire de certificat
B29: =VLOOKUP(D29,'Basic Risk Assessment DATASHEET'!A:B,2,FALSE) -> 4.6 Gestion des produits agrochimiques | C29: =VLOOKUP(D29,'Basic Risk Assessment DATASHEET'!A:E,5,FALSE) -> Utilisation des produits agrochimiques interdits | D29: 10 | E29: =IFERROR(VLOOKUP($B$29&D29&$B$5,'Basic Risk Assessment DATASHEET'!$F$3:$G$129,2,FALSE),$B$128) -> Examiner la Liste des produits agrochimiques interdits de Rainforest Alliance : L’utilisation sur l’exploitation d’un ou plusieurs produits phytosanitaires inclus dans la Liste des produits interdits par Rainforest Alliance est-elle une pratique courante dans la région ? | F29: Non | G29: =VLOOKUP(RIGHT(E29&F29,255),'Basic Risk Assessment DATASHEET'!$J$3:$K$129,2,FALSE) -> Pas d’action supplémentaire requise
C30: =VLOOKUP(D30,'Basic Risk Assessment DATASHEET'!A:E,5,FALSE) -> Quantité d’applications de pesticides | D30: 11 | E30: =IFERROR(VLOOKUP($B$29&D30&$B$5,'Basic Risk Assessment DATASHEET'!$F$3:$G$129,2,FALSE),$B$128) -> Est-il pratique habituelle pour les agriculteurs de d’abord essayer les méthodes de contrôle biologique, physique et autres méthodes non chimiques (PIC) pour le contrôle des ravageurs avant d’utiliser des produits agrochimiques ? | F30: Oui | G30: =VLOOKUP(RIGHT(E30&F30,250),'Basic Risk Assessment DATASHEET'!$J$3:$K$129,2,FALSE) -> Pas d’action supplémentaire requise
C31: =VLOOKUP(D31,'Basic Risk Assessment DATASHEET'!A:E,5,FALSE) -> Utilisation d’EPI | D31: 12 | E31: =IFERROR(VLOOKUP($B$29&D31&$B$5,'Basic Risk Assessment DATASHEET'!$F$3:$G$129,2,FALSE),$B$128) -> Est-il pratique habituelle que les membres du groupe et/ou leurs travailleurs utilisent des Équipements de protection individuelle (EPI) pour l’application des produits agrochimiques ? | F31: Oui | G31: =VLOOKUP(RIGHT(E31&F31,250),'Basic Risk Assessment DATASHEET'!$J$3:$K$129,2,FALSE) -> Pas d’action supplémentaire requise
B33: =$G$113 -> Exigence du standard | C33: =$G$114 -> Problème | D33: =$G$115 -> No. de question | E33: =$G$116 -> Question | F33: =$G$117 -> Réponse (sélectionner) | G33: =$G$118 -> Mesure d’atténuation | H33: =$G$119 -> Mesure d'atténuation propre du titulaire de certificat
B34: =VLOOKUP(D34,'Basic Risk Assessment DATASHEET'!A:B,2,FALSE) -> 4.4 Fertilité et conservation des sols | C34: =VLOOKUP(D34,'Basic Risk Assessment DATASHEET'!A:E,5,FALSE) -> Érosion | D34: 13 | E34: =IFERROR(VLOOKUP($B$34&D34&$B$115,'Basic Risk Assessment DATASHEET'!$F$3:$G$129,2,FALSE),$B$128) -> Est-ce qu'il y a des zones qui ont une pente supérieure à 1m de haut sur 3m de long sur une zone >0,1ha ? | F34: Non | G34: =VLOOKUP(RIGHT(E34&F34,250),'Basic Risk Assessment DATASHEET'!$J$3:$K$129,2,FALSE) -> S’assurer qu’il n'y ait pas de formation de ravines et que la couche organique supérieure n’est pas lessivée.
C35: =VLOOKUP(D35,'Basic Risk Assessment DATASHEET'!A:E,5,FALSE) -> Engorgement hydrique/stagnation de l'eau | D35: 14 | E35: =IFERROR(VLOOKUP($B$34&D35&$B$115,'Basic Risk Assessment DATASHEET'!$F$3:$G$129,2,FALSE),$B$128) -> Après les pluies, y-a-t-il des zones au sein de l’exploitation agricole/des exploitations agricoles des membres du groupe avec de longues périodes d’eaux stagnantes ? | F35: Oui | G35: =VLOOKUP(RIGHT(E35&F35,250),'Basic Risk Assessment DATASHEET'!$J$3:$K$129,2,FALSE) -> Mettre en œuvre des mesures pour améliorer le drainage via des mesures physiques, en creusant des tranchées de drainage ou en améliorant la structure du sol pour augmenter la capacité des sols à absorber l’eau et à la garder.
C36: =VLOOKUP(D36,'Basic Risk Assessment DATASHEET'!A:E,5,FALSE) -> Engorgement hydrique/stagnation de l'eau | D36: 15 | E36: =IFERROR(VLOOKUP($B$34&D36&$B$115,'Basic Risk Assessment DATASHEET'!$F$3:$G$129,2,FALSE),$B$128) -> Est-ce que le niveau élevé des eaux souterraines est un problème dans certaines zones ? | F36: Oui | G36: =VLOOKUP(RIGHT(E36&F36,250),'Basic Risk Assessment DATASHEET'!$J$3:$K$129,2,FALSE) -> 1) Évaluer si la zone est adaptée pour la culture et prendre en compte quelles sont les cultures appropriées pour ces zones. 2) Dans certains cas : améliorer le drainage et/ou conserver la végétation protectrice.
C37: =VLOOKUP(D37,'Basic Risk Assessment DATASHEET'!A:E,5,FALSE) -> Sécheresse | D37: 16 | E37: =IFERROR(VLOOKUP($B$34&D37&$B$115,'Basic Risk Assessment DATASHEET'!$F$3:$G$129,2,FALSE),$B$128) -> Est-ce que la sécheresse est (devient) un facteur limitant pour la production des cultures ? | F37: Non | G37: =VLOOKUP(RIGHT(E37&F37,250),'Basic Risk Assessment DATASHEET'!$J$3:$K$129,2,FALSE) -> S’assurer que la structure du sol est conservée pour éviter la compaction.
B39: =H114 -> Conditions de travail
B41: =$G$113 -> Exigence du standard | C41: =$G$114 -> Problème | D41: =$G$115 -> No. de question | E41: =$G$116 -> Question | F41: =$G$117 -> Réponse (sélectionner) | G41: =$G$118 -> Mesure d’atténuation | H41: =$G$119 -> Mesure d'atténuation propre du titulaire de certificat
B42: =VLOOKUP(D42,'Basic Risk Assessment DATASHEET'!A:B,2,FALSE) -> 1.5 Mécanisme de réclamation | C42: =VLOOKUP(D42,'Basic Risk Assessment DATASHEET'!A:E,5,FALSE) -> Mécanisme de réclamation | D42: 17 | E42: =IFERROR(VLOOKUP($B$42&D42&$B$115,'Basic Risk Assessment DATASHEET'!$F$3:$G$129,2,FALSE),$B$128) -> L’information relative au mécanisme de réclamation et au comité d’évaluation et de résolution est-elle visible et accessible par tous les individus, travailleurs, communautés et/ou la société civile ? | F42: Oui | G42: =VLOOKUP(RIGHT(E42&F42,250),'Basic Risk Assessment DATASHEET'!$J$3:$K$129,2,FALSE) -> Vérifier et mettre à jour régulièrement l’affichage public afin d’être sûr que les informations sont toujours correctes, visibles et accessibles par tous, y compris dans les langues du personnel local et temporaire
G44: =HYPERLINK("https://www.rainforest-alliance.org/in-the-field/manage-risk-with-the-rainforest-alliance-child-labor-and-forced-labor-sectoral-risk-maps/") -> https://www.rainforest-alliance.org/in-the-field/manage-risk-with-the-rainforest-alliance-child-labor-and-forced-labor-sectoral-risk-maps/
B45: =$G$113 -> Exigence du standard | C45: =$G$114 -> Problème | D45: =$G$115 -> No. de question | E45: =$G$116 -> Question | F45: =$G$117 -> Réponse (sélectionner) | G45: =G134 -> Mesures d'atténuation ("risque bas, moyen, élevé" se refère aux cartes de risque Rainforest Alliance sur le Travail des Enfants et le Travail Forcé qui sont applicables à votre pays et votre produit) <- Pour les pays ou les cultures qui ne sont pas encore inclus dans les cartes de risques, veuillez sélectionner les mesures d'atténuation appropriées en vous basant sur les risques identifiés. | H45: =$G$119 -> Mesure d'atténuation propre du titulaire de certificat
B46: =VLOOKUP(D46,'Basic Risk Assessment DATASHEET'!A:B,2,FALSE) -> 5.1 Évaluation-et-Résolution | C46: =VLOOKUP(D46,'Basic Risk Assessment DATASHEET'!A:E,5,FALSE) -> Égalité des chances et prévention de la discrimination | D46: 18 | E46: =IFERROR(VLOOKUP($B$46&D46&$B$115,'Basic Risk Assessment DATASHEET'!$F$3:$G$129,2,FALSE),$B$128) -> Les populations suivantes sont-elles présentes sur ou à proximité de l’exploitation agricole ou du groupe ? Travailleurs migrants, minorités ethniques particulières, populations autochtones, personnes qui ne parlent pas la langue principale du pays et de la région. | F46: Oui | G46: =VLOOKUP(RIGHT(E46&F46,255),'Basic Risk Assessment DATASHEET'!$J$3:$K$129,2,FALSE) -> 1) Évaluer si les membres de ces populations travaillent sur l’exploitation agricoles ou sont employés par les membres du groupe. 2) S’assurer que la direction de l'exploitation agricole et du groupe est consciente du type de populations présentes et qu’elle consigne leurs caractéristiques : type de population, nombre (estimation), langue et autres paramètres appropriés.
C47: =VLOOKUP(D47,'Basic Risk Assessment DATASHEET'!A:E,5,FALSE) -> Égalité des chances et prévention de la discrimination | D47: 19 | E47: =IFERROR(VLOOKUP($B$46&D47&$B$5,'Basic Risk Assessment DATASHEET'!$F$3:$G$129,2,FALSE),$B$128) -> (Ne s'applique pas à ce type de Titulaire de Certificat) | F47: Oui | G47: =VLOOKUP(RIGHT(E47&F47,255),'Basic Risk Assessment DATASHEET'!$J$3:$K$129,2,FALSE) -> #N/A
C48: =VLOOKUP(D48,'Basic Risk Assessment DATASHEET'!A:E,5,FALSE) -> Prévention de la violence et du harcèlement au travail | D48: 20 | E48: =IFERROR(VLOOKUP($B$46&D48&$B$115,'Basic Risk Assessment DATASHEET'!$F$3:$G$129,2,FALSE),$B$128) -> Est-ce que la direction met en place des actions ciblées pour empêcher la violence et le harcèlement (dont le harcèlement sexuel) ? | F48: Oui | G48: =VLOOKUP(RIGHT(E48&F48,255),'Basic Risk Assessment DATASHEET'!$J$3:$K$129,2,FALSE) -> Pas d’action supplémentaire requise
C49: =VLOOKUP(D49,'Basic Risk Assessment DATASHEET'!A:E,5,FALSE) -> Prévention de la violence et du harcèlement au travail | D49: 21 | E49: =IFERROR(VLOOKUP($B$46&D49&$B$5,'Basic Risk Assessment DATASHEET'!$F$3:$G$129,2,FALSE),$B$128) -> (Ne s'applique pas à ce type de Titulaire de Certificat) | F49: Oui | G49: =VLOOKUP(RIGHT(E49&F49,255),'Basic Risk Assessment DATASHEET'!$J$3:$K$129,2,FALSE) -> #N/A
C50: =VLOOKUP(D50,'Basic Risk Assessment DATASHEET'!A:E,5,FALSE) -> Vérification de l’âge | D50: 22 | E50: =IFERROR(VLOOKUP($B$46&D50&$B$5,'Basic Risk Assessment DATASHEET'!$F$3:$G$129,2,FALSE),$B$128) -> Le risque existe-t-il que les membres du groupe d’exploitations agricoles ne vérifient pas de la conformité de l’âge des travailleurs employés au moment de leur embauche ? | F50: Oui | G50: =VLOOKUP(RIGHT(E50&F50,255),'Basic Risk Assessment DATASHEET'!$J$3:$K$129,2,FALSE) -> 1) Expliquer à tous les agriculteurs qui ont embauché des travailleurs comment vérifier l’âge de toutes les nouvelles embauches sur le lieu de travail, y compris celui de travailleurs envoyés par les agences de placement. 2) La vérification de l’âge doit se baser sur les documents d'identité, les dossiers scolaires et médicaux ou sur d’autres formulaires vérifiables de preuves d’identité. 3) Vérifier avec l'inspection interne les données de la liste des travailleurs.
C51: =VLOOKUP(D51,'Basic Risk Assessment DATASHEET'!A:E,5,FALSE) -> Travail dangereux | D51: 23 | E51: =IFERROR(VLOOKUP($B$46&D51&$B$5,'Basic Risk Assessment DATASHEET'!$F$3:$G$129,2,FALSE),$B$128) -> Est-ce que la direction du groupe a listé des tâches, des processus ou des conditions de travail qui pourraient être dangereuses pour les jeunes travailleurs ? | F51: Oui | G51: =VLOOKUP(RIGHT(E51&F51,255),'Basic Risk Assessment DATASHEET'!$J$3:$K$129,2,FALSE) -> Faible risque : Communiquer cette liste à tous les membres du groupe qui embauchent des jeunes travailleurs Risque moyen et élevé : 1) Communiquer cette liste à tous les membres du groupe et ; 2) S’assurer, via la formation et le suivi du travail des enfants, que les membres savent qu’il est interdit d’assigner les jeunes travailleurs de moins de 18 ans à des tâches dangereuses. 3) Vérifier via des inspections internes que la liste existe, que cette liste est communiquée et que le contrôle du travail des enfants est effectué et focalisé sur les tâches dangereuses
C52: =VLOOKUP(D52,'Basic Risk Assessment DATASHEET'!A:E,5,FALSE) -> Education | D52: 24 | E52: =IFERROR(VLOOKUP($B$46&D52&$B$5,'Basic Risk Assessment DATASHEET'!$F$3:$G$129,2,FALSE),$B$128) -> Existe-t-il un risque que les enfants du personnel du groupe, ou des membres du groupe, ou les enfants des travailleurs, en âge scolaire, ne puissent fréquenter une école implantée à une distance de transport ou de marche garantissant leur sécurité ? (Utiliser la carte de la zone du groupe pour évaluer cela) | F52: Oui | G52: =VLOOKUP(RIGHT(E52&F52,255),'Basic Risk Assessment DATASHEET'!$J$3:$K$129,2,FALSE) -> 1) Sensibiliser les membres du groupe à l’importance de l’éducation et discuter avec eux des différentes manières dont dispose le groupe pour faciliter l’accès des enfants à l’éducation. 2) Identifier via des inspections internes si les enfants de membres du groupe sont exposés à un risque plus élevé de ne pas pouvoir fréquenter l’école en raison de son éloignement ou à cause d’autres problèmes d’accessibilité. 3) Définir et mettre en œuvre une procédure par étapes d’aide aux familles permettant aux enfants de fréquenter l’école (directement ou via le Ministère ou le Service de l’éducation ou via les ‘AVEC’ - Associations Villageoises d’Épargne et de Crédit)
C53: =VLOOKUP(D53,'Basic Risk Assessment DATASHEET'!A:E,5,FALSE) -> Travailleurs familiaux | D53: 25 | E53: =IFERROR(VLOOKUP($B$46&D53&$B$5,'Basic Risk Assessment DATASHEET'!$F$3:$G$129,2,FALSE),$B$128) -> Existe-t-il un risque que des jeunes de moins de 18 ans soient assignés à des tâches dangereuses et/ou pour lesquelles ils sont trop jeunes dans l’une des exploitations du groupe ? | F53: Oui | G53: =VLOOKUP(RIGHT(E53&F53,255),'Basic Risk Assessment DATASHEET'!$J$3:$K$129,2,FALSE) -> Risque moyen et élevé 1) Informer les membres de la politique concernant le travail des enfants, y compris l’âge à partir duquel les enfants peuvent aider leurs parents, ainsi que l’âge à partir duquel l’embauche directe des enfants dans d’autres exploitations est autorisée pour un travail léger, conformément à la Norme de Rainforest Alliance et à la législation nationale. 2) Désigner des contrôleurs (en nombre suffisant pour garantir un niveau de couverture et une visibilité efficaces dans les exploitations du groupe de producteurs) en vue d’assurer la surveillance permanente de l’application des règles de travail, de sécurité sanitaire et d’assiduité scolaire des enfants et afin de garantir que les inspecteurs, les agriculteurs, les superviseurs des jeunes travailleurs et les travailleurs employés eux-mêmes restent en permanence sensibilisés à la politique du groupe sur le travail des enfants. Risque faible : 1) Informer les membres de la politique concernant le travail des enfants, y compris l’âge à partir duquel les enfants peuvent aider leurs parents, ainsi que l’âge à partir duquel l’embauche directe des enfants dans d’autres exploitations est autorisée pour un travail léger, conformément à la Norme de Rainforest Alliance et à la législation nationale. 2) Expliquer le modèle Évaluation-et-Résolution aux membres pour promouvoir la transparence concernant les risques de travail des enfants et pour apporter des solutions afin d’atténuer le risque.
C54: =VLOOKUP(D54,'Basic Risk Assessment DATASHEET'!A:E,5,FALSE) -> Agences de placement de main-d'œuvre | D54: 26 | E54: =IFERROR(VLOOKUP($B$46&D54&$B$5,'Basic Risk Assessment DATASHEET'!$F$3:$G$129,2,FALSE),$B$128) -> Est-il probable que les membres du groupe utilisent des agences de placement de main-d'œuvre pour recruter les travailleurs ? | F54: Oui | G54: =VLOOKUP(RIGHT(E54&F54,255),'Basic Risk Assessment DATASHEET'!$J$3:$K$129,2,FALSE) -> Risque faible : 1. Rechercher s’il existe un système administratif d’immatriculation ou de délivrance de licence d’agence de placement de main-d'œuvre. Si c’est le cas, informer les membres que toutes les agences de placement dont ils pourraient utiliser les services doivent être titulaires d’un numéro d'immatriculation ou de licence. 2. Indiquer aux membres que tous les frais et commissions de recrutement à payer aux agences de placement sont à leur charge exclusive et en aucun cas à la charge des travailleurs. 3. Indiquer aux membres que les agences de placement qu’ils sollicitent doivent respecter toutes les obligations salariales et contractuelles (5.3) ainsi que toute la réglementation du travail (5.5). Risque moyen et élevé : 1. Mettre en œuvre toutes les mesures d’atténuation « risque faible », de plus : 2. Les membres doivent souscrire des contrats écrits avec toutes les agences de placements auxquelles ils font appel, consigner les numéros d’immatriculation ou de licence, les rémunérations/frais payés par chaque membre à l’agence de placement, l’interdiction d’imputer les charges de recrutement aux travailleurs, l’interdiction des pratiques frauduleuses ou coercitives,et l’obligation de respecter les contraintes 5.3 et 5.5. 3. Contrôler via des inspections internes ou une surveillance évaluation-et- résolution, l’existence de contrats entre les membres et les agences de placement. 4. Contrôler via des inspections internes ou une surveillance évaluation-et- résolution, que les agences de placement ne recourent pas à des méthodes de recrutement frauduleuses ou coercitives.
C55: =VLOOKUP(D55,'Basic Risk Assessment DATASHEET'!A:E,5,FALSE) -> Agences de placement de main-d'œuvre | D55: 27 | E55: =IFERROR(VLOOKUP($B$46&D55&$B$115,'Basic Risk Assessment DATASHEET'!$F$3:$G$129,2,FALSE),$B$128) -> Est-ce que la direction du groupe/exploitation agricole utilise des agences de placement de main-d'œuvre pour recruter des travailleurs ? | F55: Oui | G55: =VLOOKUP(RIGHT(E55&F55,255),'Basic Risk Assessment DATASHEET'!$J$3:$K$129,2,FALSE) -> Risque faible : 1. Rechercher s’il existe un système administratif d’immatriculation ou de délivrance de licence d’agence de placement de main-d'œuvre. Si c’est le cas, toutes les agences de placement doivent être immatriculées ou licenciées et titulaires d’un numéro d'immatriculation ou de licence. 2. Vérifier que l’exploitation ou la direction du groupe paye tous les frais et commissions de recrutement aux agences de placement et que ces dépenses ne sont pas à la charge des travailleurs. 3. Indiquer aux agences de placement qu’elles doivent respecter toutes les obligations salariales et contractuelles (5.3) ainsi que toute la réglementation du travail (5.5) aussi longtemps que les travailleurs sont sous leur responsabilité. Risque moyen et élevé : 1. Mettre en œuvre toutes les mesures d’atténuation « risque faible », de plus : 2. Vérifier auprès des autorités administratives que l’immatriculation ou la licence des agences de placement est toujours valide et qu’elles se conforment à la loi. 3. Souscrire des contrats écrits avec toutes les agences de placements auxquelles ils font appel, consigner les numéros d’immatriculation ou de licence, les rémunérations/frais payés par la direction de l'exploitation ou du groupe à l’agence de placement, l’interdiction d’imputer les charges de recrutement aux travailleurs, l’interdiction des pratiques frauduleuses ou coercitives,et l’obligation de respecter les contraintes 5.3 et 5.5. 4. Contrôler également via une surveillance évaluation-et- résolution, l’existence de contrats avec les agences de placement. 5. En cas de recrutement de travailleurs, avoir instauré un processus permettant en collaboration avec les travailleurs de vérifier les salaires et les conditions de travail promises (ou utilisées frauduleusement) et vérifier si les travailleurs sont endettés au profit des agences de placement. 6. Contrôler, également via une surveillance évaluation-et-résolution, que les agences de placement ne recourent pas à des méthodes de recrutement frauduleuses ou coercitives.
C56: =VLOOKUP(D56,'Basic Risk Assessment DATASHEET'!A:E,5,FALSE) -> Pratiques de paiement des salaires | D56: 28 | E56: =IFERROR(VLOOKUP($B$46&D56&$B$5,'Basic Risk Assessment DATASHEET'!$F$3:$G$129,2,FALSE),$B$128) -> Les membres du groupes rémunèrent-ils les travailleurs à la production/au quota/à la pièce, au moins à certaines époques de l’année ? | F56: Oui | G56: =VLOOKUP(RIGHT(E56&F56,255),'Basic Risk Assessment DATASHEET'!$J$3:$K$129,2,FALSE) -> Risque faible : 1. L’exploitation dispose d’un système de calcul/de garantie qui assure que le salaire des travailleurs payés à la pièce est au moins égal au salaire minimum. Risque moyen et élevé : 1. Les procédures de réclamation ou de questionnement établies par le groupe à propos du calcul de la paye sont communiquées au travailleurs au moment de l’embauche. Cette information doit également les informer sur la disponibilité d’un mécanisme de réclamation. Cette information doit être délivrée dans la (les) langue(s) parlée(s) par les travailleurs.
C57: =VLOOKUP(D57,'Basic Risk Assessment DATASHEET'!A:E,5,FALSE) -> Liberté de mouvement | D57: 29 | E57: =IFERROR(VLOOKUP($B$46&D57&$B$5,'Basic Risk Assessment DATASHEET'!$F$3:$G$129,2,FALSE),$B$128) -> (Ne s'applique pas à ce type de Titulaire de Certificat) | F57: Oui | G57: =VLOOKUP(RIGHT(E57&F57,255),'Basic Risk Assessment DATASHEET'!$J$3:$K$129,2,FALSE) -> #N/A
C58: =VLOOKUP(D58,'Basic Risk Assessment DATASHEET'!A:E,5,FALSE) -> Travail de prisonniers/militaires | D58: 30 | E58: =IFERROR(VLOOKUP($B$46&D58&$B$115,'Basic Risk Assessment DATASHEET'!$F$3:$G$129,2,FALSE),$B$128) -> Y-a-t-il des travailleurs recrutés/fournis à l’exploitation agricole/groupe par le personnel pénitentiaire ou les militaires ? | F58: Oui | G58: =VLOOKUP(RIGHT(E58&F58,255),'Basic Risk Assessment DATASHEET'!$J$3:$K$129,2,FALSE) -> 1. Les officiers militaires mobilisant du personnel militaire pour réaliser du travail agricole est une forme de travail forcé. S’assurer que les exploitations agricoles n’utilisent pas ce type de travail. 2. S’assurer que chaque détenu travaillant sur l’exploitation agricole a librement consenti au travail volontaire. 3. S’assurer que les travailleurs détenus sont traités de la même manière que les autres travailleurs en matière de contrats, de paye, de conditions de travail et de toutes les autres protections des travailleurs indiquées dans la norme de Rainforest Alliance.
C59: =VLOOKUP(D59,'Basic Risk Assessment DATASHEET'!A:E,5,FALSE) -> Dépôt ou rétention de documents | D59: 31 | E59: =IFERROR(VLOOKUP($B$46&D59&$B$115,'Basic Risk Assessment DATASHEET'!$F$3:$G$129,2,FALSE),$B$128) -> Est-ce que les travailleurs fournissent des liquidités (tels que des cautions) ou des documents originaux (tels que les passeports) à la direction de l'exploitation agricole ou aux agences de placement ? | F59: Oui | G59: =VLOOKUP(RIGHT(E59&F59,255),'Basic Risk Assessment DATASHEET'!$J$3:$K$129,2,FALSE) -> 1. S’assurer que les travailleurs ne doivent pas payer de cautions ni fournir des documents personnels originaux à la direction, autres que ceux permettant de confirmer leur identité au moment du recrutement. 2. S’assurer que les travailleurs disposent d’un accès permanent et non restreint aux lieux sûrs où la direction dépose les documents ou d’autres objets personnels confiés volontairement à la direction pour qu'elle les mette en sécurité.
B61: =$G$113 -> Exigence du standard | C61: =$G$114 -> Problème | D61: =$G$115 -> No. de question | E61: =$G$116 -> Question | F61: =$G$117 -> Réponse (sélectionner) | G61: =$G$118 -> Mesure d’atténuation | H61: =$G$119 -> Mesure d'atténuation propre du titulaire de certificat
B62: =VLOOKUP(D62,'Basic Risk Assessment DATASHEET'!A:B,2,FALSE) -> 1.6 Égalité des genres | C62: =VLOOKUP(D62,'Basic Risk Assessment DATASHEET'!A:E,5,FALSE) -> Engagement envers les genres de la part de la direction | D62: 32 | E62: =IFERROR(VLOOKUP($B$62&D62&$B$115,'Basic Risk Assessment DATASHEET'!$F$3:$G$129,2,FALSE),$B$128) -> Est-ce que la direction de l'exploitation agricole/du groupe a déjà pris des mesures pour résoudre le problème de l’autonomisation des femmes et/ou des genres depuis plus d'un an au moins ? | F62: Oui | G62: =VLOOKUP(RIGHT(E62&F62,250),'Basic Risk Assessment DATASHEET'!$J$3:$K$129,2,FALSE) -> Continuer les actions
C63: =VLOOKUP(D63,'Basic Risk Assessment DATASHEET'!A:E,5,FALSE) -> Représentation des femmes dans le groupe | D63: 33 | E63: =IFERROR(VLOOKUP($B$62&D63&$B$5,'Basic Risk Assessment DATASHEET'!$F$3:$G$129,2,FALSE),$B$128) -> Est-ce que les membres femmes représentent au moins 25% du nombre total des membres du groupe ? | F63: Oui | G63: =VLOOKUP(RIGHT(E63&F63,250),'Basic Risk Assessment DATASHEET'!$J$3:$K$129,2,FALSE) -> Pas d’action supplémentaire requise
C64: =VLOOKUP(D64,'Basic Risk Assessment DATASHEET'!A:E,5,FALSE) -> Représentation dans les fonctions de niveau plus élevé | D64: 34 | E64: =IFERROR(VLOOKUP($B$62&D64&$B$115,'Basic Risk Assessment DATASHEET'!$F$3:$G$129,2,FALSE),$B$128) -> Est-ce que les femmes sont actuellement représentées de manière égale (par rapport au % total de membres femmes ou de travailleuses) parmi les formateurs, les superviseurs, le personnel de la direction et/ou les autres fonctions de haut niveau au sein de la direction du groupe ou de l'exploitation agricole ? | F64: Non/Ne sais pas | G64: =VLOOKUP(RIGHT(E64&F64,255),'Basic Risk Assessment DATASHEET'!$J$3:$K$129,2,FALSE) -> 1) Tenir un registre de tous les postes par genre et par type de poste. 2) Établir un quota minimum de formateurs femmes, de superviseurs femmes, de personnel femme de la direction et des femmes aux autres fonctions de haut niveau. (Pour les groupes ou les exploitations agricoles avec plus de 50% de membres femmes ou travailleuses, la représentation des femmes doit être d’au moins 50%, mais n’a pas besoin d’être supérieure à 50%). 3) Organiser une formation ciblée sur les agricultrices ou les travailleuses qui est nécessaire pour être éligible en tant que formateur, superviseur ou autre fonction de haut niveau. 4) S’assurer que les annonces d’emplois atteignent les agriculteurs ET les agricultrices et les travailleurs ET les travailleuses et que les exigences des postes sont réalisables par les agricultrices et les travailleuses. 5) Donner une formation au personnel de la direction impliqué dans le recrutement sur les biais inconscients et les méthodologies pour prévenir les pratiques de discrimination basées sur les genres.
C65: =VLOOKUP(D65,'Basic Risk Assessment DATASHEET'!A:E,5,FALSE) -> Participation des agricultrices aux formations | D65: 35 | E65: =IFERROR(VLOOKUP($B$62&D65&$B$115,'Basic Risk Assessment DATASHEET'!$F$3:$G$129,2,FALSE),$B$128) -> Est-ce que les membres femmes du groupe/travailleuses participent actuellement de manière égale aux formations (comparé au % total de membres femmes ou de travailleuses) ? | F65: Non | G65: =VLOOKUP(RIGHT(E65&F65,250),'Basic Risk Assessment DATASHEET'!$J$3:$K$129,2,FALSE) -> 1) Tenir des registres sur les participants aux formations par genre. 2) Voir avec les travailleuses et les membres femmes quels sont les obstacles potentiels à leur participation aux formations. 3) Conduire des formations à des jours/heures/lieux où les femmes peuvent facilement être présentes et envoyer des invitations personnelles.
C66: =VLOOKUP(D66,'Basic Risk Assessment DATASHEET'!A:E,5,FALSE) -> Participation des agricultrices aux formations | D66: 36 | E66: =IFERROR(VLOOKUP($B$62&D66&$B$5,'Basic Risk Assessment DATASHEET'!$F$3:$G$129,2,FALSE),$B$128) -> Est-ce habituel que les épouses des membres hommes ou d’autres travailleuses de la famille participent aux activités de formation ? | F66: Non | G66: =VLOOKUP(RIGHT(E66&F66,250),'Basic Risk Assessment DATASHEET'!$J$3:$K$129,2,FALSE) -> 1) Inviter les épouses des membres hommes et/ou les autres travailleuses de la famille aux formations. 2) Expliquer aux membres hommes durant les réunions l’importance de la participation de leurs épouses et/ou des autres travailleuses de la famille aux formations.
B69: =$G$113 -> Exigence du standard | C69: =$G$114 -> Problème | D69: =$G$115 -> No. de question | E69: =$G$116 -> Question | F69: =$G$117 -> Réponse (sélectionner) | G69: =$G$118 -> Mesure d’atténuation | H69: =$G$119 -> Mesure d'atténuation propre du titulaire de certificat
B70: =VLOOKUP(D70,'Basic Risk Assessment DATASHEET'!A:B,2,FALSE) -> 5.7 Conditions de vie et de logement | C70: =VLOOKUP(D70,'Basic Risk Assessment DATASHEET'!A:E,5,FALSE) -> Les travailleurs et leurs familles vivent sur site | D70: 37 | E70: =IFERROR(VLOOKUP($B$70&D70&$B$5,'Basic Risk Assessment DATASHEET'!$F$3:$G$129,2,FALSE),$B$128) -> (Ne s'applique pas à ce type de Titulaire de Certificat) | F70: Oui | G70: =VLOOKUP(RIGHT(E70&F70,250),'Basic Risk Assessment DATASHEET'!$J$3:$K$129,2,FALSE) -> #N/A
B73: =H115 -> Environnement
B75: =$G$113 -> Exigence du standard | C75: =$G$114 -> Problème | D75: =$G$115 -> No. de question | E75: =$G$116 -> Question | F75: =$G$117 -> Réponse (sélectionner) | G75: =$G$118 -> Mesure d’atténuation | H75: =$G$119 -> Mesure d'atténuation propre du titulaire de certificat
B76: =VLOOKUP(D76,'Basic Risk Assessment DATASHEET'!A:B,2,FALSE) -> 6.1.3 / 6.1.4 Évaluation des HVC | C76: =VLOOKUP(D76,'Basic Risk Assessment DATASHEET'!A:E,5,FALSE) -> EHVC | D76: 38 | E76: =IFERROR(VLOOKUP($B$76&D76&$B$115,'Basic Risk Assessment DATASHEET'!$F$3:$G$129,2,FALSE),$B$128) -> L’exploitation agricole est-elle implantée à moins de 5 km d’une zone forestière naturelle intacte ? | F76: Non | G76: =VLOOKUP(RIGHT(E76&F76,250),'Basic Risk Assessment DATASHEET'!$J$3:$K$129,2,FALSE) -> Pas d’action supplémentaire requise
C77: =VLOOKUP(D77,'Basic Risk Assessment DATASHEET'!A:E,5,FALSE) -> EHVC | D77: 39 | E77: =IFERROR(VLOOKUP($B$76&D77&$B$115,'Basic Risk Assessment DATASHEET'!$F$3:$G$129,2,FALSE),$B$128) -> L’exploitation agricole ou le groupe d'exploitations agricoles est-il implanté à moins de 2 km d'une Aire protégée (AP) enregistrée, d'une aire sensible de biodiversité (ASB), d'un site Ramsar ou d'un site inscrit au Patrimoine mondial de l’UNESCO ? | F77: Oui | G77: =VLOOKUP(RIGHT(E77&F77,255),'Basic Risk Assessment DATASHEET'!$J$3:$K$129,2,FALSE) -> S’assurer que les attributs majeurs de conservation de la zone ne sont pas menacés, c’est-à-dire les valeurs pour lesquelles la zone a été protégée ou classée en AP, en ZIB ou en site Ramsar.
C78: =VLOOKUP(D78,'Basic Risk Assessment DATASHEET'!A:E,5,FALSE) -> EHVC | D78: 40 | E78: =IFERROR(VLOOKUP($B$76&D78&$B$115,'Basic Risk Assessment DATASHEET'!$F$3:$G$129,2,FALSE),$B$128) -> Est-ce que les communautés locales ont des droits coutumiers ou légaux sur l’exploitation agricole ? | F78: Oui | G78: =VLOOKUP(RIGHT(E78&F78,250),'Basic Risk Assessment DATASHEET'!$J$3:$K$129,2,FALSE) -> a) Cartographier les utilisations des terres des communautés locales sur l’exploitation agricole d'une manière inclusive et participative avec les communautés affectées ; b) Identifier et atténuer tous les impacts directs et indirects des activités agricoles sur ces ressources ou sur les habitats qui abritent ces ressources ; c) Formaliser des accords (étendus) avec les communautés sur l’utilisation et la gestion de telles zones en utilisant les principes du Consentement Préalable, donné Librement et en Connaissance de Cause et documenter le processus (exigence 5.8.1).
C79: =VLOOKUP(D79,'Basic Risk Assessment DATASHEET'!A:E,5,FALSE) -> EHVC | D79: 41 | E79: =IFERROR(VLOOKUP($B$76&D79&$B$115,'Basic Risk Assessment DATASHEET'!$F$3:$G$129,2,FALSE),$B$128) -> Est-ce que vous utilisez des terres communales pour des raisons liées à la production ou à la transformation de culture certifiée, ex : la collecte du bois ? | F79: Non | G79: =VLOOKUP(RIGHT(E79&F79,250),'Basic Risk Assessment DATASHEET'!$J$3:$K$129,2,FALSE) -> Pas d’action supplémentaire requise
C80: =VLOOKUP(D80,'Basic Risk Assessment DATASHEET'!A:E,5,FALSE) -> EHVC | D80: 42 | E80: =IFERROR(VLOOKUP($B$76&D80&$B$5,'Basic Risk Assessment DATASHEET'!$F$3:$G$129,2,FALSE),$B$128) -> (Ne s'applique pas à ce type de Titulaire de Certificat) | F80: Oui | G80: =VLOOKUP(RIGHT(E80&F80,250),'Basic Risk Assessment DATASHEET'!$J$3:$K$129,2,FALSE) -> #N/A
B82: =$G$113 -> Exigence du standard | C82: =$G$114 -> Problème | D82: =$G$115 -> No. de question | E82: =$G$116 -> Question | F82: =$G$117 -> Réponse (sélectionner) | G82: =$G$118 -> Mesure d’atténuation | H82: =$G$119 -> Mesure d'atténuation propre du titulaire de certificat
B83: =VLOOKUP(D83,'Basic Risk Assessment DATASHEET'!A:B,2,FALSE) -> 6.2 Conservation et amélioration de la végétation et des écosystèmes naturels | C83: =VLOOKUP(D83,'Basic Risk Assessment DATASHEET'!A:E,5,FALSE) -> Connectivité des écosystèmes | D83: 43 | E83: =IFERROR(VLOOKUP($B$83&D83&$B$5,'Basic Risk Assessment DATASHEET'!$F$3:$G$129,2,FALSE),$B$128) -> Est-ce que les zones d’écosystème naturel et de couvert de végétation naturelle sont connectées par des corridors de territoires ? | F83: Oui | G83: =VLOOKUP(RIGHT(E83&F83,255),'Basic Risk Assessment DATASHEET'!$J$3:$K$129,2,FALSE) -> Pas d’action supplémentaire requise
C84: =VLOOKUP(D84,'Basic Risk Assessment DATASHEET'!A:E,5,FALSE) -> Végétation naturelle | D84: 44 | E84: =IFERROR(VLOOKUP($B$83&D84&$B$115,'Basic Risk Assessment DATASHEET'!$F$3:$G$129,2,FALSE),$B$128) -> Prévoyez-vous que tous les écosystèmes naturels de l’exploitation agricole, dont les haies, les limites forestières, les zones tampons ripariennes et les forêts, aient une diversité en espèces et contiennent en majorité des espèces adaptées localement ? | F84: Non/Ne sais pas | G84: =VLOOKUP(RIGHT(E84&F84,255),'Basic Risk Assessment DATASHEET'!$J$3:$K$129,2,FALSE) -> Investiguer si tous les écosystèmes naturels sur l’exploitation agricole, dont les haies, les limites forestières, les zones tampons ripariennes et les forêts, contiennent de la végétation adaptée localement. Dans le cas contraire, identifier les espèces appropriées qui peuvent être plantées pour augmenter la proportion de végétation naturelle dans les écosystèmes naturels sur l’exploitation agricole, dont les forêts, les zones ripariennes tampons, les haies et les limites forestières.
C85: =VLOOKUP(D85,'Basic Risk Assessment DATASHEET'!A:E,5,FALSE) -> Forêts | D85: 45 | E85: =IFERROR(VLOOKUP($B$83&D85&$B$115,'Basic Risk Assessment DATASHEET'!$F$3:$G$129,2,FALSE),$B$128) -> Est-ce que la forêt ressemble à une forêt naturelle en matière de couvert de canopée, de strates forestières et de présence de lianes et de plantes grimpantes ? Pour plus d'informations, voir le document intitulé Document d’orientation M : Document d’orientation végétation indigène et écosystèmes naturels. | F85: Non | G85: =VLOOKUP(RIGHT(E85&F85,255),'Basic Risk Assessment DATASHEET'!$J$3:$K$129,2,FALSE) -> Planifier la gestion du couvert de canopée, des strates forestières et de la présence de lianes et de plantes grimpantes (ex : en créant des ouvertures, en plantant des espèces supplémentaires et en restreignant les prélèvements ou le pâturage si nécessaire) afin de faciliter la régénération et la croissance de la forêt naturelle. Pour plus de détails, voir le document intitulé Document d’orientation M : Document d’orientation végétation indigène et écosystèmes naturels sur les exploitations agricoles.
C86: =VLOOKUP(D86,'Basic Risk Assessment DATASHEET'!A:E,5,FALSE) -> Cours d’eau, étendues d’eau et zones humides | D86: 46 | E86: =IFERROR(VLOOKUP($B$83&D86&$B$115,'Basic Risk Assessment DATASHEET'!$F$3:$G$129,2,FALSE),$B$128) -> Répondre uniquement si vous avez des zones humides au sein du groupe/exploitation agricole -- Est-ce que les zones humides stockent ou acheminent les eaux d'inondation à n’importe quel moment de l’année ? | F86: Oui | G86: =VLOOKUP(RIGHT(E86&F86,255),'Basic Risk Assessment DATASHEET'!$J$3:$K$129,2,FALSE) -> Planifier la délimitation et la gestion des zones humides et des plaines d'inondation actives et s’assurer que les activités de transformation ou de production n’empiètent pas sur les plaines d'inondation.
C87: =VLOOKUP(D87,'Basic Risk Assessment DATASHEET'!A:E,5,FALSE) -> Prairies, pâturage et désert non naturel | D87: 47 | E87: =IFERROR(VLOOKUP($B$83&D87&$B$115,'Basic Risk Assessment DATASHEET'!$F$3:$G$129,2,FALSE),$B$128) -> Répondre uniquement si vous avez des prairies/pâturages ou des déserts non naturels au sein du groupe/exploitation agricole -- Est-ce que les prairies/pâturages ou les zones de désert non naturel contiennent de vastes zones à nu qui sont en danger d’érosion au sein des cours d’eau proches ? | F87: Oui | G87: =VLOOKUP(RIGHT(E87&F87,255),'Basic Risk Assessment DATASHEET'!$J$3:$K$129,2,FALSE) -> Planter du couvert terrestre autochtone supplémentaire (herbes, arbustes, arbres) et mettre en œuvre des mesures pour protéger contre l’érosion.
C88: =VLOOKUP(D88,'Basic Risk Assessment DATASHEET'!A:E,5,FALSE) -> Jachère | D88: 48 | E88: =IFERROR(VLOOKUP($B$83&D88&$B$115,'Basic Risk Assessment DATASHEET'!$F$3:$G$129,2,FALSE),$B$128) -> Répondre uniquement si vous avez des terres en jachère au sein du groupe/exploitation agricole -- Est-ce que les arbres se régénèrent naturellement sur les terre en jachère permanente ? | F88: Oui | G88: =VLOOKUP(RIGHT(E88&F88,255),'Basic Risk Assessment DATASHEET'!$J$3:$K$129,2,FALSE) -> Pas d’action supplémentaire requise
B90: =$G$113 -> Exigence du standard | C90: =$G$114 -> Problème | D90: =$G$115 -> No. de question | E90: =$G$116 -> Question | F90: =$G$117 -> Réponse (sélectionner) | G90: =$G$118 -> Mesure d’atténuation | H90: =$G$119 -> Mesure d'atténuation propre du titulaire de certificat
B91: =VLOOKUP(D91,'Basic Risk Assessment DATASHEET'!A:B,2,FALSE) -> Changement climatique | C91: =VLOOKUP(D91,'Basic Risk Assessment DATASHEET'!A:E,5,FALSE) -> Risques du changement climatique | D91: 49 | E91: =IFERROR(VLOOKUP($B$91&D91&$B$115,'Basic Risk Assessment DATASHEET'!$F$3:$G$129,2,FALSE),$B$128) -> Est-ce que la direction, les superviseurs et/ou le personnel technique sont formés à l’évaluation des risques et des impacts infligés par le changement climatique sur les moyens de subsistance et sur les systèmes de production ? | F91: Non | G91: =VLOOKUP(RIGHT(E91&F91,250),'Basic Risk Assessment DATASHEET'!$J$3:$K$129,2,FALSE) -> Formation/sensibilisation sur les risques du changement climatique et de leurs impacts sur les systèmes de production agricole et sur les moyens de subsistance plus largement.
C92: =VLOOKUP(D92,'Basic Risk Assessment DATASHEET'!A:E,5,FALSE) -> Risques du changement climatique | D92: 50 | E92: =IFERROR(VLOOKUP($B$91&D92&$B$115,'Basic Risk Assessment DATASHEET'!$F$3:$G$129,2,FALSE),$B$128) -> Est-ce que la direction, les superviseurs et/ou le personnel technique ont identifiés les menaces /risques/impacts (actuels et prévus) les plus significatifs du changement climatique sur les ressources en moyens de subsistance et sur les systèmes agricoles ? | F92: Non | G92: =VLOOKUP(RIGHT(E92&F92,255),'Basic Risk Assessment DATASHEET'!$J$3:$K$129,2,FALSE) -> Réaliser l’évaluation Rainforest Alliance des risques liés au changement climatique pour identifier et décrire les risques les plus significatifs de changement climatique basés sur l'outil Rainforest Alliance d’évaluation des risques de changement climatique.
